Workbook

Sheet C.Pagar
A1: =SUBTOTAL(2,Tabela1[NF]) -> 536 | F1: 991587.1 | G1: =SUBTOTAL(9,Tabela1[VALOR]) -> 7986006 | J1: Check NF = Descobri pelo DDA
A2: NF | B2: DT. VENCIMENTO | C2: TIPO | D2: CLASSIFICAÇÃO | E2: DESCRIÇÃO | F2: FORNECEDOR | G2: VALOR | H2: PARC. | I2: # | J2: OBSERVAÇÕES | K2: DT. PAGAMENTO | L2: Valor original | M2: Juros | P2: RESUMO
A3: 14872 | B3: 45887 | C3: Váriavel | F3: Advance Comercio de Bicicletas e Motos Eireli | G3: 1439.8 | H3: 1*3 | I3: =COUNTIF(Tabela1[NF],Tabela1[[#This Row],[NF]]) -> 3 | K3: 45887 | P3: COMISSÕES E TAXAS DOS MARKETPLACES
A4: 442577 | B4: 45903 | C4: Váriavel | D4: Peças | F4: ISAPA IMPORTAÇÃO E COMERCIO LTDA | G4: 20895.3 | H4: 1*1 | I4: =COUNTIF(Tabela1[NF],Tabela1[[#This Row],[NF]]) -> 1 | K4: =Tabela1[[#This Row],[DT. VENCIMENTO]] -> 45903 | N4: {=_xlfn.XLOOKUP(TRIM(D4),TRIM(DFC!A:A),DFC!A:A,"NÃO ESTÁ NA DFC")} -> PEÇAS | P4: Consultorias
A5: 442590 | B5: 45903 | C5: Váriavel | D5: Peças | F5: ISAPA IMPORTAÇÃO E COMERCIO LTDA | G5: 11070.67 | H5: 1*1 | I5: =COUNTIF(Tabela1[NF],Tabela1[[#This Row],[NF]]) -> 1 | K5: =Tabela1[[#This Row],[DT. VENCIMENTO]] -> 45903 | N5: {=_xlfn.XLOOKUP(TRIM(D5),TRIM(DFC!A:A),DFC!A:A,"NÃO ESTÁ NA DFC")} -> PEÇAS | P5: Contabilidade
A6: 436412 | B6: 45905 | C6: Váriavel | D6: Peças | F6: LIQUIDACAO BOLETO 61327045000160 ISAPA IMPE COML | G6: 5160.11 | H6: 2*5 | I6: =COUNTIF(Tabela1[NF],Tabela1[[#This Row],[NF]]) -> 5 | K6: 45936 | P6: Emabalagens
A7: 436358 | B7: 45905 | C7: Váriavel | D7: Peças | F7: LIQUIDACAO BOLETO 61327045000160 ISAPA IMPE COML | G7: 6117.9 | I7: =COUNTIF(Tabela1[NF],Tabela1[[#This Row],[NF]]) -> 5 | K7: =B7 -> 45905 | P7: ERP
A8: 436424 | B8: 45905 | C8: Váriavel | D8: Peças | F8: LIQUIDACAO BOLETO 61327045000160 ISAPA IMPE COML | G8: 2959.38 | I8: =COUNTIF(Tabela1[NF],Tabela1[[#This Row],[NF]]) -> 4 | K8: =Tabela1[[#This Row],[DT. VENCIMENTO]] -> 45905 | P8: Ferramentas para manutenção
A9: 436345 | B9: 45905 | C9: Váriavel | D9: Peças | F9: LIQUIDACAO BOLETO 61327045000160 ISAPA IMPE COML | G9: 51965.5 | I9: =COUNTIF(Tabela1[NF],Tabela1[[#This Row],[NF]]) -> 6 | K9: =B9 -> 45905 | P9: Frete de Saída
A10: 436655 | B10: 45906 | C10: Váriavel | D10: Peças | F10: LIQUIDACAO BOLETO 61327045000160 ISAPA INC COM L | G10: 29413.88 | I10: =COUNTIF(Tabela1[NF],Tabela1[[#This Row],[NF]]) -> 5 | K10: =Tabela1[[#This Row],[DT. VENCIMENTO]] -> 45906 | P10: Gran Residence
A11: 8043 | B11: 45908 | C11: Váriavel | F11: TWR Industria e Comercio LTDA | G11: 60502.11 | H11: 1*1 | I11: =COUNTIF(Tabela1[NF],Tabela1[[#This Row],[NF]]) -> 1 | J11: Pagamento à vista. | K11: =Tabela1[[#This Row],[DT. VENCIMENTO]] -> 45908 | P11: Internet
A12: 438008 | B12: 45912 | C12: Váriavel | D12: Peças | F12: LIQUIDACAO BOLETO 61327045000160 ISAPA IMPE COML | G12: 2850.82 | I12: =COUNTIF(Tabela1[NF],Tabela1[[#This Row],[NF]]) -> 4 | K12: =Tabela1[[#This Row],[DT. VENCIMENTO]] -> 45912 | P12: Marcas e patentes
A13: 14872 | B13: 45915 | C13: Váriavel | F13: Advance Comercio de Bicicletas e Motos Eireli | G13: 1439.8 | H13: 2*3 | I13: =COUNTIF(Tabela1[NF],Tabela1[[#This Row],[NF]]) -> 3 | K13: =Tabela1[[#This Row],[DT. VENCIMENTO]] -> 45915 | P13: Material de Escritório
A14: 8761 | B14: 45917 | C14: Váriavel | F14: Arosul Ind Comercio de Peças Eireli | G14: 563.55 | H14: 1*3 | I14: =COUNTIF(Tabela1[NF],Tabela1[[#This Row],[NF]]) -> 2 | K14: =Tabela1[[#This Row],[DT. VENCIMENTO]] -> 45917 | P14: Peças
A15: 69985 | B15: 45917 | C15: Váriavel | F15: MOLIANI E GERALDINI | G15: 697.71 | H15: 1*1 | I15: =COUNTIF(Tabela1[NF],Tabela1[[#This Row],[NF]]) -> 1 | K15: =Tabela1[[#This Row],[DT. VENCIMENTO]] -> 45917 | P15: Serviço Terceirizado
A16: 438751 | B16: 45917 | C16: Váriavel | D16: Peças | F16: LIQUIDACAO BOLETO 61327045000160 ISAPA IMPE COML | G16: 1139.28 | I16: =COUNTIF(Tabela1[NF],Tabela1[[#This Row],[NF]]) -> 4 | K16: =B16 -> 45917 | P16: T.I
A17: 12943 | B17: 45918 | C17: Váriavel | F17: THOR INDUSTRIAL LTDA | G17: 1600.32 | H17: 1*3 | I17: =COUNTIF(Tabela1[NF],Tabela1[[#This Row],[NF]]) -> 2 | K17: =Tabela1[[#This Row],[DT. VENCIMENTO]] -> 45918 | P17: Trabalhista
A18: 45901 | B18: 45920 | C18: Fixo | F18: FOLHA DE PAGAMENTO | G18: 9679.49 | H18: 1*1 | I18: =COUNTIF(Tabela1[NF],Tabela1[[#This Row],[NF]]) -> 9 | J18: Adiantamento (VALE) | K18: =Tabela1[[#This Row],[DT. VENCIMENTO]] -> 45920 | P18: 13 SALARIO
A19: 221024 | B19: 45921 | C19: Váriavel | F19: OX DA AMAZONIA IND. DE BICICLETAS S.A | G19: 2211.65 | H19: 1*6 | I19: =COUNTIF(Tabela1[NF],Tabela1[[#This Row],[NF]]) -> 2 | K19: =Tabela1[[#This Row],[DT. VENCIMENTO]] -> 45921 | P19: Acordo Judicial
A20: 1278 | B20: 45922 | C20: Váriavel | F20: Wester Bike Industria e Comercio LTDA | G20: 523.18 | H20: 1*2 | I20: =COUNTIF(Tabela1[NF],Tabela1[[#This Row],[NF]]) -> 2 | K20: =Tabela1[[#This Row],[DT. VENCIMENTO]] -> 45922 | P20: Adiantamento Salarial
A21: 3568 | B21: 45924 | C21: Váriavel | F21: SAAR ADESIVOS | G21: 6996.9 | H21: 1*5 | I21: =COUNTIF(Tabela1[NF],Tabela1[[#This Row],[NF]]) -> 3 | J21: N.C.K - INDUSTRIAL | K21: =Tabela1[[#This Row],[DT. VENCIMENTO]] -> 45924 | P21: Alimentação
A22: 7341 | B22: 45925 | C22: Váriavel | F22: FLAY INDUSTRIA E COMERCIO LTDA | G22: 281.52 | H22: 3*3 | I22: =COUNTIF(Tabela1[NF],Tabela1[[#This Row],[NF]]) -> 1 | K22: =Tabela1[[#This Row],[DT. VENCIMENTO]] -> 45925 | P22: Aluguel
A23: 120785 | B23: 45925 | C23: Váriavel | F23: Kalf Ind Com Plasticos LTDA | G23: 1908.61 | H23: 2*2 | I23: =COUNTIF(Tabela1[NF],Tabela1[[#This Row],[NF]]) -> 1 | K23: =Tabela1[[#This Row],[DT. VENCIMENTO]] -> 45925 | P23: Alvará
A24: 162321 | B24: 45925 | C24: Váriavel | F24: BRAS ONDA PAPELÃO ONDULADO LTDA | G24: 3311.57 | H24: 3*3 | I24: =COUNTIF(Tabela1[NF],Tabela1[[#This Row],[NF]]) -> 1 | K24: =Tabela1[[#This Row],[DT. VENCIMENTO]] -> 45925 | P24: Amortização Felipe
A25: 7881 | B25: 45926 | C25: Váriavel | F25: FLAY INDUSTRIA E COMERCIO LTDA | G25: 269.16 | H25: 1*3 | I25: =COUNTIF(Tabela1[NF],Tabela1[[#This Row],[NF]]) -> 2 | K25: =Tabela1[[#This Row],[DT. VENCIMENTO]] -> 45926 | P25: anymarket mensalidade
A26: 7921 | B26: 45926 | C26: Váriavel | F26: FLAY INDUSTRIA E COMERCIO LTDA | G26: 7134.45 | H26: 1*3 | I26: =COUNTIF(Tabela1[NF],Tabela1[[#This Row],[NF]]) -> 2 | K26: =Tabela1[[#This Row],[DT. VENCIMENTO]] -> 45926 | N26: {=_xlfn.XLOOKUP(TRIM(D26),TRIM(DFC!A:A),DFC!A:A,"NÃO ESTÁ NA DFC")} -> 0 | P26: anymarket taxas
A27: 2879 | B27: 45927 | C27: Váriavel | F27: AD Flex Etiquetas Eireli | G27: 440 | H27: 1*1 | I27: =COUNTIF(Tabela1[NF],Tabela1[[#This Row],[NF]]) -> 1 | K27: 45929 | N27: {=_xlfn.XLOOKUP(TRIM(D27),TRIM(DFC!A:A),DFC!A:A,"NÃO ESTÁ NA DFC")} -> 0 | P27: CFR
A28: 143402 | B28: 45927 | C28: Váriavel | F28: JULIO ANDÓ | G28: 2555.63 | H28: 4*4 | I28: =COUNTIF(Tabela1[NF],Tabela1[[#This Row],[NF]]) -> 1 | K28: 45929 | P28: Combustível
A29: 155144 | B29: 45927 | C29: Váriavel | F29: JULIO ANDÓ | G29: 8542.83 | H29: 1*1 | I29: =COUNTIF(Tabela1[NF],Tabela1[[#This Row],[NF]]) -> 1 | K29: 45929 | P29: COMISSÕES E TAXAS DOS MARKETPLACES
A30: 1928 | B30: 45928 | C30: Váriavel | F30: GUIDON BIKE PEÇAS PARA BICICLETAS IND E COM EIRELI | G30: 1180.64 | H30: 3*3 | I30: =COUNTIF(Tabela1[NF],Tabela1[[#This Row],[NF]]) -> 1 | K30: 45929 | P30: Compra de máquina
A31: 7266 | B31: 45928 | C31: Váriavel | F31: GUIDON BIKE PEÇAS PARA BICICLETAS IND E COM EIRELI | G31: 505.99 | H31: 3*3 | I31: =COUNTIF(Tabela1[NF],Tabela1[[#This Row],[NF]]) -> 1 | K31: 45929 | P31: Compra de Móveis e Utensílios
A32: 152744 | B32: 45928 | C32: Váriavel | F32: JULIO ANDÓ | G32: 1616.98 | H32: 1*5 | I32: =COUNTIF(Tabela1[NF],Tabela1[[#This Row],[NF]]) -> 2 | K32: 45929 | N32: {=_xlfn.XLOOKUP(TRIM(D32),TRIM(DFC!A:A),DFC!A:A,"NÃO ESTÁ NA DFC")} -> 0 | P32: Confraternização
A33: 614512 | B33: 45928 | C33: Váriavel | D33: Peças | F33: ISAPA IMPORTAÇÃO E COMERCIO LTDA | G33: 3359.95 | H33: 1*5 | I33: =COUNTIF(Tabela1[NF],Tabela1[[#This Row],[NF]]) -> 5 | K33: 45929 | N33: {=_xlfn.XLOOKUP(TRIM(D33),TRIM(DFC!A:A),DFC!A:A,"NÃO ESTÁ NA DFC")} -> PEÇAS | P33: Copel
A34: 614562 | B34: 45928 | C34: Váriavel | D34: Peças | F34: ISAPA IMPORTAÇÃO E COMERCIO LTDA | G34: 2768.5 | H34: 1*5 | I34: =COUNTIF(Tabela1[NF],Tabela1[[#This Row],[NF]]) -> 5 | K34: 45929 | N34: {=_xlfn.XLOOKUP(TRIM(D34),TRIM(DFC!A:A),DFC!A:A,"NÃO ESTÁ NA DFC")} -> PEÇAS | P34: Desp de Marketing e Propaganda
A35: 3974 | B35: 45929 | C35: Váriavel | F35: FLAY INDUSTRIA E COMERCIO LTDA | G35: 9001.622 | H35: 1*3 | I35: =COUNTIF(Tabela1[NF],Tabela1[[#This Row],[NF]]) -> 2 | K35: 45929 | N35: {=_xlfn.XLOOKUP(TRIM(D35),TRIM(DFC!A:A),DFC!A:A,"NÃO ESTÁ NA DFC")} -> 0 | P35: Detran
A36: 7373 | B36: 45929 | C36: Váriavel | F36: FLAY INDUSTRIA E COMERCIO LTDA | G36: 3793.65 | H36: 3*3 | I36: =COUNTIF(Tabela1[NF],Tabela1[[#This Row],[NF]]) -> 1 | K36: 45929 | N36: {=_xlfn.XLOOKUP(TRIM(D36),TRIM(DFC!A:A),DFC!A:A,"NÃO ESTÁ NA DFC")} -> 0 | P36: Diária
A37: 7374 | B37: 45929 | C37: Váriavel | F37: FLAY INDUSTRIA E COMERCIO LTDA | G37: 281.52 | H37: 3*3 | I37: =COUNTIF(Tabela1[NF],Tabela1[[#This Row],[NF]]) -> 1 | K37: 45929 | N37: {=_xlfn.XLOOKUP(TRIM(D37),TRIM(DFC!A:A),DFC!A:A,"NÃO ESTÁ NA DFC")} -> 0 | P37: Diárias
A38: 7614 | B38: 45929 | C38: Váriavel | F38: FLAY INDUSTRIA E COMERCIO LTDA | G38: 563.04 | H38: 2*3 | I38: =COUNTIF(Tabela1[NF],Tabela1[[#This Row],[NF]]) -> 2 | K38: 45929 | N38: {=_xlfn.XLOOKUP(TRIM(D38),TRIM(DFC!A:A),DFC!A:A,"NÃO ESTÁ NA DFC")} -> 0 | P38: Empilhadeira
A39: 7976 | B39: 45929 | C39: Váriavel | F39: FLAY INDUSTRIA E COMERCIO LTDA | G39: 9001.62 | H39: 1*3 | I39: =COUNTIF(Tabela1[NF],Tabela1[[#This Row],[NF]]) -> 1 | J39: Checar NF | K39: 45929 | N39: {=_xlfn.XLOOKUP(TRIM(D39),TRIM(DFC!A:A),DFC!A:A,"NÃO ESTÁ NA DFC")} -> 0 | P39: Equipamentos de Informática
A40: 121102 | B40: 45929 | C40: Váriavel | F40: Kalf Ind Com Plasticos LTDA | G40: 2403.44 | H40: 1*2 | I40: =COUNTIF(Tabela1[NF],Tabela1[[#This Row],[NF]]) -> 2 | K40: 45929 | N40: {=_xlfn.XLOOKUP(TRIM(D40),TRIM(DFC!A:A),DFC!A:A,"NÃO ESTÁ NA DFC")} -> 0 | P40: FGTS
A41: 146651 | B41: 45929 | C41: Váriavel | F41: JULIO ANDÓ | G41: 942.41 | H41: 3*4 | I41: =COUNTIF(Tabela1[NF],Tabela1[[#This Row],[NF]]) -> 2 | K41: 45929 | N41: {=_xlfn.XLOOKUP(TRIM(D41),TRIM(DFC!A:A),DFC!A:A,"NÃO ESTÁ NA DFC")} -> 0 | P41: Frete de Entrada
A42: 146673 | B42: 45929 | C42: Váriavel | F42: JULIO ANDÓ | G42: 6338.6 | H42: 3*4 | I42: =COUNTIF(Tabela1[NF],Tabela1[[#This Row],[NF]]) -> 2 | K42: 45929 | N42: {=_xlfn.XLOOKUP(TRIM(D42),TRIM(DFC!A:A),DFC!A:A,"NÃO ESTÁ NA DFC")} -> 0 | P42: Fundo Penitenciário
A43: 155429 | B43: 45929 | C43: Váriavel | F43: JULIO ANDÓ | G43: 9236.49 | H43: 1*1 | I43: =COUNTIF(Tabela1[NF],Tabela1[[#This Row],[NF]]) -> 1 | K43: 45929 | N43: {=_xlfn.XLOOKUP(TRIM(D43),TRIM(DFC!A:A),DFC!A:A,"NÃO ESTÁ NA DFC")} -> 0 | P43: Honorários Advogáticios
A44: 429843 | B44: 45929 | C44: Váriavel | D44: Peças | F44: ISAPA IMPORTAÇÃO E COMERCIO LTDA | G44: 14450 | H44: 3*4 | I44: =COUNTIF(Tabela1[NF],Tabela1[[#This Row],[NF]]) -> 2 | K44: 45929 | N44: {=_xlfn.XLOOKUP(TRIM(D44),TRIM(DFC!A:A),DFC!A:A,"NÃO ESTÁ NA DFC")} -> PEÇAS | P44: Impostos e Taxas
A45: 7627 | B45: 45930 | C45: Váriavel | F45: FLAY INDUSTRIA E COMERCIO LTDA | G45: 140.76 | H45: 2*3 | I45: =COUNTIF(Tabela1[NF],Tabela1[[#This Row],[NF]]) -> 2 | K45: =Tabela1[[#This Row],[DT. VENCIMENTO]] -> 45930 | N45: {=_xlfn.XLOOKUP(TRIM(D45),TRIM(DFC!A:A),DFC!A:A,"NÃO ESTÁ NA DFC")} -> 0 | P45: INSS
A46: 150030 | B46: 45930 | C46: Váriavel | F46: JULIO ANDÓ | G46: 2354.5 | H46: 2*4 | I46: =COUNTIF(Tabela1[NF],Tabela1[[#This Row],[NF]]) -> 2 | K46: =Tabela1[[#This Row],[DT. VENCIMENTO]] -> 45930 | N46: {=_xlfn.XLOOKUP(TRIM(D46),TRIM(DFC!A:A),DFC!A:A,"NÃO ESTÁ NA DFC")} -> 0 | P46: Internet
A47: 162583 | B47: 45930 | C47: Váriavel | F47: BRAS ONDA PAPELÃO ONDULADO LTDA | G47: 2126.79 | H47: 2*3 | I47: =COUNTIF(Tabela1[NF],Tabela1[[#This Row],[NF]]) -> 2 | K47: =Tabela1[[#This Row],[DT. VENCIMENTO]] -> 45930 | N47: {=_xlfn.XLOOKUP(TRIM(D47),TRIM(DFC!A:A),DFC!A:A,"NÃO ESTÁ NA DFC")} -> 0 | P47: IRPF
A48: 466115 | B48: 45930 | C48: Váriavel | D48: Peças | F48: ISAPA IMPORTAÇÃO E COMERCIO LTDA | G48: 1355 | H48: 2*4 | I48: =COUNTIF(Tabela1[NF],Tabela1[[#This Row],[NF]]) -> 3 | K48: =Tabela1[[#This Row],[DT. VENCIMENTO]] -> 45930 | N48: {=_xlfn.XLOOKUP(TRIM(D48),TRIM(DFC!A:A),DFC!A:A,"NÃO ESTÁ NA DFC")} -> PEÇAS | P48: ISS
A49: 609659 | B49: 45930 | C49: Váriavel | D49: Peças | F49: ISAPA IMPORTAÇÃO E COMERCIO LTDA | G49: 7718 | H49: 2*5 | I49: =COUNTIF(Tabela1[NF],Tabela1[[#This Row],[NF]]) -> 4 | K49: =Tabela1[[#This Row],[DT. VENCIMENTO]] -> 45930 | N49: {=_xlfn.XLOOKUP(TRIM(D49),TRIM(DFC!A:A),DFC!A:A,"NÃO ESTÁ NA DFC")} -> PEÇAS | P49: JUROS CHEQUE ESPECIAL
A50: 4005 | B50: 45931 | C50: Váriavel | D50: Peças | F50: FLAY INDUSTRIA E COMERCIO LTDA | G50: 2242.26 | H50: 1*3 | I50: =COUNTIF(Tabela1[NF],Tabela1[[#This Row],[NF]]) -> 2 | K50: =Tabela1[[#This Row],[DT. VENCIMENTO]] -> 45931 | N50: {=_xlfn.XLOOKUP(TRIM(D50),TRIM(DFC!A:A),DFC!A:A,"NÃO ESTÁ NA DFC")} -> PEÇAS | P50: Manutenção Predial
B51: 45931 | C51: Váriavel | D51: REEMBOLSO SAC | F51: PAGAMENTO PIX 04139180250 DAVI SOUZA SANTOS | G51: 15 | I51: =COUNTIF(Tabela1[NF],Tabela1[[#This Row],[NF]]) -> 0 | K51: =Tabela1[[#This Row],[DT. VENCIMENTO]] -> 45931 | N51: {=_xlfn.XLOOKUP(TRIM(D51),TRIM(DFC!A:A),DFC!A:A,"NÃO ESTÁ NA DFC")} -> REEMBOLSO SAC | P51: Marketing com produtos
B52: 45931 | C52: Váriavel | D52: REEMBOLSO SAC | F52: PAGAMENTO PIX 11206954493 ANTONIA ARAUJO DA SILV | G52: 25 | I52: =COUNTIF(Tabela1[NF],Tabela1[[#This Row],[NF]]) -> 0 | K52: =Tabela1[[#This Row],[DT. VENCIMENTO]] -> 45931 | N52: {=_xlfn.XLOOKUP(TRIM(D52),TRIM(DFC!A:A),DFC!A:A,"NÃO ESTÁ NA DFC")} -> REEMBOLSO SAC | P52: Materiais de uso e consumo
B53: 45931 | C53: Váriavel | D53: Peças | F53: CHEQUE COMPE SICREDI | G53: 12966.66 | I53: =COUNTIF(Tabela1[NF],Tabela1[[#This Row],[NF]]) -> 0 | K53: =Tabela1[[#This Row],[DT. VENCIMENTO]] -> 45931 | N53: {=_xlfn.XLOOKUP(TRIM(D53),TRIM(DFC!A:A),DFC!A:A,"NÃO ESTÁ NA DFC")} -> PEÇAS | P53: Outras Despesas Administrativas
B54: 45931 | C54: Váriavel | D54: Compra de Móveis e Utensílios | E54: COMPRA CADEIRAS ESCRITORIO | F54: CHEQUE COMPE SICREDI | G54: 3350 | I54: =COUNTIF(Tabela1[NF],Tabela1[[#This Row],[NF]]) -> 0 | K54: =Tabela1[[#This Row],[DT. VENCIMENTO]] -> 45931 | N54: {=_xlfn.XLOOKUP(TRIM(D54),TRIM(DFC!A:A),DFC!A:A,"NÃO ESTÁ NA DFC")} -> COMPRA DE MÓVEIS E UTENSÍLIOS | P54: Pagamento de Empréstimos
A55: 435665 | B55: 45931 | C55: Váriavel | D55: Peças | F55: ISAPA IMPORTAÇÃO E COMERCIO LTDA | G55: 1300 | H55: 2*4 | I55: =COUNTIF(Tabela1[NF],Tabela1[[#This Row],[NF]]) -> 3 | K55: 45932 | N55: {=_xlfn.XLOOKUP(TRIM(D55),TRIM(DFC!A:A),DFC!A:A,"NÃO ESTÁ NA DFC")} -> PEÇAS | P55: Pró labore
A56: 442271 | B56: 45931 | C56: Váriavel | D56: Peças | F56: ISAPA IMPORTAÇÃO E COMERCIO LTDA | G56: 2283.16 | H56: 1*4 | I56: =COUNTIF(Tabela1[NF],Tabela1[[#This Row],[NF]]) -> 4 | K56: 45932 | N56: {=_xlfn.XLOOKUP(TRIM(D56),TRIM(DFC!A:A),DFC!A:A,"NÃO ESTÁ NA DFC")} -> PEÇAS | P56: Projeto Casas Construir
A57: 605824 | B57: 45931 | C57: Váriavel | D57: Peças | F57: ISAPA IMPORTAÇÃO E COMERCIO LTDA | G57: 517 | H57: 3*3 | I57: =COUNTIF(Tabela1[NF],Tabela1[[#This Row],[NF]]) -> 1 | K57: 45932 | N57: {=_xlfn.XLOOKUP(TRIM(D57),TRIM(DFC!A:A),DFC!A:A,"NÃO ESTÁ NA DFC")} -> PEÇAS | P57: Reembolso
A58: 45931 | B58: 45932 | C58: Váriavel | D58: Tx. bancária | F58: UTILIZAÇÃO CHEQUE | G58: 11.91 | I58: =COUNTIF(Tabela1[NF],Tabela1[[#This Row],[NF]]) -> 23 | K58: 45932 | N58: {=_xlfn.XLOOKUP(TRIM(D58),TRIM(DFC!A:A),DFC!A:A,"NÃO ESTÁ NA DFC")} -> TX. BANCÁRIA | P58: Reembolso SAC
B59: 45932 | C59: Váriavel | D59: Tx. bancária | F59: CHEQUE A PARTIR 5000 | G59: 12.97 | I59: =COUNTIF(Tabela1[NF],Tabela1[[#This Row],[NF]]) -> 0 | K59: =Tabela1[[#This Row],[DT. VENCIMENTO]] -> 45932 | N59: {=_xlfn.XLOOKUP(TRIM(D59),TRIM(DFC!A:A),DFC!A:A,"NÃO ESTÁ NA DFC")} -> TX. BANCÁRIA | P59: Rescisões
B60: 45932 | C60: Váriavel | D60: REEMBOLSO SAC | F60: PAGAMENTO PIX 14508058922 Adrian Nickson Ferreir | G60: 50 | I60: =COUNTIF(Tabela1[NF],Tabela1[[#This Row],[NF]]) -> 0 | K60: =Tabela1[[#This Row],[DT. VENCIMENTO]] -> 45932 | N60: {=_xlfn.XLOOKUP(TRIM(D60),TRIM(DFC!A:A),DFC!A:A,"NÃO ESTÁ NA DFC")} -> REEMBOLSO SAC | P60: Salários
B61: 45932 | C61: Váriavel | D61: Peças | F61: LIQUIDACAO BOLETO 78144839000190 J ARAUJO E CIA | G61: 71.3 | I61: =COUNTIF(Tabela1[NF],Tabela1[[#This Row],[NF]]) -> 0 | K61: =Tabela1[[#This Row],[DT. VENCIMENTO]] -> 45932 | N61: {=_xlfn.XLOOKUP(TRIM(D61),TRIM(DFC!A:A),DFC!A:A,"NÃO ESTÁ NA DFC")} -> PEÇAS | P61: Sanepar
B62: 45932 | C62: Váriavel | D62: Peças | F62: LIQUIDACAO BOLETO 04288963000193 SAAR IMP LTDA | G62: 3079.39 | I62: =COUNTIF(Tabela1[NF],Tabela1[[#This Row],[NF]]) -> 0 | K62: =Tabela1[[#This Row],[DT. VENCIMENTO]] -> 45932 | N62: {=_xlfn.XLOOKUP(TRIM(D62),TRIM(DFC!A:A),DFC!A:A,"NÃO ESTÁ NA DFC")} -> PEÇAS | P62: Seguro de Veículos
B63: 45932 | C63: Váriavel | D63: Peças | F63: LIQUIDACAO BOLETO 02942192000180 EXCELLENCE TRAN | G63: 429.77 | I63: =COUNTIF(Tabela1[NF],Tabela1[[#This Row],[NF]]) -> 0 | K63: =Tabela1[[#This Row],[DT. VENCIMENTO]] -> 45932 | N63: {=_xlfn.XLOOKUP(TRIM(D63),TRIM(DFC!A:A),DFC!A:A,"NÃO ESTÁ NA DFC")} -> PEÇAS | P63: Seguro de Vida
A64: 514438 | B64: 45932 | C64: Váriavel | D64: Combustível | F64: DESPESA COM COMBUSTÍVEL | G64: 603.83 | I64: =COUNTIF(Tabela1[NF],Tabela1[[#This Row],[NF]]) -> 1 | K64: =Tabela1[[#This Row],[DT. VENCIMENTO]] -> 45932 | N64: {=_xlfn.XLOOKUP(TRIM(D64),TRIM(DFC!A:A),DFC!A:A,"NÃO ESTÁ NA DFC")} -> COMBUSTÍVEL | P64: Serviços de Manutenção
B65: 45933 | C65: Váriavel | D65: Peças | F65: LIQUIDACAO BOLETO 33805683000103 WB BIKE INDUSTR | G65: 1620 | I65: =COUNTIF(Tabela1[NF],Tabela1[[#This Row],[NF]]) -> 0 | K65: =Tabela1[[#This Row],[DT. VENCIMENTO]] -> 45933 | N65: {=_xlfn.XLOOKUP(TRIM(D65),TRIM(DFC!A:A),DFC!A:A,"NÃO ESTÁ NA DFC")} -> PEÇAS | P65: Serviços de Segurança
B66: 45933 | C66: Váriavel | F66: LIQUIDACAO BOLETO 37828752000155 URBANO INSTDE P | G66: 255.46 | I66: =COUNTIF(Tabela1[NF],Tabela1[[#This Row],[NF]]) -> 0 | K66: =Tabela1[[#This Row],[DT. VENCIMENTO]] -> 45933 | N66: {=_xlfn.XLOOKUP(TRIM(D66),TRIM(DFC!A:A),DFC!A:A,"NÃO ESTÁ NA DFC")} -> 0 | P66: Simples Nacional
B67: 45933 | C67: Váriavel | D67: Peças | F67: LIQUIDACAO BOLETO SICREDI 46728719000144 NOVA ON | G67: 3613.83 | I67: =COUNTIF(Tabela1[NF],Tabela1[[#This Row],[NF]]) -> 0 | K67: =Tabela1[[#This Row],[DT. VENCIMENTO]] -> 45933 | N67: {=_xlfn.XLOOKUP(TRIM(D67),TRIM(DFC!A:A),DFC!A:A,"NÃO ESTÁ NA DFC")} -> PEÇAS | P67: Simples Nacional Parcelamento
B68: 45933 | C68: Váriavel | D68: Peças | F68: LIQUIDACAO BOLETO SICREDI 05859014000189 KLS IND | G68: 3646.8 | I68: =COUNTIF(Tabela1[NF],Tabela1[[#This Row],[NF]]) -> 0 | K68: =Tabela1[[#This Row],[DT. VENCIMENTO]] -> 45933 | N68: {=_xlfn.XLOOKUP(TRIM(D68),TRIM(DFC!A:A),DFC!A:A,"NÃO ESTÁ NA DFC")} -> PEÇAS | P68: T.I
B69: 45933 | C69: Váriavel | D69: Peças | F69: LIQUIDACAO BOLETO 60002700000147 INTEGRA INFORMA | G69: 638.2 | I69: =COUNTIF(Tabela1[NF],Tabela1[[#This Row],[NF]]) -> 0 | K69: =Tabela1[[#This Row],[DT. VENCIMENTO]] -> 45933 | N69: {=_xlfn.XLOOKUP(TRIM(D69),TRIM(DFC!A:A),DFC!A:A,"NÃO ESTÁ NA DFC")} -> PEÇAS | P69: TELEFONIA
A70: 29517 | B70: 45934 | C70: Váriavel | D70: Peças | F70: NEW BOX IND COM EMBAL LTDA | G70: 5932.75 | H70: 1*3 | I70: =COUNTIF(Tabela1[NF],Tabela1[[#This Row],[NF]]) -> 1 | K70: 45936 | N70: {=_xlfn.XLOOKUP(TRIM(D70),TRIM(DFC!A:A),DFC!A:A,"NÃO ESTÁ NA DFC")} -> PEÇAS | P70: Terreno Linham
A71: 150273 | B71: 45934 | C71: Váriavel | D71: Peças | F71: JULIO ANDÓ | G71: 2588.68 | H71: 2*4 | I71: =COUNTIF(Tabela1[NF],Tabela1[[#This Row],[NF]]) -> 1 | K71: 45936 | N71: {=_xlfn.XLOOKUP(TRIM(D71),TRIM(DFC!A:A),DFC!A:A,"NÃO ESTÁ NA DFC")} -> PEÇAS | P71: Ticket Alimentação
A72: 150316 | B72: 45934 | C72: Váriavel | D72: Peças | F72: JULIO ANDÓ | G72: 1526.93 | H72: 2*4 | I72: =COUNTIF(Tabela1[NF],Tabela1[[#This Row],[NF]]) -> 1 | K72: 45936 | N72: {=_xlfn.XLOOKUP(TRIM(D72),TRIM(DFC!A:A),DFC!A:A,"NÃO ESTÁ NA DFC")} -> PEÇAS | P72: TRANSPORTE - PAGAMENTO ENTREGA
A73: 425643 | B73: 45934 | C73: Váriavel | D73: Peças | F73: ISAPA IMPORTAÇÃO E COMERCIO LTDA | G73: 847 | H73: 4*4 | I73: =COUNTIF(Tabela1[NF],Tabela1[[#This Row],[NF]]) -> 1 | K73: 45936 | N73: {=_xlfn.XLOOKUP(TRIM(D73),TRIM(DFC!A:A),DFC!A:A,"NÃO ESTÁ NA DFC")} -> PEÇAS | P73: TRANSPORTE - PAGAMENTO FRETE
A74: 7605 | B74: 45935 | C74: Váriavel | D74: Peças | F74: FLAY INDUSTRIA E COMERCIO LTDA | G74: 3438.86 | H74: 2*3 | I74: =COUNTIF(Tabela1[NF],Tabela1[[#This Row],[NF]]) -> 1 | K74: 45936 | N74: {=_xlfn.XLOOKUP(TRIM(D74),TRIM(DFC!A:A),DFC!A:A,"NÃO ESTÁ NA DFC")} -> PEÇAS | P74: TREINAMENTO DE FUNCIONÁRIO
A75: 147298 | B75: 45935 | C75: Váriavel | D75: Peças | F75: JULIO ANDÓ | G75: 2241.54 | H75: 3*3 | I75: =COUNTIF(Tabela1[NF],Tabela1[[#This Row],[NF]]) -> 1 | K75: 45936 | N75: {=_xlfn.XLOOKUP(TRIM(D75),TRIM(DFC!A:A),DFC!A:A,"NÃO ESTÁ NA DFC")} -> PEÇAS | P75: Tx. Bancária
A76: 153476 | B76: 45935 | C76: Váriavel | D76: Peças | F76: JULIO ANDÓ | G76: 714.81 | H76: 1*5 | I76: =COUNTIF(Tabela1[NF],Tabela1[[#This Row],[NF]]) -> 1 | K76: 45936 | N76: {=_xlfn.XLOOKUP(TRIM(D76),TRIM(DFC!A:A),DFC!A:A,"NÃO ESTÁ NA DFC")} -> PEÇAS | P76: UNIFORMES GOTT
A77: 430675 | B77: 45935 | C77: Váriavel | D77: Peças | F77: ISAPA IMPORTAÇÃO E COMERCIO LTDA | G77: 744 | H77: 3*4 | I77: =COUNTIF(Tabela1[NF],Tabela1[[#This Row],[NF]]) -> 2 | K77: 45936 | N77: {=_xlfn.XLOOKUP(TRIM(D77),TRIM(DFC!A:A),DFC!A:A,"NÃO ESTÁ NA DFC")} -> PEÇAS | P77: VALES
A78: 443343 | B78: 45935 | C78: Váriavel | D78: Peças | F78: ISAPA IMPORTAÇÃO E COMERCIO LTDA | G78: 4825 | H78: 1*4 | I78: =COUNTIF(Tabela1[NF],Tabela1[[#This Row],[NF]]) -> 4 | K78: 45936 | N78: {=_xlfn.XLOOKUP(TRIM(D78),TRIM(DFC!A:A),DFC!A:A,"NÃO ESTÁ NA DFC")} -> PEÇAS
A79: 436345 | B79: 45935 | C79: Váriavel | D79: Peças | F79: ISAPA IMPORTAÇÃO E COMERCIO LTDA | G79: 51962 | H79: 2*5 | I79: =COUNTIF(Tabela1[NF],Tabela1[[#This Row],[NF]]) -> 6 | K79: 45936 | N79: {=_xlfn.XLOOKUP(TRIM(D79),TRIM(DFC!A:A),DFC!A:A,"NÃO ESTÁ NA DFC")} -> PEÇAS
A80: 436358 | B80: 45935 | C80: Váriavel | D80: Peças | F80: ISAPA IMPORTAÇÃO E COMERCIO LTDA | G80: 6115 | H80: 2*5 | I80: =COUNTIF(Tabela1[NF],Tabela1[[#This Row],[NF]]) -> 5 | K80: 45936 | N80: {=_xlfn.XLOOKUP(TRIM(D80),TRIM(DFC!A:A),DFC!A:A,"NÃO ESTÁ NA DFC")} -> PEÇAS
A81: 436424 | B81: 45935 | C81: Váriavel | D81: Peças | F81: LIQUIDACAO BOLETO 61327045000160 ISAPA IMPE COML | G81: 2959 | H81: 2*4 | I81: =COUNTIF(Tabela1[NF],Tabela1[[#This Row],[NF]]) -> 4 | K81: 45936 | N81: {=_xlfn.XLOOKUP(TRIM(D81),TRIM(DFC!A:A),DFC!A:A,"NÃO ESTÁ NA DFC")} -> PEÇAS
A82: 443185 | B82: 45935 | C82: Váriavel | D82: Peças | F82: ISAPA IMPORTAÇÃO E COMERCIO LTDA | G82: 4825 | H82: 1*4 | I82: =COUNTIF(Tabela1[NF],Tabela1[[#This Row],[NF]]) -> 4 | K82: 45936 | N82: {=_xlfn.XLOOKUP(TRIM(D82),TRIM(DFC!A:A),DFC!A:A,"NÃO ESTÁ NA DFC")} -> PEÇAS
A83: 443246 | B83: 45935 | C83: Váriavel | D83: Peças | F83: ISAPA IMPORTAÇÃO E COMERCIO LTDA | G83: 776.06 | H83: 1*3 | I83: =COUNTIF(Tabela1[NF],Tabela1[[#This Row],[NF]]) -> 3 | K83: 45936 | N83: {=_xlfn.XLOOKUP(TRIM(D83),TRIM(DFC!A:A),DFC!A:A,"NÃO ESTÁ NA DFC")} -> PEÇAS
A84: 436345 | B84: 45935 | C84: Váriavel | D84: Peças | F84: LIQUIDACAO BOLETO 61327045000160 ISAPA IMPE COML | G84: 51962 | I84: =COUNTIF(Tabela1[NF],Tabela1[[#This Row],[NF]]) -> 6 | K84: =B84 -> 45935 | N84: {=_xlfn.XLOOKUP(TRIM(D84),TRIM(DFC!A:A),DFC!A:A,"NÃO ESTÁ NA DFC")} -> PEÇAS
A85: 1278 | B85: 45936 | C85: Váriavel | D85: Peças | F85: Wester Bike Industria e Comercio LTDA | G85: 523.18 | H85: 2*2 | I85: =COUNTIF(Tabela1[NF],Tabela1[[#This Row],[NF]]) -> 2 | K85: =Tabela1[[#This Row],[DT. VENCIMENTO]] -> 45936 | N85: {=_xlfn.XLOOKUP(TRIM(D85),TRIM(DFC!A:A),DFC!A:A,"NÃO ESTÁ NA DFC")} -> PEÇAS
A86: 45901 | B86: 45936 | C86: Fixo | D86: Salários | F86: FOLHA DE PAGAMENTO | G86: 17710.82 | H86: 1*1 | I86: =COUNTIF(Tabela1[NF],Tabela1[[#This Row],[NF]]) -> 9 | K86: =Tabela1[[#This Row],[DT. VENCIMENTO]] -> 45936 | N86: {=_xlfn.XLOOKUP(TRIM(D86),TRIM(DFC!A:A),DFC!A:A,"NÃO ESTÁ NA DFC")} -> SALÁRIOS
A87: 45901 | B87: 45936 | C87: Fixo | D87: Ticket Alimentação | F87: TICKET ALIMENTAÇÃO | G87: =280*6 -> 1680 | H87: 1*1 | I87: =COUNTIF(Tabela1[NF],Tabela1[[#This Row],[NF]]) -> 9 | J87: R$280 por colaborador. Pago exceto Vinicius, Felipe e Elisiee. | K87: =Tabela1[[#This Row],[DT. VENCIMENTO]] -> 45936 | N87: {=_xlfn.XLOOKUP(TRIM(D87),TRIM(DFC!A:A),DFC!A:A,"NÃO ESTÁ NA DFC")} -> TICKET ALIMENTAÇÃO
A88: 147373 | B88: 45936 | C88: Váriavel | D88: Peças | F88: JULIO ANDÓ | G88: 1396.92 | H88: 3*4 | I88: =COUNTIF(Tabela1[NF],Tabela1[[#This Row],[NF]]) -> 1 | K88: =Tabela1[[#This Row],[DT. VENCIMENTO]] -> 45936 | N88: {=_xlfn.XLOOKUP(TRIM(D88),TRIM(DFC!A:A),DFC!A:A,"NÃO ESTÁ NA DFC")} -> PEÇAS
A89: 150492 | B89: 45936 | C89: Váriavel | D89: Peças | F89: JULIO ANDÓ | G89: 4663.76 | H89: 2*4 | I89: =COUNTIF(Tabela1[NF],Tabela1[[#This Row],[NF]]) -> 1 | K89: =Tabela1[[#This Row],[DT. VENCIMENTO]] -> 45936 | N89: {=_xlfn.XLOOKUP(TRIM(D89),TRIM(DFC!A:A),DFC!A:A,"NÃO ESTÁ NA DFC")} -> PEÇAS
B90: 45936 | C90: Váriavel | D90: Aluguel | E90: sala comercial em SP, para filial | F90: LIQUIDACAO BOLETO 20240272000176 COMPANY HERO LT | G90: 380 | I90: =COUNTIF(Tabela1[NF],Tabela1[[#This Row],[NF]]) -> 0 | K90: =Tabela1[[#This Row],[DT. VENCIMENTO]] -> 45936 | N90: {=_xlfn.XLOOKUP(TRIM(D90),TRIM(DFC!A:A),DFC!A:A,"NÃO ESTÁ NA DFC")} -> ALUGUEL
B91: 45936 | C91: Váriavel | D91: Peças | F91: LIQUIDACAO BOLETO 22705434000120 BLUE CYCLE | G91: 1877.95 | I91: =COUNTIF(Tabela1[NF],Tabela1[[#This Row],[NF]]) -> 0 | K91: =Tabela1[[#This Row],[DT. VENCIMENTO]] -> 45936 | N91: {=_xlfn.XLOOKUP(TRIM(D91),TRIM(DFC!A:A),DFC!A:A,"NÃO ESTÁ NA DFC")} -> PEÇAS
B92: 45936 | C92: Váriavel | D92: Peças | F92: LIQUIDACAO BOLETO 34028316000103 EMPRESA BRASILE | G92: 1084.01 | I92: =COUNTIF(Tabela1[NF],Tabela1[[#This Row],[NF]]) -> 0 | K92: =Tabela1[[#This Row],[DT. VENCIMENTO]] -> 45936 | N92: {=_xlfn.XLOOKUP(TRIM(D92),TRIM(DFC!A:A),DFC!A:A,"NÃO ESTÁ NA DFC")} -> PEÇAS
B93: 45936 | C93: Váriavel | D93: Peças | F93: DEBITO CHEQUE | G93: 16500 | I93: =COUNTIF(Tabela1[NF],Tabela1[[#This Row],[NF]]) -> 0 | K93: =Tabela1[[#This Row],[DT. VENCIMENTO]] -> 45936 | N93: {=_xlfn.XLOOKUP(TRIM(D93),TRIM(DFC!A:A),DFC!A:A,"NÃO ESTÁ NA DFC")} -> PEÇAS
B94: 45936 | C94: Váriavel | D94: Equipamentos de Informática | E94: COMPRA NOTBOOK EMPRESA | F94: CHEQUE COMPE SICREDI | G94: 1750 | I94: =COUNTIF(Tabela1[NF],Tabela1[[#This Row],[NF]]) -> 0 | K94: =Tabela1[[#This Row],[DT. VENCIMENTO]] -> 45936 | N94: {=_xlfn.XLOOKUP(TRIM(D94),TRIM(DFC!A:A),DFC!A:A,"NÃO ESTÁ NA DFC")} -> EQUIPAMENTOS DE INFORMÁTICA
B95: 45936 | C95: Fixo | D95: Serviços de Segurança | E95: ROTTA | F95: LIQUIDACAO BOLETO 45177751000116 LEGACY MONITORA | G95: 152 | I95: =COUNTIF(Tabela1[NF],Tabela1[[#This Row],[NF]]) -> 0 | K95: =Tabela1[[#This Row],[DT. VENCIMENTO]] -> 45936 | N95: {=_xlfn.XLOOKUP(TRIM(D95),TRIM(DFC!A:A),DFC!A:A,"NÃO ESTÁ NA DFC")} -> SERVIÇOS DE SEGURANÇA
A96: 431002 | B96: 45936 | C96: Váriavel | D96: Peças | F96: ISAPA IMPORTAÇÃO E COMERCIO LTDA | G96: 2135 | H96: 3*4 | I96: =COUNTIF(Tabela1[NF],Tabela1[[#This Row],[NF]]) -> 2 | K96: =Tabela1[[#This Row],[DT. VENCIMENTO]] -> 45936 | N96: {=_xlfn.XLOOKUP(TRIM(D96),TRIM(DFC!A:A),DFC!A:A,"NÃO ESTÁ NA DFC")} -> PEÇAS
A97: 436655 | B97: 45936 | C97: Váriavel | D97: Peças | F97: ISAPA IMPORTAÇÃO E COMERCIO LTDA | G97: 29409 | H97: 2*5 | I97: =COUNTIF(Tabela1[NF],Tabela1[[#This Row],[NF]]) -> 5 | K97: =Tabela1[[#This Row],[DT. VENCIMENTO]] -> 45936 | N97: {=_xlfn.XLOOKUP(TRIM(D97),TRIM(DFC!A:A),DFC!A:A,"NÃO ESTÁ NA DFC")} -> PEÇAS
A98: 436412 | B98: 45936 | C98: Váriavel | D98: Peças | F98: LIQUIDACAO BOLETO 61327045000160 ISAPA IMPE COML | G98: 5157 | I98: =COUNTIF(Tabela1[NF],Tabela1[[#This Row],[NF]]) -> 5 | K98: =Tabela1[[#This Row],[DT. VENCIMENTO]] -> 45936 | N98: {=_xlfn.XLOOKUP(TRIM(D98),TRIM(DFC!A:A),DFC!A:A,"NÃO ESTÁ NA DFC")} -> PEÇAS
A99: 3573 | B99: 45937 | C99: Váriavel | D99: Peças | F99: SAAR ADESIVOS | G99: 767 | H99: 1*2 | I99: =COUNTIF(Tabela1[NF],Tabela1[[#This Row],[NF]]) -> 2 | K99: =Tabela1[[#This Row],[DT. VENCIMENTO]] -> 45937 | N99: {=_xlfn.XLOOKUP(TRIM(D99),TRIM(DFC!A:A),DFC!A:A,"NÃO ESTÁ NA DFC")} -> PEÇAS
A100: 7429 | B100: 45937 | C100: Váriavel | D100: Peças | F100: FLAY INDUSTRIA E COMERCIO LTDA | G100: 4093.88 | H100: 3*3 | I100: =COUNTIF(Tabela1[NF],Tabela1[[#This Row],[NF]]) -> 1 | K100: =Tabela1[[#This Row],[DT. VENCIMENTO]] -> 45937 | N100: {=_xlfn.XLOOKUP(TRIM(D100),TRIM(DFC!A:A),DFC!A:A,"NÃO ESTÁ NA DFC")} -> PEÇAS
...

Sheet COMPROMISSOS
B1: Inclusão | C1: Conclusão | D1: Responsáveis | E1: Gravidade | F1: TOD - Tarefa Operacional Diária (COMPROMISSOS) | G1: Descrição da Solução
A2: TRUE | B2: 46096 | C2: 46096 | D2: Matheus e Eduardo | F2: Apresentação da DRE de fev/26 | G2: Documento enviado
A3: TRUE | B3: 46097 | C3: 46097 | D3: Mateus | F3: Encerramento do contrato do barracão da Juriti Vermelha R$ 6.770,00 | G3: Entrega das chaves
A4: TRUE | B4: 46097 | C4: 46098 | D4: Matheus e Eduardo | F4: Análise de currículos para contratações | G4: Análise realizada
A5: TRUE | B5: 46097 | C5: 46104 | D5: Matheus e Eduardo | F5: Contratação compras e contas a pagar | G5: Contratada Gabriela Fernanda
A6: TRUE | B6: 46097 | C6: 46106 | D6: Vinícius | F6: Gravação Luan Pereira | G6: Gravação realizada
A7: TRUE | B7: 46097 | C7: 46106 | D7: Matheus | F7: Contratação aux. estoque | G7: Em teste
A8: TRUE | B8: 46097 | C8: 46108 | D8: Mateus | F8: Tick Tock a receber - Verificar conta corrente de recebimento | G8: ok. Recebimento PIX 27415911000136 Bytedance Brasil
A9: TRUE | B9: 46097 | C9: 46108 | D9: Matheus | F9: Verificar se o aluguel do barracão da Juriti Vermelha saiu, ou não aparece mais no DDA | G9: Aluguel Juriti Vermelha saiu do DDA
A10: TRUE | B10: 46107 | C10: 46113 | D10: Matheus e Eduardo | F10: Fluxo de caixa de março | G10: Positivo em R$ 44.402,94
A11: TRUE | B11: 46199 | C11: 46113 | D11: Mateus | F11: Definir Metas para abril/2026 | G11: Faturamento R$ 1.500.000,00, 2130 bikes
A12: TRUE | B12: 46097 | C12: 46114 | D12: Matheus | F12: Demissões | G12: Meire - OK
A13: TRUE | B13: 46097 | C13: 46114 | D13: Matheus | F13: Eliminar acessos do Lucas Landim | G13: Acessos eliminados
A14: TRUE | B14: 46097 | C14: 46121 | D14: Matheus e Eduardo | F14: Contratação contas a receber | G14: Poliana
A15: FALSE | B15: 46097 | C15: 46127 | D15: Mateus | F15: Lançamento Luan Pereira
A16: FALSE | B16: 46097 | F16: Analisar/limpar DDA - análise conta por conta (conciliação)
A17: FALSE | B17: 46097 | D17: Matheus e Eduardo | F17: Análise das contas pagar da DFC - contas analíticas
A18: FALSE | B18: 46097 | D18: Mateus e Ana | F18: Conferência nas plataformas sobre as entregas dos pedidos para liberarmos os recebimentos
A19: FALSE | B19: 46097 | D19: Mateus | F19: Definir estoque mínimo de peças
A20: FALSE | B20: 46097 | D20: Mateus | F20: Encerrar BR1 China Link do Brasil R$ 1.600,00
A21: FALSE | B21: 46107 | F21: Margem de contribuição por produto
A22: FALSE | B22: 46097 | F22: POPs, controles, indicadores
A23: FALSE | B23: 46097 | D23: Matheus | F23: Possíveis lançamentos duplicados da Prefeitura Municipal de Arapongas no DDA | G23: Verificando
A24: FALSE | B24: 46107 | F24: Projeção de compras abril
A25: FALSE | B25: 46107 | F25: Projeção de vendas abril
A26: FALSE | B26: 46107 | F26: Recebimentos e contas a receber (processo)
A27: FALSE | B27: 46097 | D27: Matheus | F27: Resumo mensal sempre atualizado diariamente do recebimento apontado no extrato Sicredi. Recebimento por canal.
A28: FALSE | B28: 46097 | D28: Matheus e Eduardo | F28: Solução envio de xmls para o Escritório (manual e domínio) - Fiscal.
A29: FALSE | B29: 46107 | D29: Mateus e Matheus | F29: Projeção de impostos competência março
A30: FALSE | B30: 46107 | D30: Mateus | F30: Redução de custos - análise de possibilidades
A31: FALSE | B31: 46107 | D31: Vinícius | F31: Marketing e lives - análise março e planejamento de abril
A32: FALSE | B32: 46107 | D32: Mateus e Matheus | F32: Cheques devolvidos e protestos (controle de contas a pagar)
A33: FALSE | B33: 45015 | D33: Matheus | F33: Análise da reimplantação do sistema ERP
A34: FALSE | B34: 46111 | D34: Matheus | F34: Levantamento de impostos e taxas em atraso
A35: FALSE | B35: 46111 | F35: Lançamento de contas no DDA (muitas contas não estão lá)
A36: FALSE | B36: 46111 | F36: Controle de devoluções e avarias
A37: FALSE | B37: 46111 | F37: Lançar todas as contas a pagar possíveis no DDA
A38: FALSE | B38: 46119 | F38: Transferir todos os funcionários de CNPJ (nova empresa)
A39: FALSE | B39: 46119 | F39: Precificação e custos
A40: FALSE
A41: FALSE
A42: FALSE
A43: FALSE
A44: FALSE
A45: FALSE
A46: FALSE
A47: FALSE
A48: FALSE
A49: FALSE
A50: FALSE
A51: FALSE
... A64: FALSE

Sheet DDA
A1: 9 | D1: =SUM(D3:D496) -> 2346138 | F1: Mês | G1: 04 | I1: =TEXT(DATE(YEAR(TODAY()),G1,1),"mmmm") -> abril | K1: Mês | L1: 05 | N1: =TEXT(DATE(YEAR(TODAY()),L1,1),"mmmm") -> maio | P1: Mês | Q1: 06 | S1: =TEXT(DATE(YEAR(TODAY()),Q1,1),"mmmm") -> junho | U1: Mês | V1: 07 | X1: =TEXT(DATE(YEAR(TODAY()),V1,1),"mmmm") -> julho | Z1: OUTROS | AA1: =D1-SUM(AA2:AA6) -> 1790949.5
A2: Beneficiário | B2: Nº Doc | C2: Vencto | D2: Valor (R$) | F2: Ano | G2: 2026 | I2: DDA | K2: Ano | L2: 2026 | N2: DDA | P2: Ano | Q2: 2026 | S2: DDA | U2: Ano | V2: 2026 | X2: DDA | Z2: ZOEMAQ INDUSTRIA E COMERCIO DE MAQUINAS LTDA | AA2: =SUMIF(A:A,Z2,D:D) -> 479125.35
A3: JULIO ANDO CIA LTDA | B3: 164721 8 | C3: 46143 | D3: 2911.3 | F3: Dia | G3: Data | H3: Sem | I3: =SUM(I4:I34) -> 0 | K3: Dia | L3: Data | M3: Sem | N3: =SUM(N4:N34) -> 704328.16 | P3: Dia | Q3: Data | R3: Sem | S3: =SUM(S4:S34) -> 559369.71 | U3: Dia | V3: Data | W3: Sem | X3: =SUM(X4:X34) -> 436626.3 | Z3: ESCRITORIO GESTOR CONTABILIDADE LTDA | AA3: =SUMIF(A:A,Z3,D:D) -> 31952
A4: SOLUTIKA TECNOLOGIA LTDA | B4: 20722 | C4: 46143 | D4: 901.91 | F4: 01 | G4: =_xlfn.CONCAT(F4,"/",$G$1,"/",$G$2) -> 01/04/2026 | H4: =TEXT(G4,"ddd") -> qua | I4: =SUMIF(C:C,G4,D:D) -> 0 | K4: 01 | L4: =_xlfn.CONCAT(K4,"/",$L$1,"/",$L$2) -> 01/05/2026 | M4: =TEXT(L4,"ddd") -> sex | N4: =SUMIF(C:C,L4,D:D) -> 18253.52 | P4: 01 | Q4: =_xlfn.CONCAT(P4,"/",$Q$1,"/",$Q$2) -> 01/06/2026 | R4: =TEXT(Q4,"ddd") -> seg | S4: =SUMIF(C:C,Q4,D:D) -> 24267.9 | U4: 01 | V4: =_xlfn.CONCAT(U4,"/",$V$1,"/",$V$2) -> 01/07/2026 | W4: =TEXT(V4,"ddd") -> qua | X4: =SUMIF(C:C,V4,D:D) -> 22161.14 | Z4: GRAN RESIDENCE INCORPORADORA LTDA | AA4: =SUMIF(A:A,Z4,D:D) -> 6202.11
A5: VEGA DISTRIBUIDORA LTDA | B5: 24401 | C5: 46143 | D5: 4342.96 | F5: 02 | G5: =_xlfn.CONCAT(F5,"/",$G$1,"/",$G$2) -> 02/04/2026 | H5: =TEXT(G5,"ddd") -> qui | I5: =SUMIF(C:C,G5,D:D) -> 0 | K5: 02 | L5: =_xlfn.CONCAT(K5,"/",$L$1,"/",$L$2) -> 02/05/2026 | M5: =TEXT(L5,"ddd") -> sáb | N5: =SUMIF(C:C,L5,D:D) -> 36101.65 | P5: 02 | Q5: =_xlfn.CONCAT(P5,"/",$Q$1,"/",$Q$2) -> 02/06/2026 | R5: =TEXT(Q5,"ddd") -> ter | S5: =SUMIF(C:C,Q5,D:D) -> 3403.76 | U5: 02 | V5: =_xlfn.CONCAT(U5,"/",$V$1,"/",$V$2) -> 02/07/2026 | W5: =TEXT(V5,"ddd") -> qui | X5: =SUMIF(C:C,V5,D:D) -> 3403.76 | Z5: PM DE ARAPONGAS | AA5: =SUMIF(A:A,Z5,D:D) -> 9109.04
A6: M A F COM DE ARTIGOS DE PAPELA | B6: 123302 | C6: 46143 | D6: 63.3 | F6: 03 | G6: =_xlfn.CONCAT(F6,"/",$G$1,"/",$G$2) -> 03/04/2026 | H6: =TEXT(G6,"ddd") -> sex | I6: =SUMIF(C:C,G6,D:D) -> 0 | K6: 03 | L6: =_xlfn.CONCAT(K6,"/",$L$1,"/",$L$2) -> 03/05/2026 | M6: =TEXT(L6,"ddd") -> dom | N6: =SUMIF(C:C,L6,D:D) -> 5446.92 | P6: 03 | Q6: =_xlfn.CONCAT(P6,"/",$Q$1,"/",$Q$2) -> 03/06/2026 | R6: =TEXT(Q6,"ddd") -> qua | S6: =SUMIF(C:C,Q6,D:D) -> 0 | U6: 03 | V6: =_xlfn.CONCAT(U6,"/",$V$1,"/",$V$2) -> 03/07/2026 | W6: =TEXT(V6,"ddd") -> sex | X6: =SUMIF(C:C,V6,D:D) -> 0 | Z6: CEFAS S NOBRE | AA6: =SUMIF(A:A,Z6,D:D) -> 28800
A7: JULIO ANDO CIA LTDA | B7: 176542 1 | C7: 46143 | D7: 5089.31 | F7: 04 | G7: =_xlfn.CONCAT(F7,"/",$G$1,"/",$G$2) -> 04/04/2026 | H7: =TEXT(G7,"ddd") -> sáb | I7: =SUMIF(C:C,G7,D:D) -> 0 | K7: 04 | L7: =_xlfn.CONCAT(K7,"/",$L$1,"/",$L$2) -> 04/05/2026 | M7: =TEXT(L7,"ddd") -> seg | N7: =SUMIF(C:C,L7,D:D) -> 6159.42 | P7: 04 | Q7: =_xlfn.CONCAT(P7,"/",$Q$1,"/",$Q$2) -> 04/06/2026 | R7: =TEXT(Q7,"ddd") -> qui | S7: =SUMIF(C:C,Q7,D:D) -> 8774.37 | U7: 04 | V7: =_xlfn.CONCAT(U7,"/",$V$1,"/",$V$2) -> 04/07/2026 | W7: =TEXT(V7,"ddd") -> sáb | X7: =SUMIF(C:C,V7,D:D) -> 0 | Z7: TOTAL A PAGAR DDA | AA7: =SUM(AA1:AA6) -> 2346138
A8: ISAPA IMP.E COM.LTDA. | B8: 48676901 | C8: 46143 | D8: 4944.74 | F8: 05 | G8: =_xlfn.CONCAT(F8,"/",$G$1,"/",$G$2) -> 05/04/2026 | H8: =TEXT(G8,"ddd") -> dom | I8: =SUMIF(C:C,G8,D:D) -> 0 | K8: 05 | L8: =_xlfn.CONCAT(K8,"/",$L$1,"/",$L$2) -> 05/05/2026 | M8: =TEXT(L8,"ddd") -> ter | N8: =SUMIF(C:C,L8,D:D) -> 12045.74 | P8: 05 | Q8: =_xlfn.CONCAT(P8,"/",$Q$1,"/",$Q$2) -> 05/06/2026 | R8: =TEXT(Q8,"ddd") -> sex | S8: =SUMIF(C:C,Q8,D:D) -> 431.2 | U8: 05 | V8: =_xlfn.CONCAT(U8,"/",$V$1,"/",$V$2) -> 05/07/2026 | W8: =TEXT(V8,"ddd") -> dom | X8: =SUMIF(C:C,V8,D:D) -> 431.2
A9: JULIO ANDO CIA LTDA | B9: 163115 5 | C9: 46144 | D9: 19184.13 | F9: 06 | G9: =_xlfn.CONCAT(F9,"/",$G$1,"/",$G$2) -> 06/04/2026 | H9: =TEXT(G9,"ddd") -> seg | I9: =SUMIF(C:C,G9,D:D) -> 0 | K9: 06 | L9: =_xlfn.CONCAT(K9,"/",$L$1,"/",$L$2) -> 06/05/2026 | M9: =TEXT(L9,"ddd") -> qua | N9: =SUMIF(C:C,L9,D:D) -> 10715.92 | P9: 06 | Q9: =_xlfn.CONCAT(P9,"/",$Q$1,"/",$Q$2) -> 06/06/2026 | R9: =TEXT(Q9,"ddd") -> sáb | S9: =SUMIF(C:C,Q9,D:D) -> 54327.07 | U9: 06 | V9: =_xlfn.CONCAT(U9,"/",$V$1,"/",$V$2) -> 06/07/2026 | W9: =TEXT(V9,"ddd") -> seg | X9: =SUMIF(C:C,V9,D:D) -> 39507.91
A10: JR COMERCIO B ACESSORIOS LTDA | B10: 174646 1 | C10: 46144 | D10: 10842 | F10: 07 | G10: =_xlfn.CONCAT(F10,"/",$G$1,"/",$G$2) -> 07/04/2026 | H10: =TEXT(G10,"ddd") -> ter | I10: =SUMIF(C:C,G10,D:D) -> 0 | K10: 07 | L10: =_xlfn.CONCAT(K10,"/",$L$1,"/",$L$2) -> 07/05/2026 | M10: =TEXT(L10,"ddd") -> qui | N10: =SUMIF(C:C,L10,D:D) -> 56973.62 | P10: 07 | Q10: =_xlfn.CONCAT(P10,"/",$Q$1,"/",$Q$2) -> 07/06/2026 | R10: =TEXT(Q10,"ddd") -> dom | S10: =SUMIF(C:C,Q10,D:D) -> 8647.35 | U10: 07 | V10: =_xlfn.CONCAT(U10,"/",$V$1,"/",$V$2) -> 07/07/2026 | W10: =TEXT(V10,"ddd") -> ter | X10: =SUMIF(C:C,V10,D:D) -> 2504.62 | Z10: DDA | AA10: =I1 -> abril
A11: J A GOMES DE SOUZA | B11: 126011 | C11: 46144 | D11: 1628 | F11: 08 | G11: =_xlfn.CONCAT(F11,"/",$G$1,"/",$G$2) -> 08/04/2026 | H11: =TEXT(G11,"ddd") -> qua | I11: =SUMIF(C:C,G11,D:D) -> 0 | K11: 08 | L11: =_xlfn.CONCAT(K11,"/",$L$1,"/",$L$2) -> 08/05/2026 | M11: =TEXT(L11,"ddd") -> sex | N11: =SUMIF(C:C,L11,D:D) -> 10213.48 | P11: 08 | Q11: =_xlfn.CONCAT(P11,"/",$Q$1,"/",$Q$2) -> 08/06/2026 | R11: =TEXT(Q11,"ddd") -> seg | S11: =SUMIF(C:C,Q11,D:D) -> 24412.01 | U11: 08 | V11: =_xlfn.CONCAT(U11,"/",$V$1,"/",$V$2) -> 08/07/2026 | W11: =TEXT(V11,"ddd") -> qua | X11: =SUMIF(C:C,V11,D:D) -> 15778.66
A12: JHC COM DE PECAS E ACESS P BICICLETAS LTDA | B12: 112641 | C12: 46144 | D12: 3941.28 | F12: 09 | G12: =_xlfn.CONCAT(F12,"/",$G$1,"/",$G$2) -> 09/04/2026 | H12: =TEXT(G12,"ddd") -> qui | I12: =SUMIF(C:C,G12,D:D) -> 0 | K12: 09 | L12: =_xlfn.CONCAT(K12,"/",$L$1,"/",$L$2) -> 09/05/2026 | M12: =TEXT(L12,"ddd") -> sáb | N12: =SUMIF(C:C,L12,D:D) -> 15920.81 | P12: 09 | Q12: =_xlfn.CONCAT(P12,"/",$Q$1,"/",$Q$2) -> 09/06/2026 | R12: =TEXT(Q12,"ddd") -> ter | S12: =SUMIF(C:C,Q12,D:D) -> 19814 | U12: 09 | V12: =_xlfn.CONCAT(U12,"/",$V$1,"/",$V$2) -> 09/07/2026 | W12: =TEXT(V12,"ddd") -> qui | X12: =SUMIF(C:C,V12,D:D) -> 22391.24
A13: ISAPA IMP.E COM.LTDA. | B13: 48710901 | C13: 46144 | D13: 506.24 | F13: 10 | G13: =_xlfn.CONCAT(F13,"/",$G$1,"/",$G$2) -> 10/04/2026 | H13: =TEXT(G13,"ddd") -> sex | I13: =SUMIF(C:C,G13,D:D) -> 0 | K13: 10 | L13: =_xlfn.CONCAT(K13,"/",$L$1,"/",$L$2) -> 10/05/2026 | M13: =TEXT(L13,"ddd") -> dom | N13: =SUMIF(C:C,L13,D:D) -> 26826.11 | P13: 10 | Q13: =_xlfn.CONCAT(P13,"/",$Q$1,"/",$Q$2) -> 10/06/2026 | R13: =TEXT(Q13,"ddd") -> qua | S13: =SUMIF(C:C,Q13,D:D) -> 26914.8 | U13: 10 | V13: =_xlfn.CONCAT(U13,"/",$V$1,"/",$V$2) -> 10/07/2026 | W13: =TEXT(V13,"ddd") -> sex | X13: =SUMIF(C:C,V13,D:D) -> 25065.28 | Z13: Saldo a Pagar | AA13: =I3 -> 0
A14: JULIO ANDO CIA LTDA | B14: 163170 5 | C14: 46145 | D14: 1933.39 | F14: 11 | G14: =_xlfn.CONCAT(F14,"/",$G$1,"/",$G$2) -> 11/04/2026 | H14: =TEXT(G14,"ddd") -> sáb | I14: =SUMIF(C:C,G14,D:D) -> 0 | K14: 11 | L14: =_xlfn.CONCAT(K14,"/",$L$1,"/",$L$2) -> 11/05/2026 | M14: =TEXT(L14,"ddd") -> seg | N14: =SUMIF(C:C,L14,D:D) -> 28818.24 | P14: 11 | Q14: =_xlfn.CONCAT(P14,"/",$Q$1,"/",$Q$2) -> 11/06/2026 | R14: =TEXT(Q14,"ddd") -> qui | S14: =SUMIF(C:C,Q14,D:D) -> 7281.22 | U14: 11 | V14: =_xlfn.CONCAT(U14,"/",$V$1,"/",$V$2) -> 11/07/2026 | W14: =TEXT(V14,"ddd") -> sáb | X14: =SUMIF(C:C,V14,D:D) -> 2082.12
A15: LUMASA EMBALAGENS LTDA | B15: 505-2 | C15: 46145 | D15: 3513.53 | F15: 12 | G15: =_xlfn.CONCAT(F15,"/",$G$1,"/",$G$2) -> 12/04/2026 | H15: =TEXT(G15,"ddd") -> dom | I15: =SUMIF(C:C,G15,D:D) -> 0 | K15: 12 | L15: =_xlfn.CONCAT(K15,"/",$L$1,"/",$L$2) -> 12/05/2026 | M15: =TEXT(L15,"ddd") -> ter | N15: =SUMIF(C:C,L15,D:D) -> 12917.25 | P15: 12 | Q15: =_xlfn.CONCAT(P15,"/",$Q$1,"/",$Q$2) -> 12/06/2026 | R15: =TEXT(Q15,"ddd") -> sex | S15: =SUMIF(C:C,Q15,D:D) -> 7439.9 | U15: 12 | V15: =_xlfn.CONCAT(U15,"/",$V$1,"/",$V$2) -> 12/07/2026 | W15: =TEXT(V15,"ddd") -> dom | X15: =SUMIF(C:C,V15,D:D) -> 502.29
A16: FLAY INDUSTRIA E COMERCIO LTDA | B16: 5221 - 1 | C16: 46146 | D16: 2654.51 | F16: 13 | G16: =_xlfn.CONCAT(F16,"/",$G$1,"/",$G$2) -> 13/04/2026 | H16: =TEXT(G16,"ddd") -> seg | I16: =SUMIF(C:C,G16,D:D) -> 0 | K16: 13 | L16: =_xlfn.CONCAT(K16,"/",$L$1,"/",$L$2) -> 13/05/2026 | M16: =TEXT(L16,"ddd") -> qua | N16: =SUMIF(C:C,L16,D:D) -> 7774.67 | P16: 13 | Q16: =_xlfn.CONCAT(P16,"/",$Q$1,"/",$Q$2) -> 13/06/2026 | R16: =TEXT(Q16,"ddd") -> sáb | S16: =SUMIF(C:C,Q16,D:D) -> 6558.66 | U16: 13 | V16: =_xlfn.CONCAT(U16,"/",$V$1,"/",$V$2) -> 13/07/2026 | W16: =TEXT(V16,"ddd") -> seg | X16: =SUMIF(C:C,V16,D:D) -> 9180.53
A17: ISAPA IMP.E COM.LTDA. | B17: 489350 | C17: 46146 | D17: 3504.91 | F17: 14 | G17: =_xlfn.CONCAT(F17,"/",$G$1,"/",$G$2) -> 14/04/2026 | H17: =TEXT(G17,"ddd") -> ter | I17: =SUMIF(C:C,G17,D:D) -> 0 | K17: 14 | L17: =_xlfn.CONCAT(K17,"/",$L$1,"/",$L$2) -> 14/05/2026 | M17: =TEXT(L17,"ddd") -> qui | N17: =SUMIF(C:C,L17,D:D) -> 7468.85 | P17: 14 | Q17: =_xlfn.CONCAT(P17,"/",$Q$1,"/",$Q$2) -> 14/06/2026 | R17: =TEXT(Q17,"ddd") -> dom | S17: =SUMIF(C:C,Q17,D:D) -> 38173.42 | U17: 14 | V17: =_xlfn.CONCAT(U17,"/",$V$1,"/",$V$2) -> 14/07/2026 | W17: =TEXT(V17,"ddd") -> ter | X17: =SUMIF(C:C,V17,D:D) -> 40160.93 | Z17: OUTROS | AA17: 1173693.2
A18: NEW BOX EMBALAGENS | B18: 30675 002 | C18: 46147 | D18: 3906.98 | F18: 15 | G18: =_xlfn.CONCAT(F18,"/",$G$1,"/",$G$2) -> 15/04/2026 | H18: =TEXT(G18,"ddd") -> qua | I18: =SUMIF(C:C,G18,D:D) -> 0 | K18: 15 | L18: =_xlfn.CONCAT(K18,"/",$L$1,"/",$L$2) -> 15/05/2026 | M18: =TEXT(L18,"ddd") -> sex | N18: =SUMIF(C:C,L18,D:D) -> 48103.74 | P18: 15 | Q18: =_xlfn.CONCAT(P18,"/",$Q$1,"/",$Q$2) -> 15/06/2026 | R18: =TEXT(Q18,"ddd") -> seg | S18: =SUMIF(C:C,Q18,D:D) -> 32191.7 | U18: 15 | V18: =_xlfn.CONCAT(U18,"/",$V$1,"/",$V$2) -> 15/07/2026 | W18: =TEXT(V18,"ddd") -> qua | X18: =SUMIF(C:C,V18,D:D) -> 15838.32 | Z18: ZOEMAQ INDUSTRIA E COMERCIO DE MAQUINAS LTDA | AA18: 495096.19
A19: FLAY INDUSTRIA E COMERCIO LTDA | B19: 5226 - 1 | C19: 46147 | D19: 4288.74 | F19: 16 | G19: =_xlfn.CONCAT(F19,"/",$G$1,"/",$G$2) -> 16/04/2026 | H19: =TEXT(G19,"ddd") -> qui | I19: =SUMIF(C:C,G19,D:D) -> 0 | K19: 16 | L19: =_xlfn.CONCAT(K19,"/",$L$1,"/",$L$2) -> 16/05/2026 | M19: =TEXT(L19,"ddd") -> sáb | N19: =SUMIF(C:C,L19,D:D) -> 33750.5 | P19: 16 | Q19: =_xlfn.CONCAT(P19,"/",$Q$1,"/",$Q$2) -> 16/06/2026 | R19: =TEXT(Q19,"ddd") -> ter | S19: =SUMIF(C:C,Q19,D:D) -> 3087.61 | U19: 16 | V19: =_xlfn.CONCAT(U19,"/",$V$1,"/",$V$2) -> 16/07/2026 | W19: =TEXT(V19,"ddd") -> qui | X19: =SUMIF(C:C,V19,D:D) -> 1100.43 | Z19: ESCRITORIO GESTOR CONTABILIDADE LTDA | AA19: 35946
A20: WESTER BIKE INDUSTRIA E COMERCIO LTDA | B20: 00002499/1 | C20: 46147 | D20: 707.16 | F20: 17 | G20: =_xlfn.CONCAT(F20,"/",$G$1,"/",$G$2) -> 17/04/2026 | H20: =TEXT(G20,"ddd") -> sex | I20: =SUMIF(C:C,G20,D:D) -> 0 | K20: 17 | L20: =_xlfn.CONCAT(K20,"/",$L$1,"/",$L$2) -> 17/05/2026 | M20: =TEXT(L20,"ddd") -> dom | N20: =SUMIF(C:C,L20,D:D) -> 1100.11 | P20: 17 | Q20: =_xlfn.CONCAT(P20,"/",$Q$1,"/",$Q$2) -> 17/06/2026 | R20: =TEXT(Q20,"ddd") -> qua | S20: =SUMIF(C:C,Q20,D:D) -> 11429.64 | U20: 17 | V20: =_xlfn.CONCAT(U20,"/",$V$1,"/",$V$2) -> 17/07/2026 | W20: =TEXT(V20,"ddd") -> sex | X20: =SUMIF(C:C,V20,D:D) -> 0 | Z20: GRAN RESIDENCE INCORPORADORA LTDA | AA20: 8269.48
A21: LEGACY MONITORAMENTO LTDA | B21: 46025 | C21: 46147 | D21: 144.56 | F21: 18 | G21: =_xlfn.CONCAT(F21,"/",$G$1,"/",$G$2) -> 18/04/2026 | H21: =TEXT(G21,"ddd") -> sáb | I21: =SUMIF(C:C,G21,D:D) -> 0 | K21: 18 | L21: =_xlfn.CONCAT(K21,"/",$L$1,"/",$L$2) -> 18/05/2026 | M21: =TEXT(L21,"ddd") -> seg | N21: =SUMIF(C:C,L21,D:D) -> 8095.87 | P21: 18 | Q21: =_xlfn.CONCAT(P21,"/",$Q$1,"/",$Q$2) -> 18/06/2026 | R21: =TEXT(Q21,"ddd") -> qui | S21: =SUMIF(C:C,Q21,D:D) -> 10963.14 | U21: 18 | V21: =_xlfn.CONCAT(U21,"/",$V$1,"/",$V$2) -> 18/07/2026 | W21: =TEXT(V21,"ddd") -> sáb | X21: =SUMIF(C:C,V21,D:D) -> 2068.47 | Z21: PM DE ARAPONGAS | AA21: 10247.68
A22: EMPRESA BRASILEIRA DE CORREIOS E TELEGRAFOS - ECT | B22: 1668551 | C22: 46147 | D22: 1546.09 | F22: 19 | G22: =_xlfn.CONCAT(F22,"/",$G$1,"/",$G$2) -> 19/04/2026 | H22: =TEXT(G22,"ddd") -> dom | I22: =SUMIF(C:C,G22,D:D) -> 0 | K22: 19 | L22: =_xlfn.CONCAT(K22,"/",$L$1,"/",$L$2) -> 19/05/2026 | M22: =TEXT(L22,"ddd") -> ter | N22: =SUMIF(C:C,L22,D:D) -> 19055.89 | P22: 19 | Q22: =_xlfn.CONCAT(P22,"/",$Q$1,"/",$Q$2) -> 19/06/2026 | R22: =TEXT(Q22,"ddd") -> sex | S22: =SUMIF(C:C,Q22,D:D) -> 2058.96 | U22: 19 | V22: =_xlfn.CONCAT(U22,"/",$V$1,"/",$V$2) -> 19/07/2026 | W22: =TEXT(V22,"ddd") -> dom | X22: =SUMIF(C:C,V22,D:D) -> 2058.96 | Z22: CEFAS S NOBRE | AA22: 31700
A23: COMPANY HERO LTDA | C23: 46147 | D23: 405.65 | F23: 20 | G23: =_xlfn.CONCAT(F23,"/",$G$1,"/",$G$2) -> 20/04/2026 | H23: =TEXT(G23,"ddd") -> seg | I23: =SUMIF(C:C,G23,D:D) -> 0 | K23: 20 | L23: =_xlfn.CONCAT(K23,"/",$L$1,"/",$L$2) -> 20/05/2026 | M23: =TEXT(L23,"ddd") -> qua | N23: =SUMIF(C:C,L23,D:D) -> 16446.17 | P23: 20 | Q23: =_xlfn.CONCAT(P23,"/",$Q$1,"/",$Q$2) -> 20/06/2026 | R23: =TEXT(Q23,"ddd") -> sáb | S23: =SUMIF(C:C,Q23,D:D) -> 27118.37 | U23: 20 | V23: =_xlfn.CONCAT(U23,"/",$V$1,"/",$V$2) -> 20/07/2026 | W23: =TEXT(V23,"ddd") -> seg | X23: =SUMIF(C:C,V23,D:D) -> 7978.87 | Z23: TOTAL A PAGAR DDA | AA23: 1754952.6
A24: TEK SYSTEM INFORMATICA LTDA | B24: 7883-CTR F | C24: 46147 | D24: 1046.56 | F24: 21 | G24: =_xlfn.CONCAT(F24,"/",$G$1,"/",$G$2) -> 21/04/2026 | H24: =TEXT(G24,"ddd") -> ter | I24: =SUMIF(C:C,G24,D:D) -> 0 | K24: 21 | L24: =_xlfn.CONCAT(K24,"/",$L$1,"/",$L$2) -> 21/05/2026 | M24: =TEXT(L24,"ddd") -> qui | N24: =SUMIF(C:C,L24,D:D) -> 52788.48 | P24: 21 | Q24: =_xlfn.CONCAT(P24,"/",$Q$1,"/",$Q$2) -> 21/06/2026 | R24: =TEXT(Q24,"ddd") -> dom | S24: =SUMIF(C:C,Q24,D:D) -> 3401.15 | U24: 21 | V24: =_xlfn.CONCAT(U24,"/",$V$1,"/",$V$2) -> 21/07/2026 | W24: =TEXT(V24,"ddd") -> ter | X24: =SUMIF(C:C,V24,D:D) -> 3401.12
A25: VEGA DISTRIBUIDORA LTDA | B25: 21002 | C25: 46148 | D25: 10284.72 | F25: 22 | G25: =_xlfn.CONCAT(F25,"/",$G$1,"/",$G$2) -> 22/04/2026 | H25: =TEXT(G25,"ddd") -> qua | I25: =SUMIF(C:C,G25,D:D) -> 0 | K25: 22 | L25: =_xlfn.CONCAT(K25,"/",$L$1,"/",$L$2) -> 22/05/2026 | M25: =TEXT(L25,"ddd") -> sex | N25: =SUMIF(C:C,L25,D:D) -> 5924.67 | P25: 22 | Q25: =_xlfn.CONCAT(P25,"/",$Q$1,"/",$Q$2) -> 22/06/2026 | R25: =TEXT(Q25,"ddd") -> seg | S25: =SUMIF(C:C,Q25,D:D) -> 29759.64 | U25: 22 | V25: =_xlfn.CONCAT(U25,"/",$V$1,"/",$V$2) -> 22/07/2026 | W25: =TEXT(V25,"ddd") -> qua | X25: =SUMIF(C:C,V25,D:D) -> 21888.98
A26: JULIO ANDO CIA LTDA | B26: 176776 1 | C26: 46148 | D26: 431.2 | F26: 23 | G26: =_xlfn.CONCAT(F26,"/",$G$1,"/",$G$2) -> 23/04/2026 | H26: =TEXT(G26,"ddd") -> qui | I26: =SUMIF(C:C,G26,D:D) -> 0 | K26: 23 | L26: =_xlfn.CONCAT(K26,"/",$L$1,"/",$L$2) -> 23/05/2026 | M26: =TEXT(L26,"ddd") -> sáb | N26: =SUMIF(C:C,L26,D:D) -> 46541.15 | P26: 23 | Q26: =_xlfn.CONCAT(P26,"/",$Q$1,"/",$Q$2) -> 23/06/2026 | R26: =TEXT(Q26,"ddd") -> ter | S26: =SUMIF(C:C,Q26,D:D) -> 35136.55 | U26: 23 | V26: =_xlfn.CONCAT(U26,"/",$V$1,"/",$V$2) -> 23/07/2026 | W26: =TEXT(V26,"ddd") -> qui | X26: =SUMIF(C:C,V26,D:D) -> 29929.84
A27: JULIO ANDO CIA LTDA | B27: 164999 4 | C27: 46149 | D27: 3024.7 | F27: 24 | G27: =_xlfn.CONCAT(F27,"/",$G$1,"/",$G$2) -> 24/04/2026 | H27: =TEXT(G27,"ddd") -> sex | I27: =SUMIF(C:C,G27,D:D) -> 0 | K27: 24 | L27: =_xlfn.CONCAT(K27,"/",$L$1,"/",$L$2) -> 24/05/2026 | M27: =TEXT(L27,"ddd") -> dom | N27: =SUMIF(C:C,L27,D:D) -> 27578.46 | P27: 24 | Q27: =_xlfn.CONCAT(P27,"/",$Q$1,"/",$Q$2) -> 24/06/2026 | R27: =TEXT(Q27,"ddd") -> qua | S27: =SUMIF(C:C,Q27,D:D) -> 12786 | U27: 24 | V27: =_xlfn.CONCAT(U27,"/",$V$1,"/",$V$2) -> 24/07/2026 | W27: =TEXT(V27,"ddd") -> sex | X27: =SUMIF(C:C,V27,D:D) -> 12786
A28: JULIO ANDO CIA LTDA | B28: 165093 4 | C28: 46149 | D28: 5968.71 | F28: 25 | G28: =_xlfn.CONCAT(F28,"/",$G$1,"/",$G$2) -> 25/04/2026 | H28: =TEXT(G28,"ddd") -> sáb | I28: =SUMIF(C:C,G28,D:D) -> 0 | K28: 25 | L28: =_xlfn.CONCAT(K28,"/",$L$1,"/",$L$2) -> 25/05/2026 | M28: =TEXT(L28,"ddd") -> seg | N28: =SUMIF(C:C,L28,D:D) -> 29002.69 | P28: 25 | Q28: =_xlfn.CONCAT(P28,"/",$Q$1,"/",$Q$2) -> 25/06/2026 | R28: =TEXT(Q28,"ddd") -> qui | S28: =SUMIF(C:C,Q28,D:D) -> 51193.3 | U28: 25 | V28: =_xlfn.CONCAT(U28,"/",$V$1,"/",$V$2) -> 25/07/2026 | W28: =TEXT(V28,"ddd") -> sáb | X28: =SUMIF(C:C,V28,D:D) -> 46632.72
A29: JULIO ANDO CIA LTDA | B29: 165074 4 | C29: 46149 | D29: 2299.91 | F29: 26 | G29: =_xlfn.CONCAT(F29,"/",$G$1,"/",$G$2) -> 26/04/2026 | H29: =TEXT(G29,"ddd") -> dom | I29: =SUMIF(C:C,G29,D:D) -> 0 | K29: 26 | L29: =_xlfn.CONCAT(K29,"/",$L$1,"/",$L$2) -> 26/05/2026 | M29: =TEXT(L29,"ddd") -> ter | N29: =SUMIF(C:C,L29,D:D) -> 44266.05 | P29: 26 | Q29: =_xlfn.CONCAT(P29,"/",$Q$1,"/",$Q$2) -> 26/06/2026 | R29: =TEXT(Q29,"ddd") -> sex | S29: =SUMIF(C:C,Q29,D:D) -> 13248.14 | U29: 26 | V29: =_xlfn.CONCAT(U29,"/",$V$1,"/",$V$2) -> 26/07/2026 | W29: =TEXT(V29,"ddd") -> dom | X29: =SUMIF(C:C,V29,D:D) -> 13248.16
A30: NEW BOX EMBALAGENS | B30: 30509 003 | C30: 46149 | D30: 2959.84 | F30: 27 | G30: =_xlfn.CONCAT(F30,"/",$G$1,"/",$G$2) -> 27/04/2026 | H30: =TEXT(G30,"ddd") -> seg | I30: =SUMIF(C:C,G30,D:D) -> 0 | K30: 27 | L30: =_xlfn.CONCAT(K30,"/",$L$1,"/",$L$2) -> 27/05/2026 | M30: =TEXT(L30,"ddd") -> qua | N30: =SUMIF(C:C,L30,D:D) -> 21244.07 | P30: 27 | Q30: =_xlfn.CONCAT(P30,"/",$Q$1,"/",$Q$2) -> 27/06/2026 | R30: =TEXT(Q30,"ddd") -> sáb | S30: =SUMIF(C:C,Q30,D:D) -> 53497.31 | U30: 27 | V30: =_xlfn.CONCAT(U30,"/",$V$1,"/",$V$2) -> 27/07/2026 | W30: =TEXT(V30,"ddd") -> seg | X30: =SUMIF(C:C,V30,D:D) -> 55604.06
A31: KALF IND COM PLASTICOS LTDA | B31: 123825 | C31: 46149 | D31: 582.13 | F31: 28 | G31: =_xlfn.CONCAT(F31,"/",$G$1,"/",$G$2) -> 28/04/2026 | H31: =TEXT(G31,"ddd") -> ter | I31: =SUMIF(C:C,G31,D:D) -> 0 | K31: 28 | L31: =_xlfn.CONCAT(K31,"/",$L$1,"/",$L$2) -> 28/05/2026 | M31: =TEXT(L31,"ddd") -> qui | N31: =SUMIF(C:C,L31,D:D) -> 53787.48 | P31: 28 | Q31: =_xlfn.CONCAT(P31,"/",$Q$1,"/",$Q$2) -> 28/06/2026 | R31: =TEXT(Q31,"ddd") -> dom | S31: =SUMIF(C:C,Q31,D:D) -> 10333.94 | U31: 28 | V31: =_xlfn.CONCAT(U31,"/",$V$1,"/",$V$2) -> 28/07/2026 | W31: =TEXT(V31,"ddd") -> ter | X31: =SUMIF(C:C,V31,D:D) -> 3906.74
A32: JULIO ANDO CIA LTDA | B32: 177140 1 | C32: 46149 | D32: 632.31 | F32: 29 | G32: =_xlfn.CONCAT(F32,"/",$G$1,"/",$G$2) -> 29/04/2026 | H32: =TEXT(G32,"ddd") -> qua | I32: =SUMIF(C:C,G32,D:D) -> 0 | K32: 29 | L32: =_xlfn.CONCAT(K32,"/",$L$1,"/",$L$2) -> 29/05/2026 | M32: =TEXT(L32,"ddd") -> sex | N32: =SUMIF(C:C,L32,D:D) -> 13798.54 | P32: 29 | Q32: =_xlfn.CONCAT(P32,"/",$Q$1,"/",$Q$2) -> 29/06/2026 | R32: =TEXT(Q32,"ddd") -> seg | S32: =SUMIF(C:C,Q32,D:D) -> 19284.55 | U32: 29 | V32: =_xlfn.CONCAT(U32,"/",$V$1,"/",$V$2) -> 29/07/2026 | W32: =TEXT(V32,"ddd") -> qua | X32: =SUMIF(C:C,V32,D:D) -> 12737.92
A33: NEW BOX EMBALAGENS | B33: 30926 001 | C33: 46149 | D33: 1775.9 | F33: 30 | G33: =_xlfn.CONCAT(F33,"/",$G$1,"/",$G$2) -> 30/04/2026 | H33: =TEXT(G33,"ddd") -> qui | I33: =SUMIF(C:C,G33,D:D) -> 0 | K33: 30 | L33: =_xlfn.CONCAT(K33,"/",$L$1,"/",$L$2) -> 30/05/2026 | M33: =TEXT(L33,"ddd") -> sáb | N33: =SUMIF(C:C,L33,D:D) -> 17177.8 | P33: 30 | Q33: =_xlfn.CONCAT(P33,"/",$Q$1,"/",$Q$2) -> 30/06/2026 | R33: =TEXT(Q33,"ddd") -> ter | S33: =SUMIF(C:C,Q33,D:D) -> 13434.05 | U33: 30 | V33: =_xlfn.CONCAT(U33,"/",$V$1,"/",$V$2) -> 30/07/2026 | W33: =TEXT(V33,"ddd") -> qui | X33: =SUMIF(C:C,V33,D:D) -> 13434.03
A34: BLUE CYCLE | B34: 403908 | C34: 46149 | D34: 2770.07 | F34: 31 | G34: =_xlfn.CONCAT(F34,"/",$G$1,"/",$G$2) -> 31/04/2026 | H34: =TEXT(G34,"ddd") -> 31/04/2026 | I34: =SUMIF(C:C,G34,D:D) -> 0 | K34: 31 | L34: =_xlfn.CONCAT(K34,"/",$L$1,"/",$L$2) -> 31/05/2026 | M34: =TEXT(L34,"ddd") -> dom | N34: =SUMIF(C:C,L34,D:D) -> 10030.29 | P34: 31 | Q34: =_xlfn.CONCAT(P34,"/",$Q$1,"/",$Q$2) -> 31/06/2026 | R34: =TEXT(Q34,"ddd") -> 31/06/2026 | S34: =SUMIF(C:C,Q34,D:D) -> 0 | U34: 31 | V34: =_xlfn.CONCAT(U34,"/",$V$1,"/",$V$2) -> 31/07/2026 | W34: =TEXT(V34,"ddd") -> sex | X34: =SUMIF(C:C,V34,D:D) -> 10842
A35: FMD -SECURITIZADORA S A | B35: 1324-001 | C35: 46149 | D35: 18093.31
A36: FLAY INDUSTRIA E COMERCIO LTDA | B36: 5237 - 1 | C36: 46149 | D36: 4288.74
A37: GRAFIMAX INDUSTRIA GRAFICA LTDA | B37: 1.28996-1/3 | C37: 46149 | D37: 1463.18
A38: EXCELLENCE TRANSP E LOGISTICA LTDA | B38: 3097455 | C38: 46149 | D38: 83.72
A39: NEW BIKE | B39: CJ714 001 | C39: 46149 | D39: 12247.5
A40: SPEED TECNET | B40: 700487653 | C40: 46149 | D40: 783.6
A41: JULIO ANDO CIA LTDA | B41: 165267 4 | C41: 46150 | D41: 1522.38
A42: JULIO ANDO CIA LTDA | B42: 165287 7 | C42: 46150 | D42: 5461.88
A43: AROSUL IND COM DE PECAS | B43: 052633-2/4 | C43: 46150 | D43: 1874.61
A44: ATLANTA FUNDO DE INV EM DIR CRED N PAD | B44: 074518-002 | C44: 46150 | D44: 1033.09
A45: M A F COM DE ARTIGOS DE PAPELA | B45: 124209 | C45: 46150 | D45: 31.9
A46: URBANO SA SOC CRED FINAN INVES | B46: 2604121753 | C46: 46150 | D46: 289.62
A47: FMD FUNDO DE INVESTIMENTO EM DIREITOS CR | B47: 1346-001 | C47: 46151 | D47: 4599.99
A48: M A F COM DE ARTIGOS DE PAPELA | B48: 124377 | C48: 46151 | D48: 142.22
A49: FMD FUNDO DE INVESTIMENTO EM DIREITOS CR | B49: 1345-001 | C49: 46151 | D49: 5663.99
A50: WB BIKE INDUSTRIA E COMERCIO LTDA | B50: 004690/01 | C50: 46151 | D50: 1573.33
A51: JHC COM DE PECAS E ACESS P BICICLETAS LTDA | B51: 112701 | C51: 46151 | D51: 3941.28
A52: VEGA DISTRIBUIDORA LTDA | B52: 21502 | C52: 46152 | D52: 3496
A53: LUMASA EMBALAGENS LTDA | B53: 505-3 | C53: 46152 | D53: 3513.52
A54: ISAPA IMP.E COM.LTDA. | B54: 48879801 | C54: 46152 | D54: 19816.59
A55: PM DE ARAPONGAS | B55: 31384848 | C55: 46153 | D55: 569.32
A56: PM DE ARAPONGAS | B56: 32425375 | C56: 46153 | D56: 569.32
A57: J ALVES JAQUES COM. DE PECAS E ACESS. BICIC | B57: 127582 | C57: 46153 | D57: 1757.28
A58: JR COMERCIO B ACESSORIOS LTDA | B58: 172403 2 | C58: 46153 | D58: 6308.1
A59: JULIO ANDO E CIA LTDA | B59: 173676 2 | C59: 46153 | D59: 14214.78
A60: FLAY INDUSTRIA E COMERCIO LTDA | B60: 5126 - 2 | C60: 46153 | D60: 1987.5
A61: KALF IND COM PLASTICOS LTDA | B61: 1236502 | C61: 46153 | D61: 757.43
A62: FLAY INDUSTRIA E COMERCIO LTDA | B62: 5261 - 1 | C62: 46153 | D62: 2654.51
A63: NEW BOX EMBALAGENS | B63: 30530 003 | C63: 46154 | D63: 2959.84
A64: AROSUL INDUSTRIA E COMERCIO DE PECAS EIRELLI - EPP | B64: 052654.2.4 | C64: 46154 | D64: 2621.86
A65: K. MORI COMERCIO DE EXPORTACAO E IMPORTACAO DE EQU | B65: 016345-2/2 | C65: 46154 | D65: 2440.82
A66: KLS IND E COM DE BICICLETAS | B66: 1096562 | C66: 46154 | D66: 1235.66
A67: GRAFIMAX INDUSTRIA GRAFICA LTDA | B67: 1.28770-3/3 | C67: 46154 | D67: 3659.07
A68: JR COMERCIO DE BICICLETAS E ACESSORIOS L | B68: 165650 4 | C68: 46155 | D68: 1550.5
A69: JR COMERCIO DE BICICLETAS E ACESSORIOS L | B69: 165629 4 | C69: 46155 | D69: 448.5
A70: JR COMERCIO DE BICICLETAS E ACESSORIOS L | B70: 175569 1 | C70: 46155 | D70: 502.15
A71: LUMASA EMBALAGENS LTDA | B71: 536-1 | C71: 46155 | D71: 1768.61
A72: ISAPA IMP.E COM.LTDA. | B72: 490923 | C72: 46155 | D72: 3504.91
A73: M A F COM DE ARTIGOS DE PAPELA | B73: 124957 | C73: 46156 | D73: 37
A74: WB BIKE INDUSTRIA E COMERCIO LTDA | B74: 004700/01 | C74: 46156 | D74: 2674.66
A75: FMD -SECURITIZADORA S A | B75: 1356-001 | C75: 46156 | D75: 2066.66
A76: NEW BOX EMBALAGENS | B76: 30978 001 | C76: 46156 | D76: 1817.34
A77: KALF IND COM PLASTICOS LTDA | B77: 123920 | C77: 46156 | D77: 873.19
A78: AROSUL IND COM DE PECAS | B78: 052684-2/3 | C78: 46157 | D78: 2800.65
A79: JR COMERCIO DE BICICLETAS E ACESSORIOS L | B79: 175875 1 | C79: 46157 | D79: 6549.03
A80: ISAPA IMPORTACAO E COMERCIO LTDA | B80: 48975401 | C80: 46157 | D80: 20373.92
A81: JULIO ANDO CIA LTDA | B81: 178194 1 | C81: 46157 | D81: 1683.47
A82: NEW BOX EMBALAGENS | B82: 30995 001 | C82: 46157 | D82: 2782.24
A83: FLAY INDUSTRIA E COMERCIO LTDA | B83: 5294 - 1 | C83: 46157 | D83: 4288.74
A84: BLUE CYCLE | B84: 404580 | C84: 46157 | D84: 732.52
A85: CONECTTIVA TELECOM LTDA ME | B85: 1867031 | C85: 46157 | D85: 149.9
A86: LUBRIARA COMERCIO DE LUBRIFI | B86: 1691 | C86: 46157 | D86: 1159.4
A87: J A GOMES DE SOUZA | B87: 126061 | C87: 46157 | D87: 4721.2
A88: JHC COM DE PECAS E ACESS P BICICLETAS LTDA | B88: 112731 | C88: 46157 | D88: 2064.48
A89: URBANO SA SOC CRED FINAN INVES | B89: 2604162538 | C89: 46157 | D89: 798.19
A90: JULIO ANDO CIA LTDA | B90: 164721 9 | C90: 46158 | D90: 2911.3
A91: JR COMERCIO DE BICICLETAS E ACESSORIOS L | B91: 166137 4 | C91: 46158 | D91: 826.62
A92: JULIO ANDO CIA LTDA | B92: 166592 4 | C92: 46158 | D92: 3005.1
A93: FMD -SECURITIZADORA S A | B93: P5550-002 | C93: 46158 | D93: 5663.99
A94: FMD FUNDO DE INVESTIMENTO EM DIREITOS CR | B94: 14101-002 | C94: 46158 | D94: 3199.68
A95: FMD -SECURITIZADORA S A | B95: P14101-002 | C95: 46158 | D95: 3199.68
A96: FMD FUNDO DE INVESTIMENTO EM DIREITOS CR | B96: 5550-002 | C96: 46158 | D96: 1888
A97: AD FLEX ETIQUETAS LTDA | B97: 3198 | C97: 46158 | D97: 616
A98: ISAPA IMP.E COM.LTDA. | B98: 64490001 | C98: 46158 | D98: 1462.56
A99: ISAPA IMP.E COM.LTDA. | B99: 48992401 | C99: 46158 | D99: 3095.01
A100: JHC COM DE PECAS E ACESS P BICICLETAS LTDA | B100: 112761 | C100: 46158 | D100: 7882.56
...

Sheet RECEBIDOS
A1: Banco | B1: Data | C1: Descrição | D1: Documento | E1: Valor (R$) | F1: Mktplace | H1: Mês | I1: Saldo | J1: Recebido Mês
A2: Sicredi | B2: 02/04/2026 | C2: RECEBIMENTO PIX 48697278000196 GOTT SAUDE COMERC | D2: PIX_CRED | E2: 20435 | H2: Abril | I2: 73659.53 | J2: =SUM(J4:J34) -> 883700.3 | L2: Mês de Competência | M2: Entradas | N2: Saídas | O2: Fluxo de Caixa
A3: Sicredi | B3: 06/04/2026 | C3: RECEBIMENTO PIX 48697278000196 GOTT SAUDE COMERC | D3: PIX_CRED | E3: 13502 | H3: Data | I3: Dia | J3: Recebido
A4: Sicredi | B4: 06/04/2026 | C4: GETNET CREDITO MASTER | GETNET | 0001-96 | D4: 819244258 | E4: 82.59 | H4: 46113 | I4: =H4 -> 46113 | J4: =SUMIF(B:B,H4,E:E) -> 0 | L4: =H2 -> Abril | M4: =J2 -> 883700.3 | N4: 851256.72 | O4: =M4-N4 -> 32443.58
A5: Sicredi | B5: 06/04/2026 | C5: RECEBIMENTO PIX 13884775000119 HUB INSTITUICAO D | D5: PIX_CRED | E5: 266.32 | H5: 46114 | I5: =H5 -> 46114 | J5: =SUMIF(B:B,H5,E:E) -> 20435 | M5: =M4/N14 -> 0.6874504
A6: Sicredi | B6: 06/04/2026 | C6: RECEBIMENTO PIX 48697278000196 GOTT SAUDE COMERC | D6: PIX_CRED | E6: 46650 | H6: 46115 | I6: =H6 -> 46115 | J6: =SUMIF(B:B,H6,E:E) -> 0
A7: Sicredi | B7: 07/04/2026 | C7: RECEBIMENTO PIX 27415911000136 Bytedance Brasil | D7: PIX_CRED | E7: 542.97 | H7: 46116 | I7: =H7 -> 46116 | J7: =SUMIF(B:B,H7,E:E) -> 0 | L7: =L2 -> Mês de Competência | M7: Saldo Inicial Conta | N7: Saldo Final Conta | O7: Fluxo de Conta
A8: Sicredi | B8: 07/04/2026 | C8: RECEBIMENTO PIX 48697278000196 GOTT SAUDE COMERC | D8: PIX_CRED | E8: 50000 | H8: 46117 | I8: =H8 -> 46117 | J8: =SUMIF(B:B,H8,E:E) -> 0
A9: Sicredi | B9: 08/04/2026 | C9: RECEBIMENTO PIX SICREDI 42965989000118 L A T SHO | D9: CX297608 | E9: 350 | H9: 46118 | I9: =H9 -> 46118 | J9: =SUMIF(B:B,H9,E:E) -> 60500.91 | L9: =L4 -> Abril | M9: 41217.95 | N9: =I2 -> 73659.53 | O9: =N9-M9 -> 32441.58
A10: Sicredi | B10: 08/04/2026 | C10: RECEBIMENTO PIX 48697278000196 GOTT SAUDE COMERC | D10: PIX_CRED | E10: 24769 | H10: 46119 | I10: =H10 -> 46119 | J10: =SUMIF(B:B,H10,E:E) -> 50542.97
A11: Sicredi | B11: 46121 | C11: TED 61074175000138 MAPFRE SEGUROS GERAIS S.A. | D11: 739614 | E11: 469.86 | H11: 46120 | I11: =H11 -> 46120 | J11: =SUMIF(B:B,H11,E:E) -> 25119
A12: Sicredi | B12: 46121 | C12: RECEBIMENTO PIX 48697278000196 GOTT SAUDE COMERC | D12: PIX_CRED | E12: 50000 | H12: 46121 | I12: =H12 -> 46121 | J12: =SUMIF(B:B,H12,E:E) -> 50469.86 | L12: =L7 -> Mês de Competência | M12: Meta Faturamento Bruto | N12: Faturamento Bruto | O12: Desempenho da Meta
A13: Sicredi | B13: 46122 | C13: GETNET CREDITO VISA | GETNET | 0001-96 | D13: 821732437 | E13: 2290.28 | H13: 46122 | I13: =H13 -> 46122 | J13: =SUMIF(B:B,H13,E:E) -> 8076.39
A14: Sicredi | B14: 46122 | C14: GETNET CREDITO ELO | GETNET | 0001-96 | D14: 821732411 | E14: 479.72 | H14: 46123 | I14: =H14 -> 46123 | J14: =SUMIF(B:B,H14,E:E) -> 0 | L14: =L9 -> Abril | M14: 1500000 | N14: 1285475 | O14: =N14/M14 -> 0.85698333
A15: Sicredi | B15: 46122 | C15: GETNET CREDITO MASTER | GETNET | 0001-96 | D15: 821732424 | E15: 2690.03 | H15: 46124 | I15: =H15 -> 46124 | J15: =SUMIF(B:B,H15,E:E) -> 0
A16: Sicredi | B16: 10/04/2026 | C16: RECEBIMENTO PIX 08584116000127 WEBCONTINENTAL LT | D16: PIX_CRED | E16: 2476.36 | H16: 46125 | I16: =H16 -> 46125 | J16: =SUMIF(B:B,H16,E:E) -> 52990.14 | L16: bikes | M16: 2130 | N16: 1667 | O16: =M16-N16 -> 463
A17: Sicredi | B17: 10/04/2026 | C17: RECEBIMENTO PIX 57436421000187 57.436.421 AUDINE | D17: PIX_CRED | E17: 140 | H17: 46126 | I17: =H17 -> 46126 | J17: =SUMIF(B:B,H17,E:E) -> 707.92
A18: Sicredi | B18: 13/04/2026 | C18: RECEBIMENTO PIX 48697278000196 GOTT SAUDE COMERC | D18: PIX_CRED | E18: 24850 | H18: 46127 | I18: =H18 -> 46127 | J18: =SUMIF(B:B,H18,E:E) -> 50000
A19: Sicredi | B19: 13/04/2026 | C19: RECEBIMENTO PIX 27415911000136 Bytedance Brasil | D19: PIX_CRED | E19: 256.14 | H19: 46128 | I19: =H19 -> 46128 | J19: =SUMIF(B:B,H19,E:E) -> 113089.92 | L19: Mês de Competência | M19: Entradas | N19: Saídas | O19: Fluxo de Caixa
A20: Sicredi | B20: 46125 | C20: RECEBIMENTO PIX 48697278000196 GOTT SAUDE COMERC | D20: PIX_CRED | E20: 27884 | H20: 46129 | I20: =H20 -> 46129 | J20: =SUMIF(B:B,H20,E:E) -> 42189 | L20: Março | M20: 1036116.5 | N20: 991713.58 | O20: 44402.94
A21: Sicredi | B21: 14/04/2026 | C21: RECEBIMENTO PIX 27415911000136 Bytedance Brasil | D21: PIX_CRED | E21: 707.92 | H21: 46130 | I21: =H21 -> 46130 | J21: =SUMIF(B:B,H21,E:E) -> 0
A22: Sicredi | B22: 46127 | C22: RECEBIMENTO PIX 48697278000196 GOTT SAUDE COMERC | D22: PIX_CRED | E22: 50000 | H22: 46131 | I22: =H22 -> 46131 | J22: =SUMIF(B:B,H22,E:E) -> 0
A23: Sicredi | B23: 46128 | C23: RECEBIMENTO PIX 48697278000196 GOTT SAUDE COMERC | D23: PIX_CRED | E23: 82039 | H23: 46132 | I23: =H23 -> 46132 | J23: =SUMIF(B:B,H23,E:E) -> 51153.36 | L23: Mês de Competência | M23: Saldo Inicial | N23: Saldo Final | O23: Fluxo de Conta
A24: Sicredi | B24: 46128 | C24: RECEBIMENTO PIX 48697278000196 GOTT SAUDE COMERC | D24: PIX_CRED | E24: 30409 | H24: 46133 | I24: =H24 -> 46133 | J24: =SUMIF(B:B,H24,E:E) -> 0 | L24: Março | M24: -3932.19 | N24: 41217.95 | O24: 45150.14
A25: Sicredi | B25: 46128 | C25: RECEBIMENTO PIX 27415911000136 Bytedance Brasil | D25: PIX_CRED | E25: 641.92 | H25: 46134 | I25: =H25 -> 46134 | J25: =SUMIF(B:B,H25,E:E) -> 141158.12
A26: Sicredi | B26: 17/04/2026 | C26: RECEBIMENTO PIX 48697278000196 GOTT SAUDE COMERC | D26: PIX_CRED | E26: 42189 | H26: 46135 | I26: =H26 -> 46135 | J26: =SUMIF(B:B,H26,E:E) -> 54913
A27: Sicredi | B27: 46132 | C27: GETNET CREDITO VISA | GETNET | 0001-96 | D27: 825395361 | E27: 5771.86 | H27: 46136 | I27: =H27 -> 46136 | J27: =SUMIF(B:B,H27,E:E) -> 40462
A28: Sicredi | B28: 46132 | C28: GETNET CREDITO ELO | GETNET | 0001-96 | D28: 825395626 | E28: 751.55 | H28: 46137 | I28: =H28 -> 46137 | J28: =SUMIF(B:B,H28,E:E) -> 0
A29: Sicredi | B29: 46132 | C29: GETNET CREDITO MASTER | GETNET | 0001-96 | D29: 825395623 | E29: 8083.68 | H29: 46138 | I29: =H29 -> 46138 | J29: =SUMIF(B:B,H29,E:E) -> 0
A30: Sicredi | B30: 46132 | C30: GETNET CREDITO MASTER | GETNET | 0001-96 | D30: 825395350 | E30: 1312.2 | H30: 46139 | I30: =H30 -> 46139 | J30: =SUMIF(B:B,H30,E:E) -> 14676.54
A31: Sicredi | B31: 46132 | C31: GETNET CREDITO VISA | GETNET | 0001-96 | D31: 825395662 | E31: 678.51 | H31: 46140 | I31: =H31 -> 46140 | J31: =SUMIF(B:B,H31,E:E) -> 71423
A32: Sicredi | B32: 46132 | C32: GETNET CREDITO MASTER | GETNET | 0001-96 | D32: 825395646 | E32: 616.95 | H32: 46141 | I32: =H32 -> 46141 | J32: =SUMIF(B:B,H32,E:E) -> 33906.17
A33: Sicredi | B33: 46132 | C33: GETNET CREDITO AMEX | GETNET | 0001-96 | D33: 825395374 | E33: 553.13 | H33: 46142 | I33: =H33 -> 46142 | J33: =SUMIF(B:B,H33,E:E) -> 1887
A34: Sicredi | B34: 20/04/2026 | C34: RECEBIMENTO PIX 13884775000119 HUB INSTITUICAO D | D34: PIX_CRED | E34: 1451.48 | I34: =H34 -> 0 | J34: =SUMIF(B:B,H34,E:E) -> 0
A35: Sicredi | B35: 20/04/2026 | C35: RECEBIMENTO PIX 48697278000196 GOTT SAUDE COMERC | D35: PIX_CRED | E35: 31934
A36: Sicredi | B36: 46134 | C36: TED 33041260065290 GRUPO CASAS BAHIA S A | D36: 459370 | E36: 81158.12
A37: Sicredi | B37: 46134 | C37: RECEBIMENTO PIX 48697278000196 GOTT SAUDE COMERC | D37: PIX_CRED | E37: 50000
A38: Sicredi | B38: 46134 | C38: RECEBIMENTO PIX 48697278000196 GOTT SAUDE COMERC | D38: PIX_CRED | E38: 10000
A39: Sicredi | B39: 46135 | C39: RECEBIMENTO PIX 48697278000196 GOTT SAUDE COMERC | D39: PIX_CRED | E39: 4563
A40: Sicredi | B40: 46135 | C40: RECEBIMENTO PIX 45990586000117 TAC STORE | D40: PIX_CRED | E40: 350 | L40: Meta do Mês de abr/26
A41: Sicredi | B41: 46135 | C41: RECEBIMENTO PIX 48697278000196 GOTT SAUDE COMERC | D41: PIX_CRED | E41: 50000
A42: Sicredi | B42: 46136 | C42: RECEBIMENTO PIX 48697278000196 GOTT SAUDE COMERC | D42: PIX_CRED | E42: 23554 | L42: Faturamento R$ 1.500.000,00
A43: Sicredi | B43: 24/04/2026 | C43: RECEBIMENTO PIX 48697278000196 GOTT SAUDE COMERC | D43: PIX_CRED | E43: 16908
A44: Sicredi | B44: 27/04/2026 | C44: RECEBIMENTO PIX 42580969896 MARCOS DOUGLAS NOGUE | D44: PIX_CRED | E44: 250 | L44: 2.130 bikes
A45: Sicredi | B45: 46139 | C45: RECEBIMENTO PIX 48697278000196 GOTT SAUDE COMERC | D45: PIX_CRED | E45: 7770
A46: Sicredi | B46: 46139 | C46: RECEBIMENTO PIX 08584116000127 WEBCONTINENTAL LT | D46: PIX_CRED | E46: 1456.54
A47: Sicredi | B47: 46139 | C47: RECEBIMENTO PIX 48697278000196 GOTT SAUDE COMERC | D47: PIX_CRED | E47: 5200
A48: Sicredi | B48: 46140 | C48: RECEBIMENTO PIX 48697278000196 GOTT SAUDE COMERC | D48: PIX_CRED | E48: 21423
A49: Sicredi | B49: 46140 | C49: RECEBIMENTO PIX 48697278000196 GOTT SAUDE COMERC | D49: PIX_CRED | E49: 50000
A50: Sicredi | B50: 46141 | C50: RECEBIMENTO PIX 48697278000196 GOTT SAUDE COMERC | D50: PIX_CRED | E50: 8200
A51: Sicredi | B51: 46141 | C51: RECEBIMENTO PIX 48697278000196 GOTT SAUDE COMERC | D51: PIX_CRED | E51: 10000
A52: Sicredi | B52: 46141 | C52: RECEBIMENTO PIX 48697278000196 GOTT SAUDE COMERC | D52: PIX_CRED | E52: 15630
A53: Sicredi | B53: 46141 | C53: RECEBIMENTO PIX 27415911000136 Bytedance Brasil | D53: PIX_CRED | E53: 76.17
A54: Sicredi | B54: 30/04/2026 | C54: RECEBIMENTO PIX SICREDI 42989044000136 INUSITTA | D54: CX201949 | E54: 1120
A55: Sicredi | B55: 30/04/2026 | C55: RECEBIMENTO PIX 40318112841 Felipe Guedes da Sil | D55: PIX_CRED | E55: 33.5
A56: Sicredi | B56: 30/04/2026 | C56: RECEBIMENTO PIX 27415911000136 Bytedance Brasil | D56: PIX_CRED | E56: 733.5

Sheet COMPARATIVOS
B1: jan | C1: fev | D1: mar | E1: abr | F1: mai | G1: jun | H1: jul | I1: ago | J1: set | K1: out | L1: nov | M1: dez
A2: FATURAMENTO BRUTO 2025 | B2: 189017.45 | C2: 275579.51 | D2: 964961.41 | E2: 583899.22 | F2: 662010.94 | G2: 885159.23 | H2: 868491.23 | I2: 885285.93 | J2: 1150688.3 | K2: 1207207 | L2: 1594226.2 | M2: 1443037.2
A3: FATURAMENTO BRUTO 2026 | B3: 1101552 | C3: 936890.74 | D3: 1373580.8
A4: VARIAÇÃO 26X25 | B4: =IFERROR(B3/B2-1,0) -> 4.8277795 | C4: =IFERROR(C3/C2-1,0) -> 2.3997112 | D4: =IFERROR(D3/D2-1,0) -> 0.42345673
B24: jan | C24: fev | D24: mar | E24: abr | F24: mai | G24: jun | H24: jul | I24: ago | J24: set | K24: out | L24: nov | M24: dez
A25: BIKES FATURADAS 2025 | B25: 282 | C25: 471 | D25: 1435 | E25: 814 | F25: 921 | G25: 1142 | H25: 1313 | I25: 1291 | J25: 1765 | K25: 1825 | L25: 2268 | M25: 2185
A26: BIKES FATURADAS 2026 | B26: 1647 | C26: 1330 | D26: 1877
A27: VARIAÇÃO 26X25 | B27: =IFERROR(B26/B25-1,0) -> 4.8404255 | C27: =IFERROR(C26/C25-1,0) -> 1.8237792 | D27: =IFERROR(D26/D25-1,0) -> 0.30801394
B47: out/25 | D47: nov/25 | F47: dez/25 | H47: jan/26 | J47: 46054
B48: R$ | C48: A.V. | D48: R$ | E48: A.V. | F48: R$ | G48: A.V. | H48: R$ | I48: A.V. | J48: R$ | K48: A.V.
A49: TOTAL FATURADO | B49: =SUM(B50:B59) -> 1137554.1 | C49: =IFERROR(B49/$H$49,0) -> 1.0363134 | D49: =SUM(D50:D59) -> 1453565.2 | E49: =IFERROR(D49/$H$49,0) -> 1.3242 | F49: =SUM(F50:F59) -> 1358251.7 | G49: =IFERROR(F49/$H$49,0) -> 1.2373692 | H49: =SUM(H50:H59) -> 1097693.1 | I49: =IFERROR(H49/$H$49,0) -> 1 | J49: =SUM(J50:J59) -> 936890.74 | K49: =IFERROR(J49/$J$49,0) -> 1
A50: SHOPEE | B50: 710617.19 | C50: =IFERROR(B50/$H$49,0) -> 0.64737327 | D50: 1003857.3 | E50: =IFERROR(D50/$H$49,0) -> 0.91451542 | F50: 1143229.9 | G50: =IFERROR(F50/$H$49,0) -> 1.041484 | H50: 878335.15 | I50: =IFERROR(H50/$H$49,0) -> 0.80016457 | J50: 815488.19 | K50: =IFERROR(J50/$J$49,0) -> 0.87041974 | L50: 777103.83 | M50: -45599.04 | N50: 50000 | O50: 781504.79
A51: AMAZON | B51: 1538 | C51: =IFERROR(B51/$H$49,0) -> 0.0014011202 | D51: 2117 | E51: =IFERROR(D51/$H$49,0) -> 0.00192859 | G51: =IFERROR(F51/$H$49,0) -> 0 | H51: 0 | I51: =IFERROR(H51/$H$49,0) -> 0 | J51: 2696 | K51: =IFERROR(J51/$J$49,0) -> 0.0028776034
A52: MAGALU | B52: 82235.32 | C52: =IFERROR(B52/$H$49,0) -> 0.074916493 | D52: 124166.39 | E52: =IFERROR(D52/$H$49,0) -> 0.11311576 | F52: 35919.19 | G52: =IFERROR(F52/$H$49,0) -> 0.032722433 | H52: 19002.9 | I52: =IFERROR(H52/$H$49,0) -> 0.017311669 | J52: 8376.37 | K52: =IFERROR(J52/$J$49,0) -> 0.008940605
A53: MELI | B53: 315559.54 | C53: =IFERROR(B53/$H$49,0) -> 0.28747519 | D53: 210466.92 | E53: =IFERROR(D53/$H$49,0) -> 0.19173566 | F53: 44802.23 | G53: =IFERROR(F53/$H$49,0) -> 0.040814895 | H53: 46735.55 | I53: =IFERROR(H53/$H$49,0) -> 0.042576152 | J53: 11496.08 | K53: =IFERROR(J53/$J$49,0) -> 0.01227046
A54: NETSHOES | B54: 2493.1 | C54: =IFERROR(B54/$H$49,0) -> 0.0022712176 | D54: 2050.05 | E54: =IFERROR(D54/$H$49,0) -> 0.0018675985 | F54: 2024.1 | G54: =IFERROR(F54/$H$49,0) -> 0.001843958 | H54: 1532 | I54: =IFERROR(H54/$H$49,0) -> 0.0013956542 | J54: 2567 | K54: =IFERROR(J54/$J$49,0) -> 0.0027399139 | L54: Janeiro | O54: Janeiro
A55: TIKTOK | C55: =IFERROR(B55/$H$49,0) -> 0 | E55: =IFERROR(D55/$H$49,0) -> 0 | F55: 2626 | G55: =IFERROR(F55/$H$49,0) -> 0.0023922897 | H55: 3270 | I55: =IFERROR(H55/$H$49,0) -> 0.0029789746 | J55: 4619.3 | K55: =IFERROR(J55/$J$49,0) -> 0.0049304575 | L55: Carnê Digital / Cartão de Crédito | O55: Pix / Cartão Presente / Nubank
A56: VIA VAREJO | B56: 17303.1 | C56: =IFERROR(B56/$H$49,0) -> 0.015763149 | D56: 105336.25 | E56: =IFERROR(D56/$H$49,0) -> 0.095961473 | F56: 126380.2 | G56: =IFERROR(F56/$H$49,0) -> 0.11513254 | H56: 143471.63 | I56: =IFERROR(H56/$H$49,0) -> 0.13070286 | J56: 87751.8 | K56: =IFERROR(J56/$J$49,0) -> 0.093662789 | L56: 99100 | M56: 83200 | O56: 59321 | P56: 49830
A57: NEXTSHOP | C57: =IFERROR(B57/$H$49,0) -> 0 | E57: =IFERROR(D57/$H$49,0) -> 0 | G57: =IFERROR(F57/$H$49,0) -> 0 | H57: 1399 | I57: =IFERROR(H57/$H$49,0) -> 0.001274491 | J57: 0 | K57: =IFERROR(J57/$J$49,0) -> 0
A58: WEB CONTINENTAL | B58: 7807.88 | C58: =IFERROR(B58/$H$49,0) -> 0.0071129898 | D58: 5571.35 | E58: =IFERROR(D58/$H$49,0) -> 0.0050755078 | F58: 1672.08 | G58: =IFERROR(F58/$H$49,0) -> 0.0015232673 | H58: 3946.9 | I58: =IFERROR(H58/$H$49,0) -> 0.0035956315 | J58: 3896 | K58: =IFERROR(J58/$J$49,0) -> 0.0041584358
A59: CENTAURO | C59: =IFERROR(B59/$H$49,0) -> 0 | E59: =IFERROR(D59/$H$49,0) -> 0 | F59: 1598 | G59: =IFERROR(F59/$H$49,0) -> 0.0014557803 | I59: =IFERROR(H59/$H$49,0) -> 0 | K59: =IFERROR(J59/$J$49,0) -> 0
B61: out/25 | D61: nov/25 | F61: dez/25 | H61: jan/26 | J61: 46054
B62: R$ | C62: A.V. | D62: R$ | E62: A.V. | F62: R$ | G62: A.V. | H62: R$ | I62: A.V. | J62: R$ | K62: A.V.
A63: TOTAL RECEBIDO | B63: =SUM(B64:B72) -> 1051608.4 | C63: =IFERROR(B63/$H$49,0) -> 0.95801673 | D63: =SUM(D64:D72) -> 881367.09 | E63: =IFERROR(D63/$H$49,0) -> 0.80292667 | F63: =SUM(F64:F72) -> 1057975.4 | G63: =IFERROR(F63/$H$49,0) -> 0.96381713 | H63: =SUM(H64:H72) -> 872469.19 | I63: =IFERROR(H63/$H$63,0) -> 1 | J63: =SUM(J64:J72) -> 678773.05 | K63: =IFERROR(J63/$J$63,0) -> 1 | M63: =J49-J63 -> 258117.69
A64: SHOPEE | B64: 573515.5 | C64: =IFERROR(B64/$B$63,0) -> 0.54536985 | D64: 619369.09 | E64: =IFERROR(D64/$D$63,0) -> 0.7027368 | F64: 977743.02 | G64: =IFERROR(F64/$F$63,0) -> 0.92416419 | H64: 777103.83 | I64: =IFERROR(H64/$H$63,0) -> 0.89069487 | J64: 597013 | K64: =IFERROR(J64/$J$63,0) -> 0.87954729
A65: AMAZON | C65: =IFERROR(B65/$B$63,0) -> 0 | E65: =IFERROR(D65/$D$63,0) -> 0 | G65: =IFERROR(F65/$F$63,0) -> 0 | H65: 0 | I65: =IFERROR(H65/$H$63,0) -> 0 | J65: 0 | K65: =IFERROR(J65/$J$63,0) -> 0
A66: MAGALU | B66: 54734.07 | C66: =IFERROR(B66/$B$63,0) -> 0.052047959 | D66: 93530.54 | E66: =IFERROR(D66/$D$63,0) -> 0.10611985 | F66: 25250.5 | G66: =IFERROR(F66/$F$63,0) -> 0.023866811 | H66: 22805.34 | I66: =IFERROR(H66/$H$63,0) -> 0.026138849 | J66: 26055.41 | K66: =IFERROR(J66/$J$63,0) -> 0.038386041
A67: MELI | B67: 397000 | C67: =IFERROR(B67/$B$63,0) -> 0.37751696 | D67: 156210 | E67: =IFERROR(D67/$D$63,0) -> 0.17723603 | F67: 49400 | G67: =IFERROR(F67/$F$63,0) -> 0.046692955 | H67: 33580.54 | I67: =IFERROR(H67/$H$63,0) -> 0.038489084 | J67: 0 | K67: =IFERROR(J67/$J$63,0) -> 0
A68: NETSHOES | B68: 620.59 | C68: =IFERROR(B68/$B$63,0) -> 0.00059013413 | E68: =IFERROR(D68/$D$63,0) -> 0 | F68: 4.46 | G68: =IFERROR(F68/$F$63,0) -> 4.2155988e-06 | H68: 0 | I68: =IFERROR(H68/$H$63,0) -> 0 | J68: 0 | K68: =IFERROR(J68/$J$63,0) -> 0
A69: TIKTOK | C69: =IFERROR(B69/$B$63,0) -> 0 | E69: =IFERROR(D69/$D$63,0) -> 0 | G69: =IFERROR(F69/$F$63,0) -> 0 | H69: 0 | I69: =IFERROR(H69/$H$63,0) -> 0 | J69: 5164.94 | K69: =IFERROR(J69/$J$63,0) -> 0.0076092296
A70: VIA VAREJO | B70: 25738.22 | C70: =IFERROR(B70/$B$63,0) -> 0.0244751 | D70: 10160.24 | E70: =IFERROR(D70/$D$63,0) -> 0.011527819 | F70: 2877.48 | G70: =IFERROR(F70/$F$63,0) -> 0.0027197985 | H70: 37472.77 | I70: =IFERROR(H70/$H$63,0) -> 0.04295025 | J70: 50103.94 | K70: =IFERROR(J70/$J$63,0) -> 0.073815453
A71: NEXTSHOP | C71: =IFERROR(B71/$B$63,0) -> 0 | E71: =IFERROR(D71/$D$63,0) -> 0 | G71: =IFERROR(F71/$F$63,0) -> 0 | H71: 0 | I71: =IFERROR(H71/$H$63,0) -> 0 | J71: 0 | K71: =IFERROR(J71/$J$63,0) -> 0
A72: WEB CONTINENTAL | C72: =IFERROR(B72/$B$63,0) -> 0 | D72: 2097.22 | E72: =IFERROR(D72/$D$63,0) -> 0.002379508 | F72: 2699.98 | G72: =IFERROR(F72/$F$63,0) -> 0.0025520252 | H72: 1506.71 | I72: =IFERROR(H72/$H$63,0) -> 0.0017269492 | J72: 435.76 | K72: =IFERROR(J72/$J$63,0) -> 0.00064198188
A73: CENTAURO | C73: =IFERROR(B73/$B$63,0) -> 0 | E73: =IFERROR(D73/$D$63,0) -> 0 | G73: =IFERROR(F73/$F$63,0) -> 0 | I73: =IFERROR(H73/$H$63,0) -> 0 | K73: =IFERROR(J73/$J$49,0) -> 0
B75: out/25 | D75: nov/25 | F75: dez/25 | H75: jan/26 | J75: 46054
A76: % RECEBIDO | B76: =IFERROR(B63/B49,0) -> 0.92444689 | D76: =IFERROR(D63/D49,0) -> 0.60634849 | F76: =IFERROR(F63/F49,0) -> 0.77892445 | H76: =IFERROR(H63/H49,0) -> 0.79482067 | J76: =IFERROR(J63/J49,0) -> 0.72449542
A77: SHOPEE | B77: =IFERROR(B64/B50,0) -> 0.80706674 | D77: =IFERROR(D64/D50,0) -> 0.61698918 | F77: =IFERROR(F64/F50,0) -> 0.85524622 | H77: =IFERROR(H64/H50,0) -> 0.88474636 | J77: =IFERROR(J64/J50,0) -> 0.73209276
A78: AMAZON | B78: =IFERROR(B65/B51,0) -> 0 | D78: =IFERROR(D65/D51,0) -> 0 | F78: =IFERROR(F65/F51,0) -> 0 | H78: =IFERROR(H65/H51,0) -> 0 | J78: =IFERROR(J65/J51,0) -> 0
A79: MAGALU | B79: =IFERROR(B66/B52,0) -> 0.66557861 | D79: =IFERROR(D66/D52,0) -> 0.75326777 | F79: =IFERROR(F66/F52,0) -> 0.70298077 | H79: =IFERROR(H66/H52,0) -> 1.2000979 | J79: =IFERROR(J66/J52,0) -> 3.1105849
A80: MELI | B80: =IFERROR(B67/B53,0) -> 1.2580827 | D80: =IFERROR(D67/D53,0) -> 0.7422069 | F80: =IFERROR(F67/F53,0) -> 1.1026237 | H80: =IFERROR(H67/H53,0) -> 0.71852241 | J80: =IFERROR(J67/J53,0) -> 0
A81: NETSHOES | B81: =IFERROR(B68/B54,0) -> 0.24892303 | D81: =IFERROR(D68/D54,0) -> 0 | F81: =IFERROR(F68/F54,0) -> 0.0022034484 | H81: =IFERROR(H68/H54,0) -> 0 | J81: =IFERROR(J68/J54,0) -> 0
A82: TIKTOK | B82: =IFERROR(B69/B55,0) -> 0 | D82: =IFERROR(D69/D55,0) -> 0 | F82: =IFERROR(F69/F55,0) -> 0 | H82: =IFERROR(H69/H55,0) -> 0 | J82: =IFERROR(J69/J55,0) -> 1.1181218
A83: VIA VAREJO | B83: =IFERROR(B70/B56,0) -> 1.4874918 | D83: =IFERROR(D70/D56,0) -> 0.096455304 | F83: =IFERROR(F70/F56,0) -> 0.02276844 | H83: =IFERROR(H70/H56,0) -> 0.26118592 | J83: =IFERROR(J70/J56,0) -> 0.57097336
A84: NEXTSHOP | B84: =IFERROR(B71/B57,0) -> 0 | D84: =IFERROR(D71/D57,0) -> 0 | F84: =IFERROR(F71/F57,0) -> 0 | H84: =IFERROR(H71/H57,0) -> 0 | J84: =IFERROR(J71/J57,0) -> 0
A85: WEB CONTINENTAL | B85: =IFERROR(B72/B58,0) -> 0 | D85: =IFERROR(D72/D58,0) -> 0.37642941 | F85: =IFERROR(F72/F58,0) -> 1.6147433 | H85: =IFERROR(H72/H58,0) -> 0.38174517 | J85: =IFERROR(J72/J58,0) -> 0.11184805
A86: CENTAURO | B86: =IFERROR(B73/B59,0) -> 0 | D86: =IFERROR(D73/D59,0) -> 0 | F86: =IFERROR(F73/F59,0) -> 0 | H86: =IFERROR(H73/H59,0) -> 0 | J86: =IFERROR(J73/J59,0) -> 0
B88: out/25 | D88: nov/25 | F88: dez/25 | H88: jan/26 | J88: 46054
B89: R$ | C89: A.V. | D89: R$ | E89: A.V. | F89: R$ | G89: A.V. | H89: R$ | I89: A.V. | J89: R$ | K89: A.V.
A90: A RECEBER | B90: =SUM(B91:B99) -> 0 | C90: =IFERROR(B90/$H$63,0) -> 0 | D90: =SUM(D91:D99) -> 0 | E90: =IFERROR(D90/$H$63,0) -> 0 | F90: =SUM(F91:F99) -> 0 | G90: =IFERROR(F90/$H$63,0) -> 0 | H90: =SUM(H91:H99) -> 0 | I90: =IFERROR(H90/$H$63,0) -> 0 | J90: =SUM(J91:J99) -> 162175.9 | K90: =IFERROR(J90/$J$63,0) -> 0.23892507
A91: SHOPEE | C91: =IFERROR(B91/$H$63,0) -> 0 | E91: =IFERROR(D91/$H$63,0) -> 0 | G91: =IFERROR(F91/$H$63,0) -> 0 | I91: =IFERROR(H91/$H$63,0) -> 0 | J91: 19281 | K91: =IFERROR(J91/$J$63,0) -> 0.028405665
A92: AMAZON | C92: =IFERROR(B92/$H$63,0) -> 0 | E92: =IFERROR(D92/$H$63,0) -> 0 | G92: =IFERROR(F92/$H$63,0) -> 0 | I92: =IFERROR(H92/$H$63,0) -> 0 | J92: 3800 | K92: =IFERROR(J92/$J$63,0) -> 0.0055983366
A93: MAGALU | C93: =IFERROR(B93/$H$63,0) -> 0 | E93: =IFERROR(D93/$H$63,0) -> 0 | G93: =IFERROR(F93/$H$63,0) -> 0 | I93: =IFERROR(H93/$H$63,0) -> 0 | J93: 14839 | K93: =IFERROR(J93/$J$63,0) -> 0.021861504
A94: MELI | C94: =IFERROR(B94/$H$63,0) -> 0 | E94: =IFERROR(D94/$H$63,0) -> 0 | G94: =IFERROR(F94/$H$63,0) -> 0 | I94: =IFERROR(H94/$H$63,0) -> 0 | J94: 20617 | K94: =IFERROR(J94/$J$63,0) -> 0.030373922
A95: NETSHOES | C95: =IFERROR(B95/$H$63,0) -> 0 | E95: =IFERROR(D95/$H$63,0) -> 0 | G95: =IFERROR(F95/$H$63,0) -> 0 | I95: =IFERROR(H95/$H$63,0) -> 0 | J95: 4408 | K95: =IFERROR(J95/$J$63,0) -> 0.0064940704
A96: TIKTOK | C96: =IFERROR(B96/$H$63,0) -> 0 | E96: =IFERROR(D96/$H$63,0) -> 0 | G96: =IFERROR(F96/$H$63,0) -> 0 | I96: =IFERROR(H96/$H$63,0) -> 0 | J96: 3355 | K96: =IFERROR(J96/$J$63,0) -> 0.0049427419
A97: VIA VAREJO | C97: =IFERROR(B97/$H$63,0) -> 0 | E97: =IFERROR(D97/$H$63,0) -> 0 | G97: =IFERROR(F97/$H$63,0) -> 0 | I97: =IFERROR(H97/$H$63,0) -> 0 | J97: 84775.9 | K97: =IFERROR(J97/$J$63,0) -> 0.1248958 | L97: Somente boleto
A98: NEXTSHOP | C98: =IFERROR(B98/$H$63,0) -> 0 | E98: =IFERROR(D98/$H$63,0) -> 0 | G98: =IFERROR(F98/$H$63,0) -> 0 | I98: =IFERROR(H98/$H$63,0) -> 0 | J98: 1100 | K98: =IFERROR(J98/$J$63,0) -> 0.0016205711
A99: WEB CONTINENTAL | C99: =IFERROR(B99/$H$63,0) -> 0 | E99: =IFERROR(D99/$H$63,0) -> 0 | G99: =IFERROR(F99/$H$63,0) -> 0 | I99: =IFERROR(H99/$H$63,0) -> 0 | J99: 10000 | K99: =IFERROR(J99/$J$63,0) -> 0.014732465
A103: Classificar o contas a pagar
A104: Lançar o CPV
A105: Estoque de Peças
A106: Estoque de P.A.
A107: Estoque de P.A. no Full

Sheet FATURAS
B2: VCTO | C2: DESCRIÇÃO | D2: VALOR | E2: CLASSIFICAÇÃO | G2: VCTO | H2: (Tudo)
B3: 46066 | C3: Shopee | D3: 1500 | E3: ADS SHOPEE
B4: 46066 | C4: Shopee | D4: 1500 | E4: ADS SHOPEE | G4: CLASSIFICAÇÃO | H4: Soma de VALOR
B5: 46066 | C5: Shopee | D5: 1800 | E5: ADS SHOPEE | G5: ADS MAGALU | H5: 5200
B6: 46066 | C6: Shopee | D6: 1800 | E6: ADS SHOPEE | G6: ADS SHOPEE | H6: 39900
B7: 46066 | C7: Churrascaria Herança | D7: 641 | E7: ALIMENTAÇÃO | G7: ALIMENTAÇÃO | H7: 7604.21
B8: 46066 | C8: Padaria Chij | D8: 23 | E8: ALIMENTAÇÃO | G8: ASSINATURAS | H8: 13165.6
B9: 46066 | C9: Restaurante Abençoado | D9: 69.27 | E9: ALIMENTAÇÃO | G9: COMBUSTÍVEL | H9: 2929.73
B10: 46066 | C10: Adobe | D10: 169 | E10: ASSINATURAS | G10: COMISSÕES E TAXAS DOS MARKETPLACES | H10: 5269.82
B11: 46066 | C11: BR1 China Lin Do Brasil | D11: 1600 | E11: ASSINATURAS | G11: COMPRA DE MÓVEIS E UTENSÍLIOS | H11: 552.41
B12: 46066 | C12: Pro TeamViewer (Parc 2/10) | D12: 58.8 | E12: ASSINATURAS | G12: DESP DE MARKETING E PROPAGANDA | H12: 1305
B13: 46066 | C13: Sem Parar | D13: 64.7 | E13: ASSINATURAS | G13: DESPESAS DE VIAGEM | H13: 16647.49
B14: 46066 | C14: Vindi Tray Ecommerce (Parc 4/6) | D14: 269.99 | E14: ASSINATURAS | G14: DESPESAS MANUTENCAO VEICULOS | H14: 3411.06
B15: 46066 | C15: Auto Posto Verona | D15: 340.54 | E15: COMBUSTÍVEL | G15: ESTACIONAMENTO | H15: 639
B16: 46066 | C16: Malassise Ribeirete | D16: 187.98 | E16: COMBUSTÍVEL | G16: FERRAMENTAS PARA MANUTENÇÃO | H16: 5109
... B24: 46066 | C24: Hotel San Gabriel | D24: 772 | E24: DESPESAS DE VIAGEM | G24: Total Geral | H24: 200228.59
B25: 46066 | C25: Rancho do Tiothor | D25: 51.97 | E25: DESPESAS DE VIAGEM
B26: 46066 | C26: Rodo Stop | D26: 23.1 | E26: DESPESAS DE VIAGEM
B27: 46066 | C27: Uber | D27: 45.97 | E27: DESPESAS DE VIAGEM
B28: 46066 | C28: Uber | D28: 27.98 | E28: DESPESAS DE VIAGEM
B29: 46066 | C29: Uber | D29: 115 | E29: DESPESAS DE VIAGEM
B30: 46066 | C30: Uber (pendente) | D30: 35.98 | E30: DESPESAS DE VIAGEM
B31: 46066 | C31: Villa Country | D31: 210 | E31: DESPESAS DE VIAGEM
B32: 46066 | C32: MP Motortech (Parc 2/3) | D32: 1705.52 | E32: DESPESAS MANUTENCAO VEICULOS
B33: 46066 | C33: DR Comércio de Tintas | D33: 759 | E33: FERRAMENTAS PARA MANUTENÇÃO
B34: 46066 | C34: Superfer Comercial | D34: 2175 | E34: FERRAMENTAS PARA MANUTENÇÃO
B35: 46066 | C35: Keb Continental (Virtual) | D35: 35 | E35: OUTRAS DESPESAS ADMINISTRATIVAS
B36: 46066 | C36: MercadoLivre | D36: 54.55 | E36: OUTRAS DESPESAS ADMINISTRATIVAS
... B282: 46094 | C282: Vindi Trayecommer | D282: 269.99 | E282: ASSINATURAS

Sheet MÉTRICAS
B1: DEMONSTARATIVO DE RESULTADOS GOTT | C1: 45931 | D1: 45962 | E1: 45992 | F1: 46023 | G1: 46054 | H1: 46082
A2: Gráfico linha | B2: =DRE!B3 -> (+) FATURAMENTO BRUTO | C2: =DRE!C3 -> 1207207 | D2: =DRE!E3 -> 1594226.2 | E2: =DRE!H3 -> 1443037.2 | F2: =DRE!K3 -> 1101552 | G2: =DRE!N3 -> 936890.74 | H2: =DRE!Q3 -> 1373580.8
A3: Gráfico coluna | B3: =DRE!B3 -> (+) FATURAMENTO BRUTO | C3: =IFERROR(C2/C2,0) -> 1 | D3: =IFERROR(D2/D2,0) -> 1 | E3: =IFERROR(E2/E2,0) -> 1 | F3: =IFERROR(F2/F2,0) -> 1 | G3: =IFERROR(G2/G2,0) -> 1 | H3: =IFERROR(H2/H2,0) -> 1
A5: Gráfico linha | B5: =DRE!B4 -> (-) IMPOSTOS S/ VENDAS | C5: =DRE!C4 -> 35650.83 | D5: =DRE!E4 -> 21104.11 | E5: =DRE!H4 -> 19335 | F5: =DRE!K4 -> 15811.61 | G5: =DRE!N4 -> 14053.361 | H5: =DRE!Q4 -> 29702.17
A6: Gráfico coluna | B6: =DRE!B4 -> (-) IMPOSTOS S/ VENDAS | C6: =IFERROR(C5/C2,0) -> 0.029531663 | D6: =IFERROR(D5/D2,0) -> 0.013237839 | E6: =IFERROR(E5/E2,0) -> 0.013398823 | F6: =IFERROR(F5/F2,0) -> 0.014353939 | G6: =IFERROR(G5/G2,0) -> 0.015 | H6: =IFERROR(H5/H2,0) -> 0.021623897
A8: Gráfico linha | B8: =DRE!B5 -> (-) DEVOLUÇÕES | C8: =DRE!C5 -> 0 | D8: =DRE!E5 -> 0 | E8: =DRE!H5 -> 0 | F8: =DRE!K5 -> 0 | G8: =DRE!N5 -> 0 | H8: =DRE!Q5 -> 0
A9: Gráfico coluna | B9: =DRE!B5 -> (-) DEVOLUÇÕES | C9: =IFERROR(C8/C2,0) -> 0 | D9: =IFERROR(D8/D2,0) -> 0 | E9: =IFERROR(E8/E2,0) -> 0 | F9: =IFERROR(F8/F2,0) -> 0 | G9: =IFERROR(G8/G2,0) -> 0 | H9: =IFERROR(H8/H2,0) -> 0
A11: Gráfico linha | B11: =DRE!B6 -> (-) DESPESAS COM TRANSPORTE | C11: =DRE!C6 -> 9199.86 | D11: =DRE!E6 -> 1174.88 | E11: =DRE!H6 -> 6687.27 | F11: =DRE!K6 -> 20376.21 | G11: =DRE!N6 -> 31195.07 | H11: =DRE!Q6 -> 23710.91
A12: Gráfico coluna | B12: =DRE!B6 -> (-) DESPESAS COM TRANSPORTE | C12: =IFERROR(C11/C2,0) -> 0.0076207809 | D12: =IFERROR(D11/D2,0) -> 0.00073695939 | E12: =IFERROR(E11/E2,0) -> 0.0046341633 | F12: =IFERROR(F11/F2,0) -> 0.018497728 | G12: =IFERROR(G11/G2,0) -> 0.03329638 | H12: =IFERROR(H11/H2,0) -> 0.017262115
A14: Gráfico linha | B14: =DRE!B10 -> (-) RECEITA OPERACIONAL LÍQUIDA | C14: =DRE!C10 -> 1162356.3 | D14: =DRE!E10 -> 1571947.2 | E14: =DRE!H10 -> 1417014.9 | F14: =DRE!K10 -> 1065364.2 | G14: =DRE!N10 -> 891642.31 | H14: =DRE!Q10 -> 1320167.7
A15: Gráfico coluna | B15: =DRE!B10 -> (-) RECEITA OPERACIONAL LÍQUIDA | C15: =IFERROR(C14/C2,0) -> 0.96284756 | D15: =IFERROR(D14/D2,0) -> 0.9860252 | E15: =IFERROR(E14/E2,0) -> 0.98196701 | F15: =IFERROR(F14/F2,0) -> 0.96714833 | G15: =IFERROR(G14/G2,0) -> 0.95170362 | H15: =IFERROR(H14/H2,0) -> 0.96111399
A17: Gráfico linha | B17: =DRE!B11 -> (-) CUSTOS VARIÁVEIS OPERACIONAIS | C17: =DRE!C11 -> 923317.34 | D17: =DRE!E11 -> 1282104.1 | E17: =DRE!H11 -> 1119132.4 | F17: =DRE!K11 -> 865095.17 | G17: =DRE!N11 -> 755745.51 | H17: =DRE!Q11 -> 1074369.7
A18: Gráfico coluna | B18: =DRE!B11 -> (-) CUSTOS VARIÁVEIS OPERACIONAIS | C18: =IFERROR(C17/C2,0) -> 0.76483764 | D18: =IFERROR(D17/D2,0) -> 0.80421716 | E18: =IFERROR(E17/E2,0) -> 0.77553956 | F18: =IFERROR(F17/F2,0) -> 0.7853421 | G18: =IFERROR(G17/G2,0) -> 0.80665277 | H18: =IFERROR(H17/H2,0) -> 0.7821671
A20: Gráfico linha | B20: =DRE!B12 -> (-) CUSTO DOS PRODUTOS VENDIDOS | C20: =DRE!C12 -> 707593.72 | D20: =DRE!E12 -> 998625.2 | E20: =DRE!H12 -> 857572.81 | F20: =DRE!K12 -> 667576.62 | G20: =DRE!N12 -> 577935.69 | H20: =DRE!Q12 -> 817037.46
A21: Gráfico coluna | B21: =DRE!B12 -> (-) CUSTO DOS PRODUTOS VENDIDOS | C21: =IFERROR(C20/C2,0) -> 0.58614117 | D21: =IFERROR(D20/D2,0) -> 0.62640118 | E21: =IFERROR(E20/E2,0) -> 0.59428323 | F21: =IFERROR(F20/F2,0) -> 0.60603277 | G21: =IFERROR(G20/G2,0) -> 0.61686562 | H21: =IFERROR(H20/H2,0) -> 0.594823
A23: Gráfico linha | B23: =DRE!B13 -> (-) DESPESAS DE VENDA | C23: =DRE!C13 -> 215723.62 | D23: =DRE!E13 -> 283478.89 | E23: =DRE!H13 -> 261559.62 | F23: =DRE!K13 -> 197518.55 | G23: =DRE!N13 -> 177809.82 | H23: =DRE!Q13 -> 257332.26
A24: Gráfico coluna | B24: =DRE!B13 -> (-) DESPESAS DE VENDA | C24: =IFERROR(C23/C2,0) -> 0.17869647 | D24: =IFERROR(D23/D2,0) -> 0.17781597 | E24: =IFERROR(E23/E2,0) -> 0.18125633 | F24: =IFERROR(F23/F2,0) -> 0.17930933 | G24: =IFERROR(G23/G2,0) -> 0.18978715 | H24: =IFERROR(H23/H2,0) -> 0.1873441
A26: Gráfico linha | B26: =DRE!B21 -> (=) MARGEM DE CONTRIBUIÇÃO | C26: =DRE!C21 -> 239038.96 | D26: =DRE!E21 -> 289843.16 | E26: =DRE!H21 -> 297882.5 | F26: =DRE!K21 -> 200269.03 | G26: =DRE!N21 -> 135896.8 | H26: =DRE!Q21 -> 245798.01
A27: Gráfico coluna | B27: =DRE!B21 -> (=) MARGEM DE CONTRIBUIÇÃO | C27: =IFERROR(C26/C2,0) -> 0.19800992 | D27: =IFERROR(D26/D2,0) -> 0.18180805 | E27: =IFERROR(E26/E2,0) -> 0.20642746 | F27: =IFERROR(F26/F2,0) -> 0.18180624 | G27: =IFERROR(G26/G2,0) -> 0.14505085 | H27: =IFERROR(H26/H2,0) -> 0.17894689
A29: Gráfico linha | B29: =DRE!B22 -> (-) CUSTOS FIXOS OPERACIONAIS | C29: =DRE!C22 -> 93406.07 | D29: =DRE!E22 -> 104939.41 | E29: =DRE!H22 -> 108655.94 | F29: =DRE!K22 -> 119972.84 | G29: =DRE!N22 -> 119526.37 | H29: =DRE!Q22 -> 138043.59
A30: Gráfico coluna | B30: =DRE!B22 -> (-) CUSTOS FIXOS OPERACIONAIS | C30: =IFERROR(C29/C2,0) -> 0.077373699 | D30: =IFERROR(D29/D2,0) -> 0.065824666 | E30: =IFERROR(E29/E2,0) -> 0.075296701 | F30: =IFERROR(F29/F2,0) -> 0.10891255 | G30: =IFERROR(G29/G2,0) -> 0.1275777 | H30: =IFERROR(H29/H2,0) -> 0.10049907
A32: Gráfico linha | B32: =DRE!B23 -> (=) RESULTADO OPERACIONAL | C32: =DRE!C23 -> 145632.89 | D32: =DRE!E23 -> 184903.75 | E32: =DRE!H23 -> 189226.56 | F32: =DRE!K23 -> 80296.186 | G32: =DRE!N23 -> 16370.429 | H32: =DRE!Q23 -> 107754.42
A33: Gráfico coluna | B33: =DRE!B23 -> (=) RESULTADO OPERACIONAL | C33: =IFERROR(C32/C2,0) -> 0.12063622 | D33: =IFERROR(D32/D2,0) -> 0.11598338 | E33: =IFERROR(E32/E2,0) -> 0.13113076 | F33: =IFERROR(F32/F2,0) -> 0.072893685 | G33: =IFERROR(G32/G2,0) -> 0.017473147 | H33: =IFERROR(H32/H2,0) -> 0.078447819
A35: Gráfico linha | B35: =DRE!B24 -> (-) IMPOSTO SOBRE O LUCRO | C35: =DRE!C24 -> 0 | D35: =DRE!E24 -> 0 | E35: =DRE!H24 -> 0 | F35: =DRE!K24 -> 0 | G35: =DRE!N24 -> 0 | H35: =DRE!Q24 -> 0
A36: Gráfico coluna | B36: =DRE!B24 -> (-) IMPOSTO SOBRE O LUCRO | C36: =IFERROR(C35/C2,0) -> 0 | D36: =IFERROR(D35/D2,0) -> 0 | E36: =IFERROR(E35/E2,0) -> 0 | F36: =IFERROR(F35/F2,0) -> 0 | G36: =IFERROR(G35/G2,0) -> 0 | H36: =IFERROR(H35/H2,0) -> 0
A38: Gráfico linha | B38: =DRE!B25 -> (=) RESULTADO APÓS IMPOSTO SOBRE O LUCRO | C38: =DRE!C25 -> 145632.89 | D38: =DRE!E25 -> 184903.75 | E38: =DRE!H25 -> 189226.56 | F38: =DRE!K25 -> 80296.186 | G38: =DRE!N25 -> 16370.429 | H38: =DRE!Q25 -> 107754.42
A39: Gráfico coluna | B39: =DRE!B25 -> (=) RESULTADO APÓS IMPOSTO SOBRE O LUCRO | C39: =IFERROR(C38/C2,0) -> 0.12063622 | D39: =IFERROR(D38/D2,0) -> 0.11598338 | E39: =IFERROR(E38/E2,0) -> 0.13113076 | F39: =IFERROR(F38/F2,0) -> 0.072893685 | G39: =IFERROR(G38/G2,0) -> 0.017473147 | H39: =IFERROR(H38/H2,0) -> 0.078447819
A41: Gráfico linha | B41: =DRE!B26 -> (-) DESPESAS NÃO OPERACIONAIS | C41: =DRE!C26 -> 0 | D41: =DRE!E26 -> 0 | E41: =DRE!H26 -> 0 | F41: =DRE!K26 -> 0 | G41: =DRE!N26 -> 0 | H41: =DRE!Q26 -> 0
A42: Gráfico coluna | B42: =DRE!B26 -> (-) DESPESAS NÃO OPERACIONAIS | C42: =IFERROR(C41/C2,0) -> 0 | D42: =IFERROR(D41/D2,0) -> 0 | E42: =IFERROR(E41/E2,0) -> 0 | F42: =IFERROR(F41/F2,0) -> 0 | G42: =IFERROR(G41/G2,0) -> 0 | H42: =IFERROR(H41/H2,0) -> 0
A44: Gráfico linha | B44: =DRE!B27 -> (+) RECEITAS NÃO OPERACIONAIS | C44: =DRE!C27 -> 0 | D44: =DRE!E27 -> 0 | E44: =DRE!H27 -> 0 | F44: =DRE!K27 -> 0 | G44: =DRE!N27 -> 0 | H44: =DRE!Q27 -> 0
A45: Gráfico coluna | B45: =DRE!B27 -> (+) RECEITAS NÃO OPERACIONAIS | C45: =IFERROR(C44/C2,0) -> 0 | D45: =IFERROR(D44/D2,0) -> 0 | E45: =IFERROR(E44/E2,0) -> 0 | F45: =IFERROR(F44/F2,0) -> 0 | G45: =IFERROR(G44/G2,0) -> 0 | H45: =IFERROR(H44/H2,0) -> 0
A47: Gráfico linha | B47: =DRE!B28 -> (=) RESULTADO APÓS DESPESAS E RECEITAS NÃO OPERACIONAIS | C47: =DRE!C28 -> 145632.89 | D47: =DRE!E28 -> 184903.75 | E47: =DRE!H28 -> 189226.56 | F47: =DRE!K28 -> 80296.186 | G47: =DRE!N28 -> 16370.429 | H47: =DRE!Q28 -> 107754.42
A48: Gráfico coluna | B48: =DRE!B28 -> (=) RESULTADO APÓS DESPESAS E RECEITAS NÃO OPERACIONAIS | C48: =IFERROR(C47/C2,0) -> 0.12063622 | D48: =IFERROR(D47/D2,0) -> 0.11598338 | E48: =IFERROR(E47/E2,0) -> 0.13113076 | F48: =IFERROR(F47/F2,0) -> 0.072893685 | G48: =IFERROR(G47/G2,0) -> 0.017473147 | H48: =IFERROR(H47/H2,0) -> 0.078447819
A50: Gráfico linha | B50: =DRE!B29 -> (-) INVESTIMENTOS | C50: =DRE!C29 -> 21070.83 | D50: =DRE!E29 -> 15970.83 | E50: =DRE!H29 -> 16822.6 | F50: =DRE!K29 -> 0 | G50: =DRE!N29 -> 16154.96 | H50: =DRE!Q29 -> 32125.8
A51: Gráfico coluna | B51: =DRE!B29 -> (-) INVESTIMENTOS | C51: =IFERROR(C50/C2,0) -> 0.017454198 | D51: =IFERROR(D50/D2,0) -> 0.010017919 | E51: =IFERROR(E50/E2,0) -> 0.011657773 | F51: =IFERROR(F50/F2,0) -> 0 | G51: =IFERROR(G50/G2,0) -> 0.017243163 | H51: =IFERROR(H50/H2,0) -> 0.023388358
A53: Gráfico linha | B53: =DRE!B30 -> (-) AMORTIZAÇÕES | C53: =DRE!C30 -> 11652.6 | D53: =DRE!E30 -> 0 | E53: =DRE!H30 -> 18274 | F53: =DRE!K30 -> 32000 | G53: =DRE!N30 -> 13000 | H53: =DRE!Q30 -> 17747.62
A54: Gráfico coluna | B54: =DRE!B30 -> (-) AMORTIZAÇÕES | C54: =IFERROR(C53/C2,0) -> 0.0096525286 | D54: =IFERROR(D53/D2,0) -> 0 | E54: =IFERROR(E53/E2,0) -> 0.012663568 | F54: =IFERROR(F53/F2,0) -> 0.029049922 | G54: =IFERROR(G53/G2,0) -> 0.013875684 | H54: =IFERROR(H53/H2,0) -> 0.012920696
A56: Gráfico linha | B56: =DRE!B31 -> (=) RESULTADO ANTES DAS DISTRIBUIÇÕES | C56: =DRE!C31 -> 112909.46 | D56: =DRE!E31 -> 168932.92 | E56: =DRE!H31 -> 154129.96 | F56: =DRE!K31 -> 48296.186 | G56: =DRE!N31 -> -12784.531 | H56: =DRE!Q31 -> 57880.998
A57: Gráfico coluna | B57: =DRE!B31 -> (=) RESULTADO ANTES DAS DISTRIBUIÇÕES | C57: =IFERROR(C56/C2,0) -> 0.093529492 | D57: =IFERROR(D56/D2,0) -> 0.10596546 | E57: =IFERROR(E56/E2,0) -> 0.10680942 | F57: =IFERROR(F56/F2,0) -> 0.043843764 | G57: =IFERROR(G56/G2,0) -> -0.013645701 | H57: =IFERROR(H56/H2,0) -> 0.042138764
A59: Gráfico linha | B59: =DRE!B32 -> (-) DISTRIBUIÇÃO DE LUCROS & OUTROS | C59: =DRE!C32 -> 21445.72 | D59: =DRE!E32 -> 2067.41 | E59: =DRE!H32 -> 4407.37 | F59: =DRE!K32 -> 2067.37 | G59: =DRE!N32 -> 2110.78 | H59: =DRE!Q32 -> 5577.37
A60: Gráfico coluna | B60: =DRE!B32 -> (-) DISTRIBUIÇÃO DE LUCROS & OUTROS | C60: =IFERROR(C59/C2,0) -> 0.017764741 | D60: =IFERROR(D59/D2,0) -> 0.0012968109 | E60: =IFERROR(E59/E2,0) -> 0.0030542317 | F60: =IFERROR(F59/F2,0) -> 0.0018767793 | G60: =IFERROR(G59/G2,0) -> 0.0022529628 | H60: =IFERROR(H59/H2,0) -> 0.00406046
A62: Gráfico linha | B62: =DRE!B37 -> (=) RESULTADO APÓS DISTRIBUIÇÕES | C62: =DRE!C37 -> 91463.737 | D62: =DRE!E37 -> 166865.51 | E62: =DRE!H37 -> 149722.59 | F62: =DRE!K37 -> 46228.816 | G62: =DRE!N37 -> -14895.311 | H62: =DRE!Q37 -> 52303.628
A63: Gráfico coluna | B63: =DRE!B37 -> (=) RESULTADO APÓS DISTRIBUIÇÕES | C63: =IFERROR(C62/C2,0) -> 0.075764751 | D63: =IFERROR(D62/D2,0) -> 0.10466865 | E63: =IFERROR(E62/E2,0) -> 0.10375518 | F63: =IFERROR(F62/F2,0) -> 0.041966984 | G63: =IFERROR(G62/G2,0) -> -0.015898663 | H63: =IFERROR(H62/H2,0) -> 0.038078304
A65: Gráfico linha | B65: =B117 -> Ticket Médio de Venda | C65: =C117 -> 608.77811 | D65: =D117 -> 657.1419 | E65: =E117 -> 615.89296 | F65: =F117 -> 634.9003 | G65: =G117 -> 676.94418 | H65: =H117 -> 731.79585
A67: Gráfico linha | B67: =DRE!B39 -> (=) PONTO DE EQUILÍBRIO GERENCIAL | C67: =DRE!C39 -> 745292.06 | D67: =DRE!E39 -> 676414.78 | E67: =DRE!H39 -> 717733.54 | F67: =DRE!K39 -> 847276.82 | G67: =DRE!N39 -> 1039581 | H67: =DRE!Q39 -> 1081295
A68: Gráfico coluna | B68: PONTO DE EQUILÍBRIO GERENCIAL EM Nº DE BIKES FATURADAS | C68: =C67/C65 -> 1224.2425 | D68: =D67/D65 -> 1029.3283 | E68: =E67/E65 -> 1165.3544 | F68: =F67/F65 -> 1334.5037 | G68: =G67/G65 -> 1535.6968 | H68: =H67/H65 -> 1477.5911
A70: Gráfico linha | B70: =DRE!B40 -> (=) PONTO DE EQUILÍBRIO OPERACIONAL | C70: =DRE!C40 -> 471724.2 | D70: =DRE!E40 -> 577198.93 | E70: =DRE!H40 -> 526363.8 | F70: =DRE!K40 -> 659893.98 | G70: =DRE!N40 -> 824030.81 | H70: =DRE!Q40 -> 771422.14
A71: Gráfico coluna | B71: PONTO DE EQUILÍBRIO OPERACIONAL EM Nº DE BIKES FATURADAS | C71: =C70/C65 -> 774.8705 | D71: =D70/D65 -> 878.34748 | E71: =E70/E65 -> 854.63519 | F71: =F70/F65 -> 1039.3663 | G71: =G70/G65 -> 1217.2803 | H71: =H70/H65 -> 1054.1494
B73: DEMONSTRATIVO DE FLUXO DE CAIXA GOTT | C73: =C1 -> 45931 | D73: =D1 -> 45962 | E73: =E1 -> 45992 | F73: =F1 -> 46023 | G73: =G1 -> 46054 | H73: =H1 -> 46082
A74: Gráfico linha | B74: =DFC!A170 -> FLUXO DE CAIXA (ENTRADAS - SAÍDAS) | C74: =DFC!B170 -> -22623.92 | D74: =DFC!D170 -> -52069.95 | E74: =DFC!G170 -> 65393.6 | F74: =DFC!J170 -> -75586.46 | G74: =DFC!M170 -> -202048.76 | H74: =DFC!P170 -> 44402.94
A76: Gráfico coluna | B76: =DFC!A171 -> ENTRADAS NO MÊS | C76: =DFC!B171 -> 1123115.1 | D76: =DFC!D171 -> 1133990.4 | E76: =DFC!G171 -> 1298393.2 | F76: =DFC!J171 -> 1068022.3 | G76: =DFC!M171 -> 691744.49 | H76: =DFC!P171 -> 1036116.5
A77: Gráfico coluna | B77: =DFC!A172 -> SAÍDAS NO MÊS | C77: =-DFC!B172 -> -1145739.1 | D77: =-DFC!D172 -> -1186060.4 | E77: =-DFC!G172 -> -1232999.6 | F77: =-DFC!J172 -> -1143608.8 | G77: =-DFC!M172 -> -893793.25 | H77: =-DFC!P172 -> -991713.58
B79: ENTRADAS X FATURAMENTO | C79: =C1 -> 45931 | D79: =D1 -> 45962 | E79: =E1 -> 45992 | F79: =F1 -> 46023 | G79: =G1 -> 46054 | H79: =H1 -> 46082
A80: Gráfico linha | B80: =B2 -> (+) FATURAMENTO BRUTO | C80: =C2 -> 1207207 | D80: =D2 -> 1594226.2 | E80: =E2 -> 1443037.2 | F80: =F2 -> 1101552 | G80: =G2 -> 936890.74 | H80: =H2 -> 1373580.8
A81: Gráfico linha | B81: =B76 -> ENTRADAS NO MÊS | C81: =C76 -> 1123115.1 | D81: =D76 -> 1133990.4 | E81: =E76 -> 1298393.2 | F81: =F76 -> 1068022.3 | G81: =G76 -> 691744.49 | H81: =H76 -> 1036116.5
A82: Gráfico coluna | B82: INDICADOR ENTRADAS X FATURAMENTO | C82: =C81/C80 -> 0.93034181 | D82: =D81/D80 -> 0.71131086 | E82: =E81/E80 -> 0.8997642 | F82: =F81/F80 -> 0.96956139 | G82: =G81/G80 -> 0.73834062 | H82: =H81/H80 -> 0.75431785
B84: BIKES FATURADAS | C84: =C1 -> 45931 | D84: =D1 -> 45962 | E84: =E1 -> 45992 | F84: =F1 -> 46023 | G84: =G1 -> 46054 | H84: =H1 -> 46082
A85: Gráfico linha | B85: QUANTIDADE FATURADA TOTAL | C85: =CPV!B12 -> 1983 | D85: =CPV!E12 -> 2426 | E85: =CPV!H12 -> 2343 | F85: =CPV!K12 -> 1735 | G85: =CPV!N12 -> 1384 | H85: =CPV!Q12 -> 1877
A87: Gráfico linha | B87: CUSTO FICHA TÉCNICA | C87: =CPV!C12 -> 356.82991 | D87: =CPV!F12 -> 411.63446 | E87: =CPV!I12 -> 366.01486 | F87: =CPV!L12 -> 384.77039 | G87: =CPV!O12 -> 417.58359 | H87: =CPV!P12 -> 577935.69
A89: Gráfico linha | B89: CPV | C89: =CPV!D12 -> 707593.72 | D89: =CPV!G12 -> 998625.2 | E89: =CPV!J12 -> 857572.81 | F89: =CPV!M12 -> 667576.62 | G89: =CPV!P12 -> 577935.69 | H89: =CPV!S12 -> 817037.46
B91: BALANÇO PATRIMONIAL | C91: =C1 -> 45931 | D91: =D1 -> 45962 | E91: =E1 -> 45992 | F91: =F1 -> 46023 | G91: =G1 -> 46054 | H91: =H1 -> 46082
A92: Gráfico linha | B92: ='BALANÇO PATRIMONIAL'!B3 -> (+) Estoque Geral Preço de Custo | C92: ='BALANÇO PATRIMONIAL'!C3 -> 1870693 | D92: ='BALANÇO PATRIMONIAL'!E3 -> 1047609.1 | E92: ='BALANÇO PATRIMONIAL'!G3 -> 989532.32 | F92: ='BALANÇO PATRIMONIAL'!I3 -> 1484653.6 | G92: ='BALANÇO PATRIMONIAL'!K3 -> 1039728.8 | H92: ='BALANÇO PATRIMONIAL'!M3 -> 625302.89
B93: ='BALANÇO PATRIMONIAL'!B4 -> Estoque de Peças | C93: ='BALANÇO PATRIMONIAL'!C4 -> 1756895 | D93: ='BALANÇO PATRIMONIAL'!E4 -> 891913.41 | E93: ='BALANÇO PATRIMONIAL'!G4 -> 913788.12 | F93: ='BALANÇO PATRIMONIAL'!I4 -> 1254013 | G93: ='BALANÇO PATRIMONIAL'!K4 -> 698765.16 | H93: ='BALANÇO PATRIMONIAL'!M4 -> 547363.79
B94: ='BALANÇO PATRIMONIAL'!B5 -> Estoque de P.A. | C94: ='BALANÇO PATRIMONIAL'!C5 -> 102845 | D94: ='BALANÇO PATRIMONIAL'!E5 -> 7675 | E94: ='BALANÇO PATRIMONIAL'!G5 -> 0 | F94: ='BALANÇO PATRIMONIAL'!I5 -> 0 | G94: ='BALANÇO PATRIMONIAL'!K5 -> 186710.04 | H94: ='BALANÇO PATRIMONIAL'!M5 -> 0
B95: ='BALANÇO PATRIMONIAL'!B6 -> Estoque de P.A. no Full | C95: ='BALANÇO PATRIMONIAL'!C6 -> 10953.02 | D95: ='BALANÇO PATRIMONIAL'!E6 -> 148020.72 | E95: ='BALANÇO PATRIMONIAL'!G6 -> 75744.2 | F95: ='BALANÇO PATRIMONIAL'!I6 -> 230640.59 | G95: ='BALANÇO PATRIMONIAL'!K6 -> 154253.6 | H95: ='BALANÇO PATRIMONIAL'!M6 -> 77939.1
A97: Gráfico linha | B97: ='BALANÇO PATRIMONIAL'!B7 -> (+) Disponibilidades | C97: ='BALANÇO PATRIMONIAL'!C7 -> 60840.68 | D97: ='BALANÇO PATRIMONIAL'!E7 -> -73229.27 | E97: ='BALANÇO PATRIMONIAL'!G7 -> -87725.67 | F97: ='BALANÇO PATRIMONIAL'!I7 -> -288353.43 | G97: ='BALANÇO PATRIMONIAL'!K7 -> -488530.17 | H97: ='BALANÇO PATRIMONIAL'!M7 -> -445252.05
B98: ='BALANÇO PATRIMONIAL'!B8 -> Caixinha | C98: ='BALANÇO PATRIMONIAL'!C8 -> 0 | D98: ='BALANÇO PATRIMONIAL'!E8 -> 0 | E98: ='BALANÇO PATRIMONIAL'!G8 -> 0 | F98: ='BALANÇO PATRIMONIAL'!I8 -> 0 | G98: ='BALANÇO PATRIMONIAL'!K8 -> 0 | H98: ='BALANÇO PATRIMONIAL'!M8 -> 0
B99: ='BALANÇO PATRIMONIAL'!B9 -> Bradesco | C99: ='BALANÇO PATRIMONIAL'!C9 -> 0 | D99: ='BALANÇO PATRIMONIAL'!E9 -> 0 | E99: ='BALANÇO PATRIMONIAL'!G9 -> 0 | F99: ='BALANÇO PATRIMONIAL'!I9 -> 0 | G99: ='BALANÇO PATRIMONIAL'!K9 -> -199580 | H99: ='BALANÇO PATRIMONIAL'!M9 -> -199580
B100: ='BALANÇO PATRIMONIAL'!B10 -> Sicredi agência 0723 c/c 70.636-3 | C100: ='BALANÇO PATRIMONIAL'!C10 -> 60840.68 | D100: ='BALANÇO PATRIMONIAL'!E10 -> 8770.73 | E100: ='BALANÇO PATRIMONIAL'!G10 -> 74164.33 | F100: ='BALANÇO PATRIMONIAL'!I10 -> -1463.43 | G100: ='BALANÇO PATRIMONIAL'!K10 -> -2060.17 | H100: ='BALANÇO PATRIMONIAL'!M10 -> 41217.95
B101: ='BALANÇO PATRIMONIAL'!B11 -> Empréstimo Adonai | C101: ='BALANÇO PATRIMONIAL'!C11 -> 0 | D101: ='BALANÇO PATRIMONIAL'!E11 -> -82000 | E101: ='BALANÇO PATRIMONIAL'!G11 -> -161890 | F101: ='BALANÇO PATRIMONIAL'!I11 -> -226890 | G101: ='BALANÇO PATRIMONIAL'!K11 -> -226890 | H101: ='BALANÇO PATRIMONIAL'!M11 -> -226890
B102: ='BALANÇO PATRIMONIAL'!B12 -> Empréstimo Feedstock | C102: ='BALANÇO PATRIMONIAL'!C12 -> 0 | D102: ='BALANÇO PATRIMONIAL'!E12 -> 0 | E102: ='BALANÇO PATRIMONIAL'!G12 -> 0 | F102: ='BALANÇO PATRIMONIAL'!I12 -> -60000 | G102: ='BALANÇO PATRIMONIAL'!K12 -> -60000 | H102: ='BALANÇO PATRIMONIAL'!M12 -> -60000
A104: Gráfico linha | B104: ='BALANÇO PATRIMONIAL'!B13 -> (+) Contas a Receber | C104: ='BALANÇO PATRIMONIAL'!C13 -> 176774.24 | D104: ='BALANÇO PATRIMONIAL'!E13 -> 585872.25 | E104: ='BALANÇO PATRIMONIAL'!G13 -> 602832.77 | F104: ='BALANÇO PATRIMONIAL'!I13 -> 201831.94 | G104: ='BALANÇO PATRIMONIAL'!K13 -> 400000 | H104: ='BALANÇO PATRIMONIAL'!M13 -> 500000
B105: ='BALANÇO PATRIMONIAL'!B14 -> Contas a Receber em Atraso | C105: ='BALANÇO PATRIMONIAL'!C14 -> 0 | D105: ='BALANÇO PATRIMONIAL'!E14 -> 0 | E105: ='BALANÇO PATRIMONIAL'!G14 -> 0 | F105: ='BALANÇO PATRIMONIAL'!I14 -> 0 | G105: ='BALANÇO PATRIMONIAL'!K14 -> 0 | H105: ='BALANÇO PATRIMONIAL'!M14 -> 0
B106: ='BALANÇO PATRIMONIAL'!B15 -> Contas a Receber a Vencer | C106: ='BALANÇO PATRIMONIAL'!C15 -> 176774.24 | D106: ='BALANÇO PATRIMONIAL'!E15 -> 585872.25 | E106: ='BALANÇO PATRIMONIAL'!G15 -> 602832.77 | F106: ='BALANÇO PATRIMONIAL'!I15 -> 201831.94 | G106: ='BALANÇO PATRIMONIAL'!K15 -> 400000 | H106: ='BALANÇO PATRIMONIAL'!M15 -> 500000
A108: Gráfico linha | B108: ='BALANÇO PATRIMONIAL'!B16 -> (=) Total de Ativos | C108: ='BALANÇO PATRIMONIAL'!C16 -> 2108308 | D108: ='BALANÇO PATRIMONIAL'!E16 -> 1560252.1 | E108: ='BALANÇO PATRIMONIAL'!G16 -> 1504639.4 | F108: ='BALANÇO PATRIMONIAL'!I16 -> 1398132.1 | G108: ='BALANÇO PATRIMONIAL'!K16 -> 951198.63 | H108: ='BALANÇO PATRIMONIAL'!M16 -> 680050.84
A110: Gráfico linha | B110: ='BALANÇO PATRIMONIAL'!B17 -> (-) Contas a Pagar DDA | C110: ='BALANÇO PATRIMONIAL'!C17 -> 2460338.6 | D110: ='BALANÇO PATRIMONIAL'!E17 -> 1688812.4 | E110: ='BALANÇO PATRIMONIAL'!G17 -> 1513014.7 | F110: ='BALANÇO PATRIMONIAL'!I17 -> 1410399.3 | G110: ='BALANÇO PATRIMONIAL'!K17 -> 1030284.5 | H110: ='BALANÇO PATRIMONIAL'!M17 -> 708938.67
A112: Gráfico linha | B112: ='BALANÇO PATRIMONIAL'!B18 -> (=) Saldo Patrimonial | C112: ='BALANÇO PATRIMONIAL'!C18 -> -352030.6 | D112: ='BALANÇO PATRIMONIAL'!E18 -> -128560.24 | E112: ='BALANÇO PATRIMONIAL'!G18 -> -8375.26 | F112: ='BALANÇO PATRIMONIAL'!I18 -> -12267.22 | G112: ='BALANÇO PATRIMONIAL'!K18 -> -79085.87 | H112: ='BALANÇO PATRIMONIAL'!M18 -> -28887.83
B114: INDICADORES | C114: =C1 -> 45931 | D114: =D1 -> 45962 | E114: =E1 -> 45992 | F114: =F1 -> 46023 | G114: =G1 -> 46054 | H114: =H1 -> 46082
A115: Gráfico linha | B115: ='BALANÇO PATRIMONIAL'!B20 -> Variação das Disponibilidades | C115: ='BALANÇO PATRIMONIAL'!C20 -> 0 | D115: ='BALANÇO PATRIMONIAL'!E20 -> -134069.95 | E115: ='BALANÇO PATRIMONIAL'!G20 -> -14496.4 | F115: ='BALANÇO PATRIMONIAL'!I20 -> -200627.76 | G115: ='BALANÇO PATRIMONIAL'!K20 -> -200176.74 | H115: ='BALANÇO PATRIMONIAL'!M20 -> 43278.12
A117: Gráfico linha | B117: Ticket Médio de Venda | C117: =DRE!C3/C85 -> 608.77811 | D117: =DRE!E3/D85 -> 657.1419 | E117: =DRE!H3/E85 -> 615.89296 | F117: =DRE!K3/F85 -> 634.9003 | G117: =DRE!N3/G85 -> 676.94418 | H117: =DRE!Q3/H85 -> 731.79585
A119: Gráfico linha | B119: Ticket Médio de Custo | C119: =C129/C85 -> 356.82991 | D119: =D129/E85 -> 426.21647 | E119: =E129/D85 -> 353.4925 | F119: =F129/F85 -> 384.77039 | G119: =G129/G85 -> 417.58359 | H119: =H129/H85 -> 435.289
A121: Gráfico linha | B121: Multiplicador | C121: =C117/C119 -> 1.7060736 | D121: =D117/D119 -> 1.5418031 | E121: =E117/E119 -> 1.7423084 | F121: =F117/F119 -> 1.6500758 | G121: =G117/G119 -> 1.6210986 | H121: =H117/H119 -> 1.6811724
A123: Gráfico coluna | B123: ='BALANÇO PATRIMONIAL'!B59 -> Número de Funcionários | C123: ='BALANÇO PATRIMONIAL'!C59 -> 13 | D123: ='BALANÇO PATRIMONIAL'!E59 -> 14 | E123: ='BALANÇO PATRIMONIAL'!G59 -> 14 | F123: ='BALANÇO PATRIMONIAL'!I59 -> 12 | G123: ='BALANÇO PATRIMONIAL'!K59 -> 13 | H123: ='BALANÇO PATRIMONIAL'!M59 -> 14
A124: Gráfico linha | B124: PRODUTIVIDADE FAT. BRUTO/FUNCIONÁRIO | C124: =C2/C123 -> 92862.076 | D124: =D2/D123 -> 113873.3 | E124: =E2/E123 -> 103074.09 | F124: =F2/F123 -> 91796.002 | G124: =G2/G123 -> 72068.518 | H124: =H2/H123 -> 98112.915
A126: Gráfico linha | B126: ='BALANÇO PATRIMONIAL'!B40 -> Giro de Estoque Geral em Dias | C126: ='BALANÇO PATRIMONIAL'!C40 -> 60.997895 | D126: ='BALANÇO PATRIMONIAL'!E40 -> 43.834797 | E126: ='BALANÇO PATRIMONIAL'!G40 -> 35.632102 | F126: ='BALANÇO PATRIMONIAL'!I40 -> 55.593302 | G126: ='BALANÇO PATRIMONIAL'!K40 -> 65.518944 | H126: ='BALANÇO PATRIMONIAL'!M40 -> 30.568336
A127: Gráfico coluna | B127: ='BALANÇO PATRIMONIAL'!B49 -> Giro de Estoque Peças em Dias | C127: ='BALANÇO PATRIMONIAL'!C49 -> 58.585536 | D127: ='BALANÇO PATRIMONIAL'!E49 -> 39.786825 | E127: ='BALANÇO PATRIMONIAL'!G49 -> 31.583934 | F127: ='BALANÇO PATRIMONIAL'!I49 -> 48.709041 | G127: ='BALANÇO PATRIMONIAL'!K49 -> 50.683274 | H127: ='BALANÇO PATRIMONIAL'!M49 -> 22.877696
A129: Gráfico coluna | B129: ='BALANÇO PATRIMONIAL'!B36 -> Custo dos Produtos Vendidos (R$) - CPV Ficha Técnica | C129: ='BALANÇO PATRIMONIAL'!C36 -> 707593.72 | D129: ='BALANÇO PATRIMONIAL'!E36 -> 998625.2 | E129: ='BALANÇO PATRIMONIAL'!G36 -> 857572.81 | F129: ='BALANÇO PATRIMONIAL'!I36 -> 667576.62 | G129: ='BALANÇO PATRIMONIAL'!K36 -> 577935.69 | H129: ='BALANÇO PATRIMONIAL'!M36 -> 817037.46
A130: Gráfico coluna | B130: ='BALANÇO PATRIMONIAL'!B33 -> (+) Compras (R$) | C130: ='BALANÇO PATRIMONIAL'!C33 -> 653601 | D130: ='BALANÇO PATRIMONIAL'!E33 -> 130272.71 | E130: ='BALANÇO PATRIMONIAL'!G33 -> 722430.91 | F130: ='BALANÇO PATRIMONIAL'!I33 -> 803250.69 | G130: ='BALANÇO PATRIMONIAL'!K33 -> 68376.03 | H130: ='BALANÇO PATRIMONIAL'!M33 -> 402611.25
A131: Gráfico coluna | B131: =DFC!A23 -> (-) PAGAMENTOS DAS MERCADORIAS VENDIDAS | C131: =DFC!B23 -> 965385.46 | D131: =DFC!D23 -> 956175.13 | E131: =DFC!G23 -> 923865.02 | F131: =DFC!J23 -> 942086.28 | G131: =DFC!M23 -> 706911.04 | H131: =DFC!P23 -> 709376.58
A133: Gráfico linha | B133: MARKETING COM PRODUTOS | C133: 0 | D133: 0 | E133: =65*291.08 -> 18920.2 | F133: 0 | G133: 0 | H133: 0

Sheet INDICADORES
A1: DEMONSTARATIVO DE RESULTADOS GOTT | B1: 45931 | C1: 45962 | D1: 45992 | E1: 46023 | F1: 46054 | G1: 46082
A2: =DRE!B3 -> (+) FATURAMENTO BRUTO | B2: =DRE!C3 -> 1207207 | C2: =DRE!E3 -> 1594226.2 | D2: =DRE!H3 -> 1443037.2 | E2: =DRE!K3 -> 1101552 | F2: =DRE!N3 -> 936890.74 | G2: =DRE!Q3 -> 1373580.8
C3: =C2-B2 -> 387019.25 | D3: =D2-C2 -> -151189.04 | E3: =E2-D2 -> -341485.18 | F3: =F2-E2 -> -164661.28 | G3: =G2-F2 -> 436690.07
I4: 46082
I5: Faturamento bruto | J5: 1373581
I6: Margem de contribuição | J6: 0.1789
I7: Lucro | J7: 52303.628
I8: Lucratividade | J8: 0.038078304
I9: Valor recebido | J9: 1036116.5
I10: Valor pago | J10: 991713.58
I11: Fluxo de caixa | J11: 44402.94
I12: Estoque | J12: 625302.89
I13: Estoque geral em dias | J13: 31
I14: Contas a pagar | J14: 708938.67
I15: Ponto de equilíbrio | J15: 1081295
I16: Ponto de equilíbrio em bikes | J16: 1477.5911
I17: Ticket médio de vendas | J17: 731.79585
A20: =DRE!B4 -> (-) IMPOSTOS S/ VENDAS | B20: =DRE!C4 -> 35650.83 | C20: =DRE!E4 -> 21104.11 | D20: =DRE!H4 -> 19335 | E20: =DRE!K4 -> 15811.61 | F20: =DRE!N4 -> 14053.361 | G20: =DRE!Q4 -> 29702.17
A21: =DRE!B5 -> (-) DEVOLUÇÕES | B21: =DRE!C5 -> 0 | C21: =DRE!E5 -> 0 | D21: =DRE!H5 -> 0 | E21: =DRE!K5 -> 0 | F21: =DRE!N5 -> 0 | G21: =DRE!Q5 -> 0
A22: =DRE!B6 -> (-) DESPESAS COM TRANSPORTE | B22: =DRE!C6 -> 9199.86 | C22: =DRE!E6 -> 1174.88 | D22: =DRE!H6 -> 6687.27 | E22: =DRE!K6 -> 20376.21 | F22: =DRE!N6 -> 31195.07 | G22: =DRE!Q6 -> 23710.91
B23: =B1 -> 45931 | C23: =C1 -> 45962 | D23: =D1 -> 45992 | E23: =E1 -> 46023 | F23: =F1 -> 46054 | G23: =G1 -> 46082
A24: =DRE!B10 -> (-) RECEITA OPERACIONAL LÍQUIDA | B24: =DRE!C10 -> 1162356.3 | C24: =DRE!E10 -> 1571947.2 | D24: =DRE!H10 -> 1417014.9 | E24: =DRE!K10 -> 1065364.2 | F24: =DRE!N10 -> 891642.31 | G24: =DRE!Q10 -> 1320167.7
C25: =C24/B24-1 -> 0.35237986 | D25: =D24/C24-1 -> -0.098560763 | E25: =E24/D24-1 -> -0.24816304 | F25: =F24/E24-1 -> -0.16306338 | G25: =G24/F24-1 -> 0.48060239
A43: =DRE!B11 -> (-) CUSTOS VARIÁVEIS OPERACIONAIS | B43: =DRE!C11 -> 923317.34 | C43: =DRE!E11 -> 1282104.1 | D43: =DRE!H11 -> 1119132.4 | E43: =DRE!K11 -> 865095.17 | F43: =DRE!N11 -> 755745.51 | G43: =DRE!Q11 -> 1074369.7
A44: =DRE!B11 -> (-) CUSTOS VARIÁVEIS OPERACIONAIS | B44: =DRE!D11 -> 0.76483764 | C44: =DRE!F11 -> 0.80421716 | D44: =DRE!I11 -> 0.77553956 | E44: =DRE!L11 -> 0.7853421 | F44: =DRE!O11 -> 0.80665277 | G44: =DRE!R11 -> 0.7821671
A45: =DRE!B12 -> (-) CUSTO DOS PRODUTOS VENDIDOS | B45: =DRE!C12 -> 707593.72 | C45: =DRE!E12 -> 998625.2 | D45: =DRE!H12 -> 857572.81 | E45: =DRE!K12 -> 667576.62 | F45: =DRE!N12 -> 577935.69 | G45: =DRE!Q12 -> 817037.46
B46: =DRE!D12 -> 0.58614117 | C46: =DRE!F12 -> 0.62640118 | D46: =DRE!I12 -> 0.59428323 | E46: =DRE!L12 -> 0.60603277 | F46: =DRE!O12 -> 0.61686562 | G46: =DRE!R12 -> 0.594823
A47: =DRE!B13 -> (-) DESPESAS DE VENDA | B47: =DRE!C13 -> 215723.62 | C47: =DRE!E13 -> 283478.89 | D47: =DRE!H13 -> 261559.62 | E47: =DRE!K13 -> 197518.55 | F47: =DRE!N13 -> 177809.82 | G47: =DRE!Q13 -> 257332.26
B48: =DRE!D13 -> 0.17869647 | C48: =DRE!F13 -> 0.17781597 | D48: =DRE!I13 -> 0.18125633 | E48: =DRE!L13 -> 0.17930933 | F48: =DRE!O13 -> 0.18978715 | G48: =DRE!R13 -> 0.1873441
B49: =B1 -> 45931 | C49: =C1 -> 45962 | D49: =D1 -> 45992 | E49: =E1 -> 46023 | F49: =F1 -> 46054 | G49: =G1 -> 46082
A50: =DRE!B21 -> (=) MARGEM DE CONTRIBUIÇÃO | B50: =DRE!C21 -> 239038.96 | C50: =DRE!E21 -> 289843.16 | D50: =DRE!H21 -> 297882.5 | E50: =DRE!K21 -> 200269.03 | F50: =DRE!N21 -> 135896.8 | G50: =DRE!Q21 -> 245798.01
A51: =DRE!B21 -> (=) MARGEM DE CONTRIBUIÇÃO | B51: =DRE!D21 -> 0.19800992 | C51: =DRE!F21 -> 0.18180805 | D51: =DRE!I21 -> 0.20642746 | E51: =DRE!L21 -> 0.18180624 | F51: =DRE!O21 -> 0.14505085 | G51: =DRE!R21 -> 0.17894689
B85: =B1 -> 45931 | C85: =C1 -> 45962 | D85: =D1 -> 45992 | E85: =E1 -> 46023 | F85: =F1 -> 46054 | G85: =G1 -> 46082
A86: =DRE!B22 -> (-) CUSTOS FIXOS OPERACIONAIS | B86: =DRE!C22 -> 93406.07 | C86: =DRE!E22 -> 104939.41 | D86: =DRE!H22 -> 108655.94 | E86: =DRE!K22 -> 119972.84 | F86: =DRE!N22 -> 119526.37 | G86: =DRE!Q22 -> 138043.59
A87: =DRE!B22 -> (-) CUSTOS FIXOS OPERACIONAIS | B87: =DRE!D22 -> 0.077373699 | C87: =DRE!F22 -> 0.065824666 | D87: =DRE!I22 -> 0.075296701 | E87: =DRE!L22 -> 0.10891255 | F87: =DRE!O22 -> 0.1275777 | G87: =DRE!R22 -> 0.10049907
B121: =B1 -> 45931 | C121: =C1 -> 45962 | D121: =D1 -> 45992 | E121: =E1 -> 46023 | F121: =F1 -> 46054 | G121: =G1 -> 46082
A122: =DRE!B23 -> (=) RESULTADO OPERACIONAL | B122: =DRE!C23 -> 145632.89 | C122: =DRE!E23 -> 184903.75 | D122: =DRE!H23 -> 189226.56 | E122: =DRE!K23 -> 80296.186 | F122: =DRE!N23 -> 16370.429 | G122: =DRE!Q23 -> 107754.42
A123: =DRE!B23 -> (=) RESULTADO OPERACIONAL | B123: =DRE!D23 -> 0.12063622 | C123: =DRE!F23 -> 0.11598338 | D123: =DRE!I23 -> 0.13113076 | E123: =DRE!L23 -> 0.072893685 | F123: =DRE!O23 -> 0.017473147 | G123: =DRE!R23 -> 0.078447819
A157: =DRE!B24 -> (-) IMPOSTO SOBRE O LUCRO | B157: =DRE!C24 -> 0 | C157: =DRE!E24 -> 0 | D157: =DRE!H24 -> 0 | E157: =DRE!K24 -> 0 | F157: =DRE!N24 -> 0 | G157: =DRE!Q24 -> 0
A158: =DRE!B25 -> (=) RESULTADO APÓS IMPOSTO SOBRE O LUCRO | B158: =DRE!C25 -> 145632.89 | C158: =DRE!E25 -> 184903.75 | D158: =DRE!H25 -> 189226.56 | E158: =DRE!K25 -> 80296.186 | F158: =DRE!N25 -> 16370.429 | G158: =DRE!Q25 -> 107754.42
A159: =DRE!B26 -> (-) DESPESAS NÃO OPERACIONAIS | B159: =DRE!C26 -> 0 | C159: =DRE!E26 -> 0 | D159: =DRE!H26 -> 0 | E159: =DRE!K26 -> 0 | F159: =DRE!N26 -> 0 | G159: =DRE!Q26 -> 0
A160: =DRE!B27 -> (+) RECEITAS NÃO OPERACIONAIS | B160: =DRE!C27 -> 0 | C160: =DRE!E27 -> 0 | D160: =DRE!H27 -> 0 | E160: =DRE!K27 -> 0 | F160: =DRE!N27 -> 0 | G160: =DRE!Q27 -> 0
A161: =DRE!B28 -> (=) RESULTADO APÓS DESPESAS E RECEITAS NÃO OPERACIONAIS | B161: =DRE!C28 -> 145632.89 | C161: =DRE!E28 -> 184903.75 | D161: =DRE!H28 -> 189226.56 | E161: =DRE!K28 -> 80296.186 | F161: =DRE!N28 -> 16370.429 | G161: =DRE!Q28 -> 107754.42
A162: =DRE!B29 -> (-) INVESTIMENTOS | B162: =DRE!C29 -> 21070.83 | C162: =DRE!E29 -> 15970.83 | D162: =DRE!H29 -> 16822.6 | E162: =DRE!K29 -> 0 | F162: =DRE!N29 -> 16154.96 | G162: =DRE!Q29 -> 32125.8
A163: =DRE!B30 -> (-) AMORTIZAÇÕES | B163: =DRE!C30 -> 11652.6 | C163: =DRE!E30 -> 0 | D163: =DRE!H30 -> 18274 | E163: =DRE!K30 -> 32000 | F163: =DRE!N30 -> 13000 | G163: =DRE!Q30 -> 17747.62
A164: =DRE!B31 -> (=) RESULTADO ANTES DAS DISTRIBUIÇÕES | B164: =DRE!C31 -> 112909.46 | C164: =DRE!E31 -> 168932.92 | D164: =DRE!H31 -> 154129.96 | E164: =DRE!K31 -> 48296.186 | F164: =DRE!N31 -> -12784.531 | G164: =DRE!Q31 -> 57880.998
A165: =DRE!B31 -> (=) RESULTADO ANTES DAS DISTRIBUIÇÕES | B165: =DRE!D31 -> 0.093529492 | C165: =DRE!F31 -> 0.10596546 | D165: =DRE!I31 -> 0.10680942 | E165: =DRE!L31 -> 0.043843764 | F165: =DRE!O31 -> -0.013645701 | G165: =DRE!R31 -> 0.042138764
A166: =DRE!B32 -> (-) DISTRIBUIÇÃO DE LUCROS & OUTROS | B166: =DRE!C32 -> 21445.72 | C166: =DRE!E32 -> 2067.41 | D166: =DRE!H32 -> 4407.37 | E166: =DRE!K32 -> 2067.37 | F166: =DRE!N32 -> 2110.78 | G166: =DRE!Q32 -> 5577.37
B167: =B1 -> 45931 | C167: =C1 -> 45962 | D167: =D1 -> 45992 | E167: =E1 -> 46023 | F167: =F1 -> 46054 | G167: =G1 -> 46082
A168: =DRE!B37 -> (=) RESULTADO APÓS DISTRIBUIÇÕES | B168: =DRE!C37 -> 91463.737 | C168: =DRE!E37 -> 166865.51 | D168: =DRE!H37 -> 149722.59 | E168: =DRE!K37 -> 46228.816 | F168: =DRE!N37 -> -14895.311 | G168: =DRE!Q37 -> 52303.628
B169: =DRE!D37 -> 0.075764751 | C169: =DRE!F37 -> 0.10466865 | D169: =DRE!I37 -> 0.10375518 | E169: =DRE!L37 -> 0.041966984 | F169: =DRE!O37 -> -0.015898663 | G169: =DRE!R37 -> 0.038078304
B187: =B1 -> 45931 | C187: =C1 -> 45962 | D187: =D1 -> 45992 | E187: =E1 -> 46023 | F187: =F1 -> 46054 | G187: =G1 -> 46082
A188: =DRE!B39 -> (=) PONTO DE EQUILÍBRIO GERENCIAL | B188: =DRE!C39 -> 745292.06 | C188: =DRE!E39 -> 676414.78 | D188: =DRE!H39 -> 717733.54 | E188: =DRE!K39 -> 847276.82 | F188: =DRE!N39 -> 1039581 | G188: =DRE!Q39 -> 1081295
A189: =A547 -> Ticket Médio de Venda | B189: =B547 -> 661.48328 | C189: =C547 -> 702.92162 | D189: =D547 -> 660.42892 | E189: =E547 -> 668.82333 | F189: =F547 -> 704.42913 | G189: =G547 -> 731.79585
A190: PONTO DE EQUILÍBRIO GERENCIAL EM BIKES FATURADAS | B190: =B188/B189 -> 1126.6983 | C190: =C188/C189 -> 962.29048 | D190: =D188/D189 -> 1086.7688 | E190: =E188/E189 -> 1266.8171 | F190: =F188/F189 -> 1475.778 | G190: =G188/G189 -> 1477.5911
B224: =B1 -> 45931 | C224: =C1 -> 45962 | D224: =D1 -> 45992 | E224: =E1 -> 46023 | F224: =F1 -> 46054 | G224: =G1 -> 46082
A225: =DRE!B40 -> (=) PONTO DE EQUILÍBRIO OPERACIONAL | B225: =DRE!C40 -> 471724.2 | C225: =DRE!E40 -> 577198.93 | D225: =DRE!H40 -> 526363.8 | E225: =DRE!K40 -> 659893.98 | F225: =DRE!N40 -> 824030.81 | G225: =DRE!Q40 -> 771422.14
A243: DEMONSTRATIVO DE FLUXO DE CAIXA GOTT | B243: =B1 -> 45931 | C243: =C1 -> 45962 | D243: =D1 -> 45992 | E243: =E1 -> 46023 | F243: =F1 -> 46054 | G243: =G1 -> 46082
A244: =DFC!A170 -> FLUXO DE CAIXA (ENTRADAS - SAÍDAS) | B244: =DFC!B170 -> -22623.92 | C244: =DFC!D170 -> -52069.95 | D244: =DFC!G170 -> 65393.6 | E244: =DFC!J170 -> -75586.46 | F244: =DFC!M170 -> -202048.76 | G244: =DFC!P170 -> 44402.94
B245: =B244/B246 -> -0.020143901 | C245: =C244/C246 -> -0.045917451 | D245: =D244/D246 -> 0.05036502 | E245: =E244/E246 -> -0.070772361 | F245: =F244/F246 -> -0.29208582 | G245: =G244/G246 -> 0.042855161
A246: =DFC!A171 -> ENTRADAS NO MÊS | B246: =DFC!B171 -> 1123115.1 | C246: =DFC!D171 -> 1133990.4 | D246: =DFC!G171 -> 1298393.2 | E246: =DFC!J171 -> 1068022.3 | F246: =DFC!M171 -> 691744.49 | G246: =DFC!P171 -> 1036116.5
A247: =DFC!A172 -> SAÍDAS NO MÊS | B247: =-DFC!B172 -> -1145739.1 | C247: =-DFC!D172 -> -1186060.4 | D247: =-DFC!G172 -> -1232999.6 | E247: =-DFC!J172 -> -1143608.8 | F247: =-DFC!M172 -> -893793.25 | G247: =-DFC!P172 -> -991713.58
A297: FATURAMENTO X ENTRADAS
B298: =B1 -> 45931 | C298: =C1 -> 45962 | D298: =D1 -> 45992 | E298: =E1 -> 46023 | F298: =F1 -> 46054 | G298: =G1 -> 46082
A299: =A2 -> (+) FATURAMENTO BRUTO | B299: =B2 -> 1207207 | C299: =C2 -> 1594226.2 | D299: =D2 -> 1443037.2 | E299: =E2 -> 1101552 | F299: =F2 -> 936890.74 | G299: =G2 -> 1373580.8
A300: =A246 -> ENTRADAS NO MÊS | B300: =B246 -> 1123115.1 | C300: =C246 -> 1133990.4 | D300: =D246 -> 1298393.2 | E300: =E246 -> 1068022.3 | F300: =F246 -> 691744.49 | G300: =G246 -> 1036116.5
A301: INDICADOR ENTRADAS X FATURAMENTO | B301: =B300/B299 -> 0.93034181 | C301: =C300/C299 -> 0.71131086 | D301: =D300/D299 -> 0.8997642 | E301: =E300/E299 -> 0.96956139 | F301: =F300/F299 -> 0.73834062 | G301: =G300/G299 -> 0.75431785
A319: BALANÇO PATRIMONIAL GOTT | B319: =B1 -> 45931 | C319: =C1 -> 45962 | D319: =D1 -> 45992 | E319: =E1 -> 46023 | F319: =F1 -> 46054 | G319: =G1 -> 46082
A320: ='BALANÇO PATRIMONIAL'!B3 -> (+) Estoque Geral Preço de Custo | B320: ='BALANÇO PATRIMONIAL'!C3 -> 1870693 | C320: ='BALANÇO PATRIMONIAL'!E3 -> 1047609.1 | D320: ='BALANÇO PATRIMONIAL'!G3 -> 989532.32 | E320: ='BALANÇO PATRIMONIAL'!I3 -> 1484653.6 | F320: ='BALANÇO PATRIMONIAL'!K3 -> 1039728.8 | G320: ='BALANÇO PATRIMONIAL'!M3 -> 625302.89
A321: ='BALANÇO PATRIMONIAL'!B4 -> Estoque de Peças | B321: ='BALANÇO PATRIMONIAL'!C4 -> 1756895 | C321: ='BALANÇO PATRIMONIAL'!E4 -> 891913.41 | D321: ='BALANÇO PATRIMONIAL'!G4 -> 913788.12 | E321: ='BALANÇO PATRIMONIAL'!I4 -> 1254013 | F321: ='BALANÇO PATRIMONIAL'!K4 -> 698765.16 | G321: ='BALANÇO PATRIMONIAL'!M4 -> 547363.79
A322: ='BALANÇO PATRIMONIAL'!B5 -> Estoque de P.A. | B322: ='BALANÇO PATRIMONIAL'!C5 -> 102845 | C322: ='BALANÇO PATRIMONIAL'!E5 -> 7675 | D322: ='BALANÇO PATRIMONIAL'!G5 -> 0 | E322: ='BALANÇO PATRIMONIAL'!I5 -> 0 | F322: ='BALANÇO PATRIMONIAL'!K5 -> 186710.04 | G322: ='BALANÇO PATRIMONIAL'!M5 -> 0
A323: ='BALANÇO PATRIMONIAL'!B6 -> Estoque de P.A. no Full | B323: ='BALANÇO PATRIMONIAL'!C6 -> 10953.02 | C323: ='BALANÇO PATRIMONIAL'!E6 -> 148020.72 | D323: ='BALANÇO PATRIMONIAL'!G6 -> 75744.2 | E323: ='BALANÇO PATRIMONIAL'!I6 -> 230640.59 | F323: ='BALANÇO PATRIMONIAL'!K6 -> 154253.6 | G323: ='BALANÇO PATRIMONIAL'!M6 -> 77939.1
A324: ='BALANÇO PATRIMONIAL'!B7 -> (+) Disponibilidades | B324: ='BALANÇO PATRIMONIAL'!C7 -> 60840.68 | C324: ='BALANÇO PATRIMONIAL'!E7 -> -73229.27 | D324: ='BALANÇO PATRIMONIAL'!G7 -> -87725.67 | E324: ='BALANÇO PATRIMONIAL'!I7 -> -288353.43 | F324: ='BALANÇO PATRIMONIAL'!K7 -> -488530.17 | G324: ='BALANÇO PATRIMONIAL'!M7 -> -445252.05
A325: ='BALANÇO PATRIMONIAL'!B8 -> Caixinha | B325: ='BALANÇO PATRIMONIAL'!C8 -> 0 | C325: ='BALANÇO PATRIMONIAL'!E8 -> 0 | D325: ='BALANÇO PATRIMONIAL'!G8 -> 0 | E325: ='BALANÇO PATRIMONIAL'!I8 -> 0 | F325: ='BALANÇO PATRIMONIAL'!K8 -> 0 | G325: ='BALANÇO PATRIMONIAL'!M8 -> 0
A326: ='BALANÇO PATRIMONIAL'!B9 -> Bradesco | B326: ='BALANÇO PATRIMONIAL'!C9 -> 0 | C326: ='BALANÇO PATRIMONIAL'!E9 -> 0 | D326: ='BALANÇO PATRIMONIAL'!G9 -> 0 | E326: ='BALANÇO PATRIMONIAL'!I9 -> 0 | F326: ='BALANÇO PATRIMONIAL'!K9 -> -199580 | G326: ='BALANÇO PATRIMONIAL'!M9 -> -199580
A327: ='BALANÇO PATRIMONIAL'!B10 -> Sicredi agência 0723 c/c 70.636-3 | B327: ='BALANÇO PATRIMONIAL'!C10 -> 60840.68 | C327: ='BALANÇO PATRIMONIAL'!E10 -> 8770.73 | D327: ='BALANÇO PATRIMONIAL'!G10 -> 74164.33 | E327: ='BALANÇO PATRIMONIAL'!I10 -> -1463.43 | F327: ='BALANÇO PATRIMONIAL'!K10 -> -2060.17 | G327: ='BALANÇO PATRIMONIAL'!M10 -> 41217.95
A328: ='BALANÇO PATRIMONIAL'!B11 -> Empréstimo Adonai | B328: ='BALANÇO PATRIMONIAL'!C11 -> 0 | C328: ='BALANÇO PATRIMONIAL'!E11 -> -82000 | D328: ='BALANÇO PATRIMONIAL'!G11 -> -161890 | E328: ='BALANÇO PATRIMONIAL'!I11 -> -226890 | F328: ='BALANÇO PATRIMONIAL'!K11 -> -226890 | G328: ='BALANÇO PATRIMONIAL'!M11 -> -226890
A329: ='BALANÇO PATRIMONIAL'!B12 -> Empréstimo Feedstock | B329: ='BALANÇO PATRIMONIAL'!C12 -> 0 | C329: ='BALANÇO PATRIMONIAL'!E12 -> 0 | D329: ='BALANÇO PATRIMONIAL'!G12 -> 0 | E329: ='BALANÇO PATRIMONIAL'!I12 -> -60000 | F329: ='BALANÇO PATRIMONIAL'!K12 -> -60000 | G329: ='BALANÇO PATRIMONIAL'!M12 -> -60000
A330: ='BALANÇO PATRIMONIAL'!B13 -> (+) Contas a Receber | B330: ='BALANÇO PATRIMONIAL'!C13 -> 176774.24 | C330: ='BALANÇO PATRIMONIAL'!E13 -> 585872.25 | D330: ='BALANÇO PATRIMONIAL'!G13 -> 602832.77 | E330: ='BALANÇO PATRIMONIAL'!I13 -> 201831.94 | F330: ='BALANÇO PATRIMONIAL'!K13 -> 400000 | G330: ='BALANÇO PATRIMONIAL'!M13 -> 500000
A331: ='BALANÇO PATRIMONIAL'!B14 -> Contas a Receber em Atraso | B331: ='BALANÇO PATRIMONIAL'!C14 -> 0 | C331: ='BALANÇO PATRIMONIAL'!E14 -> 0 | D331: ='BALANÇO PATRIMONIAL'!G14 -> 0 | E331: ='BALANÇO PATRIMONIAL'!I14 -> 0 | F331: ='BALANÇO PATRIMONIAL'!K14 -> 0 | G331: ='BALANÇO PATRIMONIAL'!M14 -> 0
... A334: ='BALANÇO PATRIMONIAL'!B17 -> (-) Contas a Pagar DDA | B334: ='BALANÇO PATRIMONIAL'!C17 -> 2460338.6 | C334: ='BALANÇO PATRIMONIAL'!E17 -> 1688812.4 | D334: ='BALANÇO PATRIMONIAL'!G17 -> 1513014.7 | E334: ='BALANÇO PATRIMONIAL'!I17 -> 1410399.3 | F334: ='BALANÇO PATRIMONIAL'!K17 -> 1030284.5 | G334: ='BALANÇO PATRIMONIAL'!M17 -> 708938.67
B335: =B1 -> 45931 | C335: =C1 -> 45962 | D335: =D1 -> 45992 | E335: =E1 -> 46023 | F335: =F1 -> 46054 | G335: =G1 -> 46082
A336: ='BALANÇO PATRIMONIAL'!B18 -> (=) Saldo Patrimonial | B336: ='BALANÇO PATRIMONIAL'!C18 -> -352030.6 | C336: ='BALANÇO PATRIMONIAL'!E18 -> -128560.24 | D336: ='BALANÇO PATRIMONIAL'!G18 -> -8375.26 | E336: ='BALANÇO PATRIMONIAL'!I18 -> -12267.22 | F336: ='BALANÇO PATRIMONIAL'!K18 -> -79085.87 | G336: ='BALANÇO PATRIMONIAL'!M18 -> -28887.83
A354: OUTROS COMERCIAIS | B354: =B1 -> 45931 | C354: =C1 -> 45962 | D354: =D1 -> 45992 | E354: =E1 -> 46023 | F354: =F1 -> 46054 | G354: =G1 -> 46082
A355: =CPV!A15 -> FATURAMENTO GOTT | B355: =CPV!B15 -> QTDE FATURADA | C355: =CPV!E15 -> QTDE FATURADA | D355: =CPV!H15 -> QTDE FATURADA | E355: =CPV!K15 -> QTDE FATURADA | F355: =CPV!N15 -> QTDE FATURADA | G355: =CPV!Q15 -> QTDE FATURADA
A356: =CPV!A16 -> BMX | B356: =CPV!B16 -> 801 | C356: =CPV!E16 -> 404 | D356: =CPV!H16 -> 844 | E356: =CPV!K16 -> 317 | F356: =CPV!N16 -> 116 | G356: =CPV!Q16 -> 284
A357: =CPV!A17 -> Aro 29 aço 21 Imp (referência) | B357: =CPV!B17 -> 593 | C357: =CPV!E17 -> 684 | D357: =CPV!H17 -> 664 | E357: =CPV!K17 -> 625 | F357: =CPV!N17 -> 261 | G357: =CPV!Q17 -> 596
A358: =CPV!A18 -> Aro 29 AL 21 Shimano | B358: =CPV!B18 -> 7 | C358: =CPV!E18 -> 153 | D358: =CPV!H18 -> 23 | E358: =CPV!K18 -> 29 | F358: =CPV!N18 -> 4 | G358: =CPV!Q18 -> 5
A359: =CPV!A19 -> Aro 29 AL 21 Imp | B359: =CPV!B19 -> 293 | C359: =CPV!E19 -> 18 | D359: =CPV!H19 -> 487 | E359: =CPV!K19 -> 332 | F359: =CPV!N19 -> 828 | G359: =CPV!Q19 -> 778
A360: =CPV!A20 -> Aro 29 AL 24 Shimano Imp | B360: =CPV!B20 -> 1 | C360: =CPV!E20 -> 12 | D360: =CPV!H20 -> 0 | E360: =CPV!K20 -> 0 | F360: =CPV!N20 -> 1 | G360: =CPV!Q20 -> 3
A361: =CPV!A21 -> Aro 29 AL 24 Shimano DNTTRS | B361: =CPV!B21 -> 5 | C361: =CPV!E21 -> 6 | D361: =CPV!H21 -> 1 | E361: =CPV!K21 -> 1 | F361: =CPV!N21 -> 1 | G361: =CPV!Q21 -> 1
A362: =CPV!A22 -> Aro 29 AL 21 Shimano DNTTRS | B362: =CPV!B22 -> 1 | C362: =CPV!E22 -> 1 | D362: =CPV!H22 -> 7 | E362: =CPV!K22 -> 14 | F362: =CPV!N22 -> 25 | G362: =CPV!Q22 -> 14
A363: =CPV!A23 -> Aro 29 AL 24 Imp | B363: =CPV!B23 -> 124 | C363: =CPV!E23 -> 990 | D363: =CPV!H23 -> 145 | E363: =CPV!K23 -> 127 | F363: =CPV!N23 -> 45 | G363: =CPV!Q23 -> 138
A364: QUANTIDADE FATURADA GOTT | B364: =CPV!B25 -> 1825 | C364: =CPV!E25 -> 2268 | D364: =CPV!H25 -> 2185 | E364: =CPV!K25 -> 1647 | F364: =CPV!N25 -> 1330 | G364: =CPV!Q25 -> 1877
C365: =C364/B364-1 -> 0.24273973 | D365: =D364/C364-1 -> -0.03659612 | E365: =E364/D364-1 -> -0.24622426 | F365: =F364/E364-1 -> -0.19247116 | G365: =G364/F364-1 -> 0.4112782
B383: =B1 -> 45931 | C383: =C1 -> 45962 | D383: =D1 -> 45992 | E383: =E1 -> 46023 | F383: =F1 -> 46054 | G383: =G1 -> 46082
A384: =CPV!A28 -> FATURAMENTO VIVER DE MARKETING | B384: =CPV!B28 -> QTDE FATURADA | C384: =CPV!E28 -> QTDE FATURADA | D384: =CPV!H28 -> QTDE FATURADA | E384: =CPV!K28 -> QTDE FATURADA | F384: =CPV!N28 -> QTDE FATURADA | G384: =CPV!Q28 -> QTDE FATURADA
A385: =CPV!A29 -> BMX | B385: =CPV!B29 -> 158 | C385: =CPV!E29 -> 158 | D385: =CPV!H29 -> 158 | E385: =CPV!K29 -> 88 | F385: =CPV!N29 -> 54 | G385: =CPV!Q29 -> 0
A386: =CPV!A30 -> Aro 29 aço 21 Imp (referência) | B386: =CPV!B30 -> 0 | C386: =CPV!E30 -> 0 | D386: =CPV!H30 -> 0 | E386: =CPV!K30 -> 0 | F386: =CPV!N30 -> 0 | G386: =CPV!Q30 -> 0
A387: =CPV!A31 -> Aro 29 AL 21 Shimano | B387: =CPV!B31 -> 0 | C387: =CPV!E31 -> 0 | D387: =CPV!H31 -> 0 | E387: =CPV!K31 -> 0 | F387: =CPV!N31 -> 0 | G387: =CPV!Q31 -> 0
...

Sheet CPV
A1: Mês | B1: =B14 -> 45931 | E1: =E14 -> 45962 | H1: =H14 -> 45992 | K1: =K14 -> 46023 | N1: =N14 -> 46054 | Q1: =Q14 -> 46082
A2: FATURAMENTO TOTAL | B2: QTDE FATURADA | C2: CUSTO FICHA TÉCNICA | D2: CPV | E2: QTDE FATURADA | F2: CUSTO FICHA TÉCNICA | G2: CPV | H2: QTDE FATURADA | I2: CUSTO FICHA TÉCNICA | J2: CPV | K2: QTDE FATURADA | L2: CUSTO FICHA TÉCNICA | M2: CPV | N2: QTDE FATURADA | O2: CUSTO FICHA TÉCNICA | P2: CPV | Q2: QTDE FATURADA | R2: CUSTO FICHA TÉCNICA | S2: CPV
A3: BMX | B3: =B16+B29 -> 959 | C3: =C16 -> 286.51 | D3: =B3*C3 -> 274763.09 | E3: =E16+E29 -> 562 | F3: =F16 -> 286.51 | G3: =E3*F3 -> 161018.62 | H3: =H16+H29 -> 1002 | I3: =I16 -> 291.08 | J3: =H3*I3 -> 291662.16 | K3: =K16+K29 -> 405 | L3: =L16 -> 286.51 | M3: =K3*L3 -> 116036.55 | N3: =N16+N29 -> 170 | O3: =O16 -> 288.6 | P3: =N3*O3 -> 49062 | Q3: =Q16+Q29 -> 284 | R3: =R16 -> 301.63 | S3: =Q3*R3 -> 85662.92
A4: Aro 29 aço 21 Imp (referência) | B4: =B17+B30 -> 593 | C4: =C17 -> 378.34 | D4: =B4*C4 -> 224355.62 | E4: =E17+E30 -> 684 | F4: =F17 -> 378.34 | G4: =E4*F4 -> 258784.56 | H4: =H17+H30 -> 664 | I4: =I17 -> 372.37 | J4: =H4*I4 -> 247253.68 | K4: =K17+K30 -> 625 | L4: =L17 -> 373.64 | M4: =K4*L4 -> 233525 | N4: =N17+N30 -> 261 | O4: =O17 -> 369.55 | P4: =N4*O4 -> 96452.55 | Q4: =Q17+Q30 -> 596 | R4: =R17 -> 405.88 | S4: =Q4*R4 -> 241904.48
A5: Ara 29 AL 21 Shimano | B5: =B18+B31 -> 7 | C5: =C18 -> 502.92 | D5: =B5*C5 -> 3520.44 | E5: =E18+E31 -> 153 | F5: =F18 -> 502.92 | G5: =E5*F5 -> 76946.76 | H5: =H18+H31 -> 23 | I5: =I18 -> 514.28 | J5: =H5*I5 -> 11828.44 | K5: =K18+K31 -> 29 | L5: =L18 -> 485.34 | M5: =K5*L5 -> 14074.86 | N5: =N18+N31 -> 4 | O5: =O18 -> 485.34 | P5: =N5*O5 -> 1941.36 | Q5: =Q18+Q31 -> 5 | R5: =R18 -> 532.78 | S5: =Q5*R5 -> 2663.9
A6: Aro 29 AL 21 Imp | B6: =B19+B32 -> 293 | C6: =C19 -> 479.43 | D6: =B6*C6 -> 140472.99 | E6: =E19+E32 -> 18 | F6: =F19 -> 479.43 | G6: =E6*F6 -> 8629.74 | H6: =H19+H32 -> 487 | I6: =I19 -> 466.75 | J6: =H6*I6 -> 227307.25 | K6: =K19+K32 -> 332 | L6: =L19 -> 457.75 | M6: =K6*L6 -> 151973 | N6: =N19+N32 -> 828 | O6: =O19 -> 453.9 | P6: =N6*O6 -> 375829.2 | Q6: =Q19+Q32 -> 778 | R6: =R19 -> 486.35 | S6: =Q6*R6 -> 378380.3
A7: Aro 29 AL 24 Shimano Imp | B7: =B20+B33 -> 1 | C7: =C20 -> 570.89 | D7: =B7*C7 -> 570.89 | E7: =E20+E33 -> 12 | F7: =F20 -> 570.89 | G7: =E7*F7 -> 6850.68 | H7: =H20+H33 -> 0 | I7: =I20 -> 562.88 | J7: =H7*I7 -> 0 | K7: =K20+K33 -> 0 | L7: =L20 -> 554.28 | M7: =K7*L7 -> 0 | N7: =N20+N33 -> 1 | O7: =O20 -> 481.49 | P7: =N7*O7 -> 481.49 | Q7: =Q20+Q33 -> 3 | R7: =R20 -> 518.85 | S7: =Q7*R7 -> 1556.55
A8: Aro 29 AL 24 Shimano DNTTRS | B8: =B21+B34 -> 5 | C8: =C21 -> 594.93 | D8: =B8*C8 -> 2974.65 | E8: =E21+E34 -> 6 | F8: =F21 -> 594.93 | G8: =E8*F8 -> 3569.58 | H8: =H21+H34 -> 1 | I8: =I21 -> 586.92 | J8: =H8*I8 -> 586.92 | K8: =K21+K34 -> 1 | L8: =L21 -> 578.31 | M8: =K8*L8 -> 578.31 | N8: =N21+N34 -> 1 | O8: =O21 -> 578.31 | P8: =N8*O8 -> 578.31 | Q8: =Q21+Q34 -> 1 | R8: =R21 -> 625.53 | S8: =Q8*R8 -> 625.53
A9: Aro 29 AL 21 Shimano DNTTRS | B9: =B22+B35 -> 1 | C9: =C22 -> 526.96 | D9: =B9*C9 -> 526.96 | E9: =E22+E35 -> 1 | F9: =F22 -> 526.96 | G9: =E9*F9 -> 526.96 | H9: =H22+H35 -> 7 | I9: =I22 -> 514.28 | J9: =H9*I9 -> 3599.96 | K9: =K22+K35 -> 14 | L9: =L22 -> 509.37 | M9: =K9*L9 -> 7131.18 | N9: =N22+N35 -> 25 | O9: =O22 -> 505.53 | P9: =N9*O9 -> 12638.25 | Q9: =Q22+Q35 -> 14 | R9: =R22 -> 555.74 | S9: =Q9*R9 -> 7780.36
A10: Ara 29 AL 24 Imp | B10: =B23+B36 -> 124 | C10: =C23 -> 487.17 | D10: =B10*C10 -> 60409.08 | E10: =E23+E36 -> 990 | F10: =F23 -> 487.17 | G10: =E10*F10 -> 482298.3 | H10: =H23+H36 -> 145 | I10: =I23 -> 479.16 | J10: =H10*I10 -> 69478.2 | K10: =K23+K36 -> 127 | L10: =L23 -> 470.56 | M10: =K10*L10 -> 59761.12 | N10: =N23+N36 -> 45 | O10: =O23 -> 467.02 | P10: =N10*O10 -> 21015.9 | Q10: =Q23+Q36 -> 138 | R10: =R23 -> 518.85 | S10: =Q10*R10 -> 71601.3
A11: Aro 29 aço 21 Imp c/ Suspensão (Nova) | B11: =B24+B37 -> 0 | C11: =C24 -> 0 | D11: =B11*C11 -> 0 | E11: =E24+E37 -> 0 | F11: =F24 -> 0 | G11: =E11*F11 -> 0 | H11: =H24+H37 -> 14 | I11: =I24 -> 418.3 | J11: =H11*I11 -> 5856.2 | K11: =K24+K37 -> 202 | L11: =L24 -> 418.3 | M11: =K11*L11 -> 84496.6 | N11: =N24+N37 -> 49 | O11: =O24 -> 406.87 | P11: =N11*O11 -> 19936.63 | Q11: =Q24+Q37 -> 58 | R11: =R24 -> 463.14 | S11: =Q11*R11 -> 26862.12
B12: =SUM(B3:B11) -> 1983 | C12: =D12/B12 -> 356.82991 | D12: =SUM(D3:D11) -> 707593.72 | E12: =SUM(E3:E11) -> 2426 | F12: =G12/E12 -> 411.63446 | G12: =SUM(G3:G11) -> 998625.2 | H12: =SUM(H3:H11) -> 2343 | I12: =J12/H12 -> 366.01486 | J12: =SUM(J3:J11) -> 857572.81 | K12: =SUM(K3:K11) -> 1735 | L12: =M12/K12 -> 384.77039 | M12: =SUM(M3:M11) -> 667576.62 | N12: =SUM(N3:N11) -> 1384 | O12: =P12/N12 -> 417.58359 | P12: =SUM(P3:P11) -> 577935.69 | Q12: =SUM(Q3:Q11) -> 1877 | R12: =S12/Q12 -> 435.289 | S12: =SUM(S3:S11) -> 817037.46
A14: Mês | B14: 45931 | E14: 45962 | H14: 45992 | K14: 46023 | N14: 46054 | Q14: 46082
A15: FATURAMENTO GOTT | B15: QTDE FATURADA | C15: CUSTO FICHA TÉCNICA | D15: CPV | E15: QTDE FATURADA | F15: CUSTO FICHA TÉCNICA | G15: CPV | H15: QTDE FATURADA | I15: CUSTO FICHA TÉCNICA | J15: CPV | K15: QTDE FATURADA | L15: CUSTO FICHA TÉCNICA | M15: CPV | N15: QTDE FATURADA | O15: CUSTO FICHA TÉCNICA | P15: CPV | Q15: QTDE FATURADA | R15: CUSTO FICHA TÉCNICA | S15: CPV
A16: BMX | B16: 801 | C16: 286.51 | D16: =B16*C16 -> 229494.51 | E16: 404 | F16: 286.51 | G16: =E16*F16 -> 115750.04 | H16: =827+17 -> 844 | I16: 291.08 | J16: =H16*I16 -> 245671.52 | K16: 317 | L16: 286.51 | M16: =K16*L16 -> 90823.67 | N16: 116 | O16: 288.6 | P16: =N16*O16 -> 33477.6 | Q16: 284 | R16: 301.63 | S16: =Q16*R16 -> 85662.92
A17: Aro 29 aço 21 Imp (referência) | B17: 593 | C17: 378.34 | D17: =B17*C17 -> 224355.62 | E17: 684 | F17: 378.34 | G17: =E17*F17 -> 258784.56 | H17: =636+28 -> 664 | I17: 372.37 | J17: =H17*I17 -> 247253.68 | K17: 625 | L17: 373.64 | M17: =K17*L17 -> 233525 | N17: 261 | O17: 369.55 | P17: =N17*O17 -> 96452.55 | Q17: 596 | R17: 405.88 | S17: =Q17*R17 -> 241904.48
A18: Aro 29 AL 21 Shimano | B18: 7 | C18: 502.92 | D18: =B18*C18 -> 3520.44 | E18: 153 | F18: 502.92 | G18: =E18*F18 -> 76946.76 | H18: 23 | I18: 514.28 | J18: =H18*I18 -> 11828.44 | K18: 29 | L18: 485.34 | M18: =K18*L18 -> 14074.86 | N18: 4 | O18: 485.34 | P18: =N18*O18 -> 1941.36 | Q18: 5 | R18: 532.78 | S18: =Q18*R18 -> 2663.9
A19: Aro 29 AL 21 Imp | B19: 293 | C19: 479.43 | D19: =B19*C19 -> 140472.99 | E19: 18 | F19: 479.43 | G19: =E19*F19 -> 8629.74 | H19: =459+28 -> 487 | I19: 466.75 | J19: =H19*I19 -> 227307.25 | K19: 332 | L19: 457.75 | M19: =K19*L19 -> 151973 | N19: 828 | O19: 453.9 | P19: =N19*O19 -> 375829.2 | Q19: =751+27 -> 778 | R19: 486.35 | S19: =Q19*R19 -> 378380.3
A20: Aro 29 AL 24 Shimano Imp | B20: 1 | C20: 570.89 | D20: =B20*C20 -> 570.89 | E20: 12 | F20: 570.89 | G20: =E20*F20 -> 6850.68 | H20: 0 | I20: 562.88 | J20: =H20*I20 -> 0 | K20: 0 | L20: 554.28 | M20: =K20*L20 -> 0 | N20: 1 | O20: 481.49 | P20: =N20*O20 -> 481.49 | Q20: 3 | R20: 518.85 | S20: =Q20*R20 -> 1556.55
A21: Aro 29 AL 24 Shimano DNTTRS | B21: 5 | C21: 594.93 | D21: =B21*C21 -> 2974.65 | E21: 6 | F21: 594.93 | G21: =E21*F21 -> 3569.58 | H21: 1 | I21: 586.92 | J21: =H21*I21 -> 586.92 | K21: 1 | L21: 578.31 | M21: =K21*L21 -> 578.31 | N21: 1 | O21: 578.31 | P21: =N21*O21 -> 578.31 | Q21: 1 | R21: 625.53 | S21: =Q21*R21 -> 625.53
A22: Aro 29 AL 21 Shimano DNTTRS | B22: 1 | C22: 526.96 | D22: =B22*C22 -> 526.96 | E22: 1 | F22: 526.96 | G22: =E22*F22 -> 526.96 | H22: 7 | I22: 514.28 | J22: =H22*I22 -> 3599.96 | K22: 14 | L22: 509.37 | M22: =K22*L22 -> 7131.18 | N22: 25 | O22: 505.53 | P22: =N22*O22 -> 12638.25 | Q22: 14 | R22: 555.74 | S22: =Q22*R22 -> 7780.36
A23: Aro 29 AL 24 Imp | B23: 124 | C23: 487.17 | D23: =B23*C23 -> 60409.08 | E23: 990 | F23: 487.17 | G23: =E23*F23 -> 482298.3 | H23: =129+16 -> 145 | I23: 479.16 | J23: =H23*I23 -> 69478.2 | K23: 127 | L23: 470.56 | M23: =K23*L23 -> 59761.12 | N23: 45 | O23: 467.02 | P23: =N23*O23 -> 21015.9 | Q23: 138 | R23: 518.85 | S23: =Q23*R23 -> 71601.3
A24: Aro 29 aço 21 Imp c/ Suspensão (Nova) | B24: 0 | C24: 0 | D24: =B24*C24 -> 0 | E24: 0 | F24: 0 | G24: =E24*F24 -> 0 | H24: =11+3 -> 14 | I24: 418.3 | J24: =H24*I24 -> 5856.2 | K24: 202 | L24: 418.3 | M24: =K24*L24 -> 84496.6 | N24: 49 | O24: 406.87 | P24: =N24*O24 -> 19936.63 | Q24: 58 | R24: 463.14 | S24: =Q24*R24 -> 26862.12
B25: =SUM(B16:B24) -> 1825 | C25: =D25/B25 -> 362.91788 | D25: =SUM(D16:D24) -> 662325.14 | E25: =SUM(E16:E24) -> 2268 | F25: =G25/E25 -> 420.35124 | G25: =SUM(G16:G24) -> 953356.62 | H25: =SUM(H16:H24) -> 2185 | I25: =J25/H25 -> 371.43349 | J25: =SUM(J16:J24) -> 811582.17 | K25: =SUM(K16:K24) -> 1647 | L25: =M25/K25 -> 390.02049 | M25: =SUM(M16:M24) -> 642363.74 | N25: =SUM(N16:N24) -> 1330 | O25: =P25/N25 -> 422.82052 | P25: =SUM(P16:P24) -> 562351.29 | Q25: =SUM(Q16:Q24) -> 1877 | R25: =S25/Q25 -> 435.289 | S25: =SUM(S16:S24) -> 817037.46
A27: Mês | B27: =B14 -> 45931 | E27: =E14 -> 45962 | H27: =H14 -> 45992 | K27: =K14 -> 46023 | N27: =N14 -> 46054 | Q27: =Q14 -> 46082
A28: FATURAMENTO VIVER DE MARKETING | B28: QTDE FATURADA | C28: CUSTO FICHA TÉCNICA | D28: CPV | E28: QTDE FATURADA | F28: CUSTO FICHA TÉCNICA | G28: CPV | H28: QTDE FATURADA | I28: CUSTO FICHA TÉCNICA | J28: CPV | K28: QTDE FATURADA | L28: CUSTO FICHA TÉCNICA | M28: CPV | N28: QTDE FATURADA | O28: CUSTO FICHA TÉCNICA | P28: CPV | Q28: QTDE FATURADA | R28: CUSTO FICHA TÉCNICA | S28: CPV
A29: =A16 -> BMX | B29: 158 | C29: =C16 -> 286.51 | D29: =B29*C29 -> 45268.58 | E29: 158 | F29: =F16 -> 286.51 | G29: =E29*F29 -> 45268.58 | H29: 158 | I29: =I16 -> 291.08 | J29: =H29*I29 -> 45990.64 | K29: 88 | L29: 286.51 | M29: =K29*L29 -> 25212.88 | N29: 54 | O29: =O16 -> 288.6 | P29: =N29*O29 -> 15584.4 | R29: =R16 -> 301.63 | S29: =Q29*R29 -> 0
A30: =A17 -> Aro 29 aço 21 Imp (referência) | B30: 0 | C30: =C17 -> 378.34 | D30: =B30*C30 -> 0 | E30: 0 | F30: =F17 -> 378.34 | G30: =E30*F30 -> 0 | H30: 0 | I30: =I17 -> 372.37 | J30: =H30*I30 -> 0 | L30: 373.64 | M30: =K30*L30 -> 0 | O30: =O17 -> 369.55 | P30: =N30*O30 -> 0 | R30: =R17 -> 405.88 | S30: =Q30*R30 -> 0
A31: =A18 -> Aro 29 AL 21 Shimano | B31: 0 | C31: =C18 -> 502.92 | D31: =B31*C31 -> 0 | E31: 0 | F31: =F18 -> 502.92 | G31: =E31*F31 -> 0 | H31: 0 | I31: =I18 -> 514.28 | J31: =H31*I31 -> 0 | L31: 485.34 | M31: =K31*L31 -> 0 | O31: =O18 -> 485.34 | P31: =N31*O31 -> 0 | R31: =R18 -> 532.78 | S31: =Q31*R31 -> 0
A32: =A19 -> Aro 29 AL 21 Imp | B32: 0 | C32: =C19 -> 479.43 | D32: =B32*C32 -> 0 | E32: 0 | F32: =F19 -> 479.43 | G32: =E32*F32 -> 0 | H32: 0 | I32: =I19 -> 466.75 | J32: =H32*I32 -> 0 | L32: 457.75 | M32: =K32*L32 -> 0 | O32: =O19 -> 453.9 | P32: =N32*O32 -> 0 | R32: =R19 -> 486.35 | S32: =Q32*R32 -> 0
A33: =A20 -> Aro 29 AL 24 Shimano Imp | B33: 0 | C33: =C20 -> 570.89 | D33: =B33*C33 -> 0 | E33: 0 | F33: =F20 -> 570.89 | G33: =E33*F33 -> 0 | H33: 0 | I33: =I20 -> 562.88 | J33: =H33*I33 -> 0 | L33: 554.28 | M33: =K33*L33 -> 0 | O33: =O20 -> 481.49 | P33: =N33*O33 -> 0 | R33: =R20 -> 518.85 | S33: =Q33*R33 -> 0
A34: =A21 -> Aro 29 AL 24 Shimano DNTTRS | B34: 0 | C34: =C21 -> 594.93 | D34: =B34*C34 -> 0 | E34: 0 | F34: =F21 -> 594.93 | G34: =E34*F34 -> 0 | H34: 0 | I34: =I21 -> 586.92 | J34: =H34*I34 -> 0 | L34: 578.31 | M34: =K34*L34 -> 0 | O34: =O21 -> 578.31 | P34: =N34*O34 -> 0 | R34: =R21 -> 625.53 | S34: =Q34*R34 -> 0
A35: =A22 -> Aro 29 AL 21 Shimano DNTTRS | B35: 0 | C35: =C22 -> 526.96 | D35: =B35*C35 -> 0 | E35: 0 | F35: =F22 -> 526.96 | G35: =E35*F35 -> 0 | H35: 0 | I35: =I22 -> 514.28 | J35: =H35*I35 -> 0 | L35: 509.37 | M35: =K35*L35 -> 0 | O35: =O22 -> 505.53 | P35: =N35*O35 -> 0 | R35: =R22 -> 555.74 | S35: =Q35*R35 -> 0
A36: =A23 -> Aro 29 AL 24 Imp | B36: 0 | C36: =C23 -> 487.17 | D36: =B36*C36 -> 0 | E36: 0 | F36: =F23 -> 487.17 | G36: =E36*F36 -> 0 | H36: 0 | I36: =I23 -> 479.16 | J36: =H36*I36 -> 0 | L36: 470.56 | M36: =K36*L36 -> 0 | O36: =O23 -> 467.02 | P36: =N36*O36 -> 0 | R36: =R23 -> 518.85 | S36: =Q36*R36 -> 0
A37: =A24 -> Aro 29 aço 21 Imp c/ Suspensão (Nova) | B37: 0 | C37: =C24 -> 0 | D37: =B37*C37 -> 0 | E37: 0 | F37: =F24 -> 0 | G37: =E37*F37 -> 0 | H37: 0 | I37: =I24 -> 418.3 | J37: =H37*I37 -> 0 | L37: 418.3 | M37: =K37*L37 -> 0 | O37: =O24 -> 406.87 | P37: =N37*O37 -> 0 | R37: =R24 -> 463.14 | S37: =Q37*R37 -> 0
B38: =SUM(B29:B37) -> 158 | C38: =D38/B38 -> 286.51 | D38: =SUM(D29:D37) -> 45268.58 | E38: =SUM(E29:E37) -> 158 | F38: =G38/E38 -> 286.51 | G38: =SUM(G29:G37) -> 45268.58 | H38: =SUM(H29:H37) -> 158 | I38: =J38/H38 -> 291.08 | J38: =SUM(J29:J37) -> 45990.64 | K38: =SUM(K29:K37) -> 88 | L38: =M38/K38 -> 286.51 | M38: =SUM(M29:M37) -> 25212.88 | N38: =SUM(N29:N37) -> 54 | O38: =P38/N38 -> 288.6 | P38: =SUM(P29:P37) -> 15584.4 | Q38: =SUM(Q29:Q37) -> 0 | R38: =S38/Q38 -> #DIV/0! | S38: =SUM(S29:S37) -> 0

Sheet DRE
B1: GOTT DEMONSTRATIVO DE RESULTADOS | C1: out/25 | E1: nov/25 | H1: dez/25 | K1: jan/26 | N1: fev/26 | Q1: mar/26
C2: R$ | D2: A.V. | E2: R$ | F2: A.V. | G2: A.H. | H2: R$ | I2: A.V. | J2: A.H. | K2: R$ | L2: A.V. | M2: A.H. | N2: R$ | O2: A.V. | P2: A.H. | Q2: R$ | R2: A.V. | S2: A.H.
A3: Gráfico linha | B3: (+) FATURAMENTO BRUTO | C3: 1207207 | D3: =C3/C$3 -> 1 | E3: 1594226.2 | F3: =E3/E$3 -> 1 | G3: =IFERROR(E3/C3-1,0) -> 0.32059063 | H3: 1443037.2 | I3: =H3/H$3 -> 1 | J3: =IFERROR(H3/E3-1,0) -> -0.094835373 | K3: 1101552 | L3: =K3/K$3 -> 1 | M3: =IFERROR(K3/H3-1,0) -> -0.23664337 | N3: 936890.74 | O3: =N3/N$3 -> 1 | P3: =IFERROR(N3/K3-1,0) -> -0.14948117 | Q3: 1373580.8 | R3: =Q3/Q$3 -> 1 | S3: =IFERROR(Q3/N3-1,0) -> 0.46610565
A4: Gráfico linha | B4: (-) IMPOSTOS S/ VENDAS | C4: 35650.83 | D4: =C4/C$3 -> 0.029531663 | E4: 21104.11 | F4: =E4/E$3 -> 0.013237839 | G4: =IFERROR(E4/C4-1,0) -> -0.40803314 | H4: 19335 | I4: =H4/H$3 -> 0.013398823 | J4: =IFERROR(H4/E4-1,0) -> -0.083827747 | K4: 15811.61 | L4: =K4/K$3 -> 0.014353939 | M4: =IFERROR(K4/H4-1,0) -> -0.1822286 | N4: =1.5%*N3 -> 14053.361 | O4: =N4/N$3 -> 0.015 | P4: =IFERROR(N4/K4-1,0) -> -0.11119987 | Q4: 29702.17 | R4: =Q4/Q$3 -> 0.021623897 | S4: =IFERROR(Q4/N4-1,0) -> 1.1135278
B5: (-) DEVOLUÇÕES | C5: 0 | D5: =C5/C$3 -> 0 | E5: 0 | F5: =E5/E$3 -> 0 | G5: =IFERROR(E5/C5-1,0) -> 0 | H5: 0 | I5: =H5/H$3 -> 0 | J5: =IFERROR(H5/E5-1,0) -> 0 | K5: 0 | L5: =K5/K$3 -> 0 | M5: =IFERROR(K5/H5-1,0) -> 0 | N5: 0 | O5: =N5/N$3 -> 0 | P5: =IFERROR(N5/K5-1,0) -> 0 | Q5: 0 | R5: =Q5/Q$3 -> 0 | S5: =IFERROR(Q5/N5-1,0) -> 0
A6: Gráfico linha | B6: (-) DESPESAS COM TRANSPORTE | C6: =SUM(C7:C9) -> 9199.86 | D6: =C6/C$3 -> 0.0076207809 | E6: =SUM(E7:E9) -> 1174.88 | F6: =E6/E$3 -> 0.00073695939 | G6: =IFERROR(E6/C6-1,0) -> -0.87229371 | H6: =SUM(H7:H9) -> 6687.27 | I6: =H6/H$3 -> 0.0046341633 | J6: =IFERROR(H6/E6-1,0) -> 4.6918749 | K6: =SUM(K7:K9) -> 20376.21 | L6: =K6/K$3 -> 0.018497728 | M6: =IFERROR(K6/H6-1,0) -> 2.0470147 | N6: =SUM(N7:N9) -> 31195.07 | O6: =N6/N$3 -> 0.03329638 | P6: =IFERROR(N6/K6-1,0) -> 0.53095546 | Q6: =SUM(Q7:Q9) -> 23710.91 | R6: =Q6/Q$3 -> 0.017262115 | S6: =IFERROR(Q6/N6-1,0) -> -0.23991483
B7: TRANSPORTE - PAGAMENTO ENTREGA | C7: 6905.45 | D7: =C7/C$3 -> 0.0057201872 | E7: 0 | F7: =E7/E$3 -> 0 | G7: =IFERROR(E7/C7-1,0) -> -1 | H7: 0 | I7: =H7/H$3 -> 0 | J7: =IFERROR(H7/E7-1,0) -> 0 | K7: 0 | L7: =K7/K$3 -> 0 | M7: =IFERROR(K7/H7-1,0) -> 0 | N7: 0 | O7: =N7/N$3 -> 0 | P7: =IFERROR(N7/K7-1,0) -> 0 | Q7: 0 | R7: =Q7/Q$3 -> 0 | S7: =IFERROR(Q7/N7-1,0) -> 0
B8: TRANSPORTE - PAGAMENTO FRETE | C8: 310 | D8: =C8/C$3 -> 0.00025679109 | E8: 0 | F8: =E8/E$3 -> 0 | G8: =IFERROR(E8/C8-1,0) -> -1 | H8: 0 | I8: =H8/H$3 -> 0 | J8: =IFERROR(H8/E8-1,0) -> 0 | K8: 0 | L8: =K8/K$3 -> 0 | M8: =IFERROR(K8/H8-1,0) -> 0 | N8: 0 | O8: =N8/N$3 -> 0 | P8: =IFERROR(N8/K8-1,0) -> 0 | Q8: 0 | R8: =Q8/Q$3 -> 0 | S8: =IFERROR(Q8/N8-1,0) -> 0
B9: FRETE DE SAÍDA | C9: 1984.41 | D9: =C9/C$3 -> 0.0016438026 | E9: 1174.88 | F9: =E9/E$3 -> 0.00073695939 | G9: =IFERROR(E9/C9-1,0) -> -0.40794493 | H9: 6687.27 | I9: =H9/H$3 -> 0.0046341633 | J9: =IFERROR(H9/E9-1,0) -> 4.6918749 | K9: 20376.21 | L9: =K9/K$3 -> 0.018497728 | M9: =IFERROR(K9/H9-1,0) -> 2.0470147 | N9: 31195.07 | O9: =N9/N$3 -> 0.03329638 | P9: =IFERROR(N9/K9-1,0) -> 0.53095546 | Q9: 23710.91 | R9: =Q9/Q$3 -> 0.017262115 | S9: =IFERROR(Q9/N9-1,0) -> -0.23991483
B10: (-) RECEITA OPERACIONAL LÍQUIDA | C10: =C3-C4-C5-C6 -> 1162356.3 | D10: =C10/C$3 -> 0.96284756 | E10: =E3-E4-E5-E6 -> 1571947.2 | F10: =E10/E$3 -> 0.9860252 | G10: =IFERROR(E10/C10-1,0) -> 0.35237986 | H10: =H3-H4-H5-H6 -> 1417014.9 | I10: =H10/H$3 -> 0.98196701 | J10: =IFERROR(H10/E10-1,0) -> -0.098560763 | K10: =K3-K4-K5-K6 -> 1065364.2 | L10: =K10/K$3 -> 0.96714833 | M10: =IFERROR(K10/H10-1,0) -> -0.24816304 | N10: =N3-N4-N5-N6 -> 891642.31 | O10: =N10/N$3 -> 0.95170362 | P10: =IFERROR(N10/K10-1,0) -> -0.16306338 | Q10: =Q3-Q4-Q5-Q6 -> 1320167.7 | R10: =Q10/Q$3 -> 0.96111399 | S10: =IFERROR(Q10/N10-1,0) -> 0.48060239
A11: Gráfico linha | B11: (-) CUSTOS VARIÁVEIS OPERACIONAIS | C11: =C12+C13 -> 923317.34 | D11: =C11/C$3 -> 0.76483764 | E11: =E12+E13 -> 1282104.1 | F11: =E11/E$3 -> 0.80421716 | G11: =IFERROR(E11/C11-1,0) -> 0.38858444 | H11: =H12+H13 -> 1119132.4 | I11: =H11/H$3 -> 0.77553956 | J11: =IFERROR(H11/E11-1,0) -> -0.12711266 | K11: =K12+K13 -> 865095.17 | L11: =K11/K$3 -> 0.7853421 | M11: =IFERROR(K11/H11-1,0) -> -0.22699481 | N11: =N12+N13 -> 755745.51 | O11: =N11/N$3 -> 0.80665277 | P11: =IFERROR(N11/K11-1,0) -> -0.12640189 | Q11: =Q12+Q13 -> 1074369.7 | R11: =Q11/Q$3 -> 0.7821671 | S11: =IFERROR(Q11/N11-1,0) -> 0.42160252
A12: Gráfico linha | B12: (-) CUSTO DOS PRODUTOS VENDIDOS | C12: =662325.14+45268.58 -> 707593.72 | D12: =C12/C$3 -> 0.58614117 | E12: =953356.62+45268.58 -> 998625.2 | F12: =E12/E$3 -> 0.62640118 | G12: =IFERROR(E12/C12-1,0) -> 0.41129743 | H12: 857572.81 | I12: =H12/H$3 -> 0.59428323 | J12: =IFERROR(H12/E12-1,0) -> -0.14124658 | K12: 667576.62 | L12: =K12/K$3 -> 0.60603277 | M12: =IFERROR(K12/H12-1,0) -> -0.22155109 | N12: 577935.69 | O12: =N12/N$3 -> 0.61686562 | P12: =IFERROR(N12/K12-1,0) -> -0.13427811 | Q12: 817037.46 | R12: =Q12/Q$3 -> 0.594823 | S12: =IFERROR(Q12/N12-1,0) -> 0.41371691
A13: Gráfico linha | B13: (-) DESPESAS DE VENDA | C13: =SUM(C14:C20) -> 215723.62 | D13: =C13/C$3 -> 0.17869647 | E13: =SUM(E14:E20) -> 283478.89 | F13: =E13/E$3 -> 0.17781597 | G13: =IFERROR(E13/C13-1,0) -> 0.31408368 | H13: =SUM(H14:H20) -> 261559.62 | I13: =H13/H$3 -> 0.18125633 | J13: =IFERROR(H13/E13-1,0) -> -0.077322413 | K13: =SUM(K14:K20) -> 197518.55 | L13: =K13/K$3 -> 0.17930933 | M13: =IFERROR(K13/H13-1,0) -> -0.24484309 | N13: =SUM(N14:N20) -> 177809.82 | O13: =N13/N$3 -> 0.18978715 | P13: =IFERROR(N13/K13-1,0) -> -0.099781685 | Q13: =SUM(Q14:Q20) -> 257332.26 | R13: =Q13/Q$3 -> 0.1873441 | S13: =IFERROR(Q13/N13-1,0) -> 0.44723313
B14: COMISSÕES AFILIADOS | C14: =1.5%*C3 -> 18108.105 | D14: =C14/C$3 -> 0.015 | E14: =1.5%*E3 -> 23913.394 | F14: =E14/E$3 -> 0.015 | G14: =IFERROR(E14/C14-1,0) -> 0.32059063 | H14: =1.5%*H3 -> 21645.558 | I14: =H14/H$3 -> 0.015 | J14: =IFERROR(H14/E14-1,0) -> -0.094835373 | K14: =1.5%*K3 -> 16523.28 | L14: =K14/K$3 -> 0.015 | M14: =IFERROR(K14/H14-1,0) -> -0.23664337 | N14: =1.5%*N3 -> 14053.361 | O14: =N14/N$3 -> 0.015 | P14: =IFERROR(N14/K14-1,0) -> -0.14948117 | Q14: =1.5%*Q3 -> 20603.712 | R14: =Q14/Q$3 -> 0.015 | S14: =IFERROR(Q14/N14-1,0) -> 0.46610565
B15: COMISSÕES E TAXAS DOS MARKETPLACES | C15: =16%*C3 -> 193153.12 | D15: =C15/C$3 -> 0.16 | E15: =16%*E3 -> 255076.2 | F15: =E15/E$3 -> 0.16 | G15: =IFERROR(E15/C15-1,0) -> 0.32059063 | H15: =16%*H3 -> 230885.95 | I15: =H15/H$3 -> 0.16 | J15: =IFERROR(H15/E15-1,0) -> -0.094835373 | K15: =16%*K3 -> 176248.32 | L15: =K15/K$3 -> 0.16 | M15: =IFERROR(K15/H15-1,0) -> -0.23664337 | N15: =16%*N3 -> 149902.52 | O15: =N15/N$3 -> 0.16 | P15: =IFERROR(N15/K15-1,0) -> -0.14948117 | Q15: =16%*Q3 -> 219772.93 | R15: =Q15/Q$3 -> 0.16 | S15: =IFERROR(Q15/N15-1,0) -> 0.46610565
B16: ANYMARKET TAXAS | C16: 4053.4 | D16: =C16/C$3 -> 0.0033576678 | E16: 4449.3 | F16: =E16/E$3 -> 0.0027908837 | G16: =IFERROR(E16/C16-1,0) -> 0.097671091 | H16: 4329.11 | I16: =H16/H$3 -> 0.0029999989 | J16: =IFERROR(H16/E16-1,0) -> -0.027013238 | K16: 4422.55 | L16: =K16/K$3 -> 0.0040148354 | M16: =IFERROR(K16/H16-1,0) -> 0.021584113 | N16: 4178.94 | O16: =N16/N$3 -> 0.0044604347 | P16: =IFERROR(N16/K16-1,0) -> -0.055083606 | Q16: 3460.62 | R16: =Q16/Q$3 -> 0.0025194149 | S16: =IFERROR(Q16/N16-1,0) -> -0.17189048
B17: ADS MAGALU | C17: 0 | D17: =C17/C$3 -> 0 | E17: 0 | F17: =E17/E$3 -> 0 | G17: =IFERROR(E17/C17-1,0) -> 0 | H17: 4000 | I17: =H17/H$3 -> 0.0027719313 | J17: =IFERROR(H17/E17-1,0) -> 0 | K17: 0 | L17: =K17/K$3 -> 0 | M17: =IFERROR(K17/H17-1,0) -> -1 | N17: 0 | O17: =N17/N$3 -> 0 | P17: =IFERROR(N17/K17-1,0) -> 0 | Q17: 1200 | R17: =Q17/Q$3 -> 0.00087362898 | S17: =IFERROR(Q17/N17-1,0) -> 0
B18: ADS SHOPEE | C18: 0 | D18: =C18/C$3 -> 0 | E18: 0 | F18: =E18/E$3 -> 0 | G18: =IFERROR(E18/C18-1,0) -> 0 | H18: 0 | I18: =H18/H$3 -> 0 | J18: =IFERROR(H18/E18-1,0) -> 0 | K18: 0 | L18: =K18/K$3 -> 0 | M18: =IFERROR(K18/H18-1,0) -> 0 | N18: 6600 | O18: =N18/N$3 -> 0.0070445781 | P18: =IFERROR(N18/K18-1,0) -> 0 | Q18: 10000 | R18: =Q18/Q$3 -> 0.0072802415 | S18: =IFERROR(Q18/N18-1,0) -> 0.51515152
B19: ADS TIKTOK | C19: 0 | D19: =C19/C$3 -> 0 | E19: 0 | F19: =E19/E$3 -> 0 | G19: =IFERROR(E19/C19-1,0) -> 0 | H19: 0 | I19: =H19/H$3 -> 0 | J19: =IFERROR(H19/E19-1,0) -> 0 | K19: 0 | L19: =K19/K$3 -> 0 | M19: =IFERROR(K19/H19-1,0) -> 0 | N19: 0 | O19: =N19/N$3 -> 0 | P19: =IFERROR(N19/K19-1,0) -> 0 | Q19: 2000 | R19: =Q19/Q$3 -> 0.0014560483 | S19: =IFERROR(Q19/N19-1,0) -> 0
B20: REEMBOLSO SAC | C20: 409 | D20: =C20/C$3 -> 0.00033879857 | E20: 40 | F20: =E20/E$3 -> 2.5090542e-05 | G20: =IFERROR(E20/C20-1,0) -> -0.90220049 | H20: 699 | I20: =H20/H$3 -> 0.000484395 | J20: =IFERROR(H20/E20-1,0) -> 16.475 | K20: 324.4 | L20: =K20/K$3 -> 0.00029449358 | M20: =IFERROR(K20/H20-1,0) -> -0.53590844 | N20: 3075 | O20: =N20/N$3 -> 0.003282133 | P20: =IFERROR(N20/K20-1,0) -> 8.4790382 | Q20: 295 | R20: =Q20/Q$3 -> 0.00021476712 | S20: =IFERROR(Q20/N20-1,0) -> -0.90406504
A21: Gráfico linha | B21: (=) MARGEM DE CONTRIBUIÇÃO | C21: =C10-C11 -> 239038.96 | D21: =C21/C$3 -> 0.19800992 | E21: =E10-E11 -> 289843.16 | F21: =E21/E$3 -> 0.18180805 | G21: =IFERROR(E21/C21-1,0) -> 0.21253524 | H21: =H10-H11 -> 297882.5 | I21: =H21/H$3 -> 0.20642746 | J21: =IFERROR(H21/E21-1,0) -> 0.02773687 | K21: =K10-K11 -> 200269.03 | L21: =K21/K$3 -> 0.18180624 | M21: =IFERROR(K21/H21-1,0) -> -0.3276912 | N21: =N10-N11 -> 135896.8 | O21: =N21/N$3 -> 0.14505085 | P21: =IFERROR(N21/K21-1,0) -> -0.32142877 | Q21: =Q10-Q11 -> 245798.01 | R21: =Q21/Q$3 -> 0.17894689 | S21: =IFERROR(Q21/N21-1,0) -> 0.8087108
A22: Gráfico linha | B22: (-) CUSTOS FIXOS OPERACIONAIS | C22: 93406.07 | D22: =C22/C$3 -> 0.077373699 | E22: 104939.41 | F22: =E22/E$3 -> 0.065824666 | G22: =IFERROR(E22/C22-1,0) -> 0.12347527 | H22: 108655.94 | I22: =H22/H$3 -> 0.075296701 | J22: =IFERROR(H22/E22-1,0) -> 0.035415961 | K22: 119972.84 | L22: =K22/K$3 -> 0.10891255 | M22: =IFERROR(K22/H22-1,0) -> 0.10415353 | N22: =104587.45+14938.92 -> 119526.37 | O22: =N22/N$3 -> 0.1275777 | P22: =IFERROR(N22/K22-1,0) -> -0.0037214256 | Q22: =152982.51-14938.92 -> 138043.59 | R22: =Q22/Q$3 -> 0.10049907 | S22: =IFERROR(Q22/N22-1,0) -> 0.15492163
A23: Gráfico linha | B23: (=) RESULTADO OPERACIONAL | C23: =C21-C22 -> 145632.89 | D23: =C23/C$3 -> 0.12063622 | E23: =E21-E22 -> 184903.75 | F23: =E23/E$3 -> 0.11598338 | G23: =IFERROR(E23/C23-1,0) -> 0.26965655 | H23: =H21-H22 -> 189226.56 | I23: =H23/H$3 -> 0.13113076 | J23: =IFERROR(H23/E23-1,0) -> 0.023378715 | K23: =K21-K22 -> 80296.186 | L23: =K23/K$3 -> 0.072893685 | M23: =IFERROR(K23/H23-1,0) -> -0.57566112 | N23: =N21-N22 -> 16370.429 | O23: =N23/N$3 -> 0.017473147 | P23: =IFERROR(N23/K23-1,0) -> -0.79612445 | Q23: =Q21-Q22 -> 107754.42 | R23: =Q23/Q$3 -> 0.078447819 | S23: =IFERROR(Q23/N23-1,0) -> 5.5822597
A24: Gráfico linha | B24: (-) IMPOSTO SOBRE O LUCRO | C24: 0 | D24: =C24/C$3 -> 0 | E24: 0 | F24: =E24/E$3 -> 0 | G24: =IFERROR(E24/C24-1,0) -> 0 | H24: 0 | I24: =H24/H$3 -> 0 | J24: =IFERROR(H24/E24-1,0) -> 0 | K24: 0 | L24: =K24/K$3 -> 0 | M24: =IFERROR(K24/H24-1,0) -> 0 | N24: 0 | O24: =N24/N$3 -> 0 | P24: =IFERROR(N24/K24-1,0) -> 0 | Q24: 0 | R24: =Q24/Q$3 -> 0 | S24: =IFERROR(Q24/N24-1,0) -> 0
B25: (=) RESULTADO APÓS IMPOSTO SOBRE O LUCRO | C25: =C23-C24 -> 145632.89 | D25: =C25/C$3 -> 0.12063622 | E25: =E23-E24 -> 184903.75 | F25: =E25/E$3 -> 0.11598338 | G25: =IFERROR(E25/C25-1,0) -> 0.26965655 | H25: =H23-H24 -> 189226.56 | I25: =H25/H$3 -> 0.13113076 | J25: =IFERROR(H25/E25-1,0) -> 0.023378715 | K25: =K23-K24 -> 80296.186 | L25: =K25/K$3 -> 0.072893685 | M25: =IFERROR(K25/H25-1,0) -> -0.57566112 | N25: =N23-N24 -> 16370.429 | O25: =N25/N$3 -> 0.017473147 | P25: =IFERROR(N25/K25-1,0) -> -0.79612445 | Q25: =Q23-Q24 -> 107754.42 | R25: =Q25/Q$3 -> 0.078447819 | S25: =IFERROR(Q25/N25-1,0) -> 5.5822597
A26: Gráfico linha | B26: (-) DESPESAS NÃO OPERACIONAIS | C26: 0 | D26: =C26/C$3 -> 0 | E26: 0 | F26: =E26/E$3 -> 0 | G26: =IFERROR(E26/C26-1,0) -> 0 | H26: 0 | I26: =H26/H$3 -> 0 | J26: =IFERROR(H26/E26-1,0) -> 0 | K26: 0 | L26: =K26/K$3 -> 0 | M26: =IFERROR(K26/H26-1,0) -> 0 | N26: 0 | O26: =N26/N$3 -> 0 | P26: =IFERROR(N26/K26-1,0) -> 0 | Q26: 0 | R26: =Q26/Q$3 -> 0 | S26: =IFERROR(Q26/N26-1,0) -> 0
A27: Gráfico linha | B27: (+) RECEITAS NÃO OPERACIONAIS | C27: 0 | D27: =C27/C$3 -> 0 | E27: 0 | F27: =E27/E$3 -> 0 | G27: =IFERROR(E27/C27-1,0) -> 0 | H27: 0 | I27: =H27/H$3 -> 0 | J27: =IFERROR(H27/E27-1,0) -> 0 | K27: 0 | L27: =K27/K$3 -> 0 | M27: =IFERROR(K27/H27-1,0) -> 0 | N27: 0 | O27: =N27/N$3 -> 0 | P27: =IFERROR(N27/K27-1,0) -> 0 | Q27: 0 | R27: =Q27/Q$3 -> 0 | S27: =IFERROR(Q27/N27-1,0) -> 0
B28: (=) RESULTADO APÓS DESPESAS E RECEITAS NÃO OPERACIONAIS | C28: =C25-C26+C27 -> 145632.89 | D28: =C28/C$3 -> 0.12063622 | E28: =E25-E26+E27 -> 184903.75 | F28: =E28/E$3 -> 0.11598338 | G28: =IFERROR(E28/C28-1,0) -> 0.26965655 | H28: =H25-H26+H27 -> 189226.56 | I28: =H28/H$3 -> 0.13113076 | J28: =IFERROR(H28/E28-1,0) -> 0.023378715 | K28: =K25-K26+K27 -> 80296.186 | L28: =K28/K$3 -> 0.072893685 | M28: =IFERROR(K28/H28-1,0) -> -0.57566112 | N28: =N25-N26+N27 -> 16370.429 | O28: =N28/N$3 -> 0.017473147 | P28: =IFERROR(N28/K28-1,0) -> -0.79612445 | Q28: =Q25-Q26+Q27 -> 107754.42 | R28: =Q28/Q$3 -> 0.078447819 | S28: =IFERROR(Q28/N28-1,0) -> 5.5822597
A29: Gráfico linha | B29: (-) INVESTIMENTOS | C29: 21070.83 | D29: =C29/C$3 -> 0.017454198 | E29: 15970.83 | F29: =E29/E$3 -> 0.010017919 | G29: =IFERROR(E29/C29-1,0) -> -0.24204077 | H29: 16822.6 | I29: =H29/H$3 -> 0.011657773 | J29: =IFERROR(H29/E29-1,0) -> 0.053332857 | K29: 0 | L29: =K29/K$3 -> 0 | M29: =IFERROR(K29/H29-1,0) -> -1 | N29: =184.12+15970.84 -> 16154.96 | O29: =N29/N$3 -> 0.017243163 | P29: =IFERROR(N29/K29-1,0) -> 0 | Q29: 32125.8 | R29: =Q29/Q$3 -> 0.023388358 | S29: =IFERROR(Q29/N29-1,0) -> 0.98860288
A30: Gráfico linha | B30: (-) AMORTIZAÇÕES | C30: 11652.6 | D30: =C30/C$3 -> 0.0096525286 | E30: 0 | F30: =E30/E$3 -> 0 | G30: =IFERROR(E30/C30-1,0) -> -1 | H30: 18274 | I30: =H30/H$3 -> 0.012663568 | J30: =IFERROR(H30/E30-1,0) -> 0 | K30: 32000 | L30: =K30/K$3 -> 0.029049922 | M30: =IFERROR(K30/H30-1,0) -> 0.75112181 | N30: 13000 | O30: =N30/N$3 -> 0.013875684 | P30: =IFERROR(N30/K30-1,0) -> -0.59375 | Q30: 17747.62 | R30: =Q30/Q$3 -> 0.012920696 | S30: =IFERROR(Q30/N30-1,0) -> 0.36520154
A31: Gráfico linha | B31: (=) RESULTADO ANTES DAS DISTRIBUIÇÕES | C31: =C28-C29-C30 -> 112909.46 | D31: =C31/C$3 -> 0.093529492 | E31: =E28-E29-E30 -> 168932.92 | F31: =E31/E$3 -> 0.10596546 | G31: =IFERROR(E31/C31-1,0) -> 0.49618042 | H31: =H28-H29-H30 -> 154129.96 | I31: =H31/H$3 -> 0.10680942 | J31: =IFERROR(H31/E31-1,0) -> -0.087626249 | K31: =K28-K29-K30 -> 48296.186 | L31: =K31/K$3 -> 0.043843764 | M31: =IFERROR(K31/H31-1,0) -> -0.68665283 | N31: =N28-N29-N30 -> -12784.531 | O31: =N31/N$3 -> -0.013645701 | P31: =IFERROR(N31/K31-1,0) -> -1.264711 | Q31: =Q28-Q29-Q30 -> 57880.998 | R31: =Q31/Q$3 -> 0.042138764 | S31: =IFERROR(Q31/N31-1,0) -> -5.5274246
A32: Gráfico linha | B32: (-) DISTRIBUIÇÃO DE LUCROS & OUTROS | C32: =SUM(C33:C36) -> 21445.72 | D32: =C32/C$3 -> 0.017764741 | E32: =SUM(E33:E36) -> 2067.41 | F32: =E32/E$3 -> 0.0012968109 | G32: =IFERROR(E32/C32-1,0) -> -0.90359801 | H32: =SUM(H33:H36) -> 4407.37 | I32: =H32/H$3 -> 0.0030542317 | J32: =IFERROR(H32/E32-1,0) -> 1.1318316 | K32: =SUM(K33:K36) -> 2067.37 | L32: =K32/K$3 -> 0.0018767793 | M32: =IFERROR(K32/H32-1,0) -> -0.53092888 | N32: =SUM(N33:N36) -> 2110.78 | O32: =N32/N$3 -> 0.0022529628 | P32: =IFERROR(N32/K32-1,0) -> 0.020997693 | Q32: =SUM(Q33:Q36) -> 5577.37 | R32: =Q32/Q$3 -> 0.00406046 | S32: =IFERROR(Q32/N32-1,0) -> 1.6423265
B33: DISTRIBUIÇÃO DE LUCROS | C33: 0 | D33: =C33/C$3 -> 0 | E33: 0 | F33: =E33/E$3 -> 0 | G33: =IFERROR(E33/C33-1,0) -> 0 | H33: 0 | I33: =H33/H$3 -> 0 | J33: =IFERROR(H33/E33-1,0) -> 0 | K33: 0 | L33: =K33/K$3 -> 0 | M33: =IFERROR(K33/H33-1,0) -> 0 | N33: 0 | O33: =N33/N$3 -> 0 | P33: =IFERROR(N33/K33-1,0) -> 0 | Q33: 0 | R33: =Q33/Q$3 -> 0 | S33: =IFERROR(Q33/N33-1,0) -> 0
B34: GRAN RESIDENCE | C34: 11025.97 | D34: =C34/C$3 -> 0.0091334544 | E34: 2067.41 | F34: =E34/E$3 -> 0.0012968109 | G34: =IFERROR(E34/C34-1,0) -> -0.81249632 | H34: 2067.37 | I34: =H34/H$3 -> 0.0014326519 | J34: =IFERROR(H34/E34-1,0) -> -1.934788e-05 | K34: 2067.37 | L34: =K34/K$3 -> 0.0018767793 | M34: =IFERROR(K34/H34-1,0) -> 0 | N34: 2110.78 | O34: =N34/N$3 -> 0.0022529628 | P34: =IFERROR(N34/K34-1,0) -> 0.020997693 | Q34: 2067.37 | R34: =Q34/Q$3 -> 0.0015050953 | S34: =IFERROR(Q34/N34-1,0) -> -0.020565857
B35: TERRENO LINHAM | C35: 8079.75 | D35: =C35/C$3 -> 0.0066929284 | E35: 0 | F35: =E35/E$3 -> 0 | G35: =IFERROR(E35/C35-1,0) -> -1 | H35: 0 | I35: =H35/H$3 -> 0 | J35: =IFERROR(H35/E35-1,0) -> 0 | K35: 0 | L35: =K35/K$3 -> 0 | M35: =IFERROR(K35/H35-1,0) -> 0 | N35: 0 | O35: =N35/N$3 -> 0 | P35: =IFERROR(N35/K35-1,0) -> 0 | Q35: 0 | R35: =Q35/Q$3 -> 0 | S35: =IFERROR(Q35/N35-1,0) -> 0
B36: PROJETO CASAS CONSTRUIR | C36: 2340 | D36: =C36/C$3 -> 0.0019383586 | E36: 0 | F36: =E36/E$3 -> 0 | G36: =IFERROR(E36/C36-1,0) -> -1 | H36: 2340 | I36: =H36/H$3 -> 0.0016215798 | J36: =IFERROR(H36/E36-1,0) -> 0 | K36: 0 | L36: =K36/K$3 -> 0 | M36: =IFERROR(K36/H36-1,0) -> -1 | N36: 0 | O36: =N36/N$3 -> 0 | P36: =IFERROR(N36/K36-1,0) -> 0 | Q36: 3510 | R36: =Q36/Q$3 -> 0.0025553648 | S36: =IFERROR(Q36/N36-1,0) -> 0
A37: Gráfico linha | B37: (=) RESULTADO APÓS DISTRIBUIÇÕES | C37: =C31-C32 -> 91463.737 | D37: =C37/C$3 -> 0.075764751 | E37: =E31-E32 -> 166865.51 | F37: =E37/E$3 -> 0.10466865 | G37: =IFERROR(E37/C37-1,0) -> 0.8243898 | H37: =H31-H32 -> 149722.59 | I37: =H37/H$3 -> 0.10375518 | J37: =IFERROR(H37/E37-1,0) -> -0.10273494 | K37: =K31-K32 -> 46228.816 | L37: =K37/K$3 -> 0.041966984 | M37: =IFERROR(K37/H37-1,0) -> -0.69123686 | N37: =N31-N32 -> -14895.311 | O37: =N37/N$3 -> -0.015898663 | P37: =IFERROR(N37/K37-1,0) -> -1.3222083 | Q37: =Q31-Q32 -> 52303.628 | R37: =Q37/Q$3 -> 0.038078304 | S37: =IFERROR(Q37/N37-1,0) -> -4.5114158
A39: Gráfico linha | B39: (=) PONTO DE EQUILÍBRIO GERENCIAL | C39: =IFERROR((C22+C24+C26+C29+C30+C32)/D21,0) -> 745292.06 | E39: =IFERROR((E22+E24+E26+E29+E30+E32)/F21,0) -> 676414.78 | H39: =IFERROR((H22+H24+H26+H29+H30+H32)/I21,0) -> 717733.54 | K39: =IFERROR((K22+K24+K26+K29+K30+K32)/L21,0) -> 847276.82 | N39: =IFERROR((N22+N24+N26+N29+N30+N32)/O21,0) -> 1039581 | Q39: =IFERROR((Q22+Q24+Q26+Q29+Q30+Q32)/R21,0) -> 1081295
A40: Gráfico linha | B40: (=) PONTO DE EQUILÍBRIO OPERACIONAL | C40: =IFERROR((C22)/D21,0) -> 471724.2 | E40: =IFERROR((E22)/F21,0) -> 577198.93 | H40: =IFERROR((H22)/I21,0) -> 526363.8 | K40: =IFERROR((K22)/L21,0) -> 659893.98 | N40: =IFERROR((N22)/O21,0) -> 824030.81 | Q40: =IFERROR((Q22)/R21,0) -> 771422.14

Sheet DFC
A1: GOTT DEMONSTRATIVO DE FLUXO DE CAIXA | B1: out/25 | D1: nov/25 | G1: dez/25 | J1: jan/26 | M1: fev/26 | P1: mar/26 | S1: abr/26
B2: R$ | C2: A.V. | D2: R$ | E2: A.V. | F2: A.H. | G2: R$ | H2: A.V. | I2: A.H. | J2: R$ | K2: A.V. | L2: A.H. | M2: R$ | N2: A.V. | O2: A.H. | P2: R$ | Q2: A.V. | R2: A.H. | S2: R$ | T2: A.V. | U2: A.H.
A3: (+) ENTRADAS OPERACIONAIS BRUTAS | B3: =SUM(B4:B4) -> 1123115.1 | C3: =B3/B$3 -> 1 | D3: =SUM(D4:D4) -> 988990.43 | E3: =D3/D$3 -> 1 | F3: =IFERROR(D3/B3-1,0) -> -0.11942205 | G3: =SUM(G4:G4) -> 1091503.2 | H3: =G3/G$3 -> 1 | I3: =IFERROR(G3/D3-1,0) -> 0.10365397 | J3: =SUM(J4:J4) -> 943022.31 | K3: =J3/J$3 -> 1 | L3: =IFERROR(J3/G3-1,0) -> -0.13603341 | M3: =SUM(M4:M4) -> 691744.49 | N3: =M3/M$3 -> 1 | O3: =IFERROR(M3/J3-1,0) -> -0.2664601 | P3: =SUM(P4:P4) -> 1036116.5 | Q3: =P3/P$3 -> 1 | R3: =IFERROR(P3/M3-1,0) -> 0.49783126 | S3: =SUM(S4:S4) -> 883700.3 | T3: =S3/S$3 -> 1 | U3: =IFERROR(S3/P3-1,0) -> -0.14710336
A4: RECEITA DE VENDA | B4: =1134115.13-10999.99 -> 1123115.1 | C4: =B4/B$3 -> 1 | D4: =1164757.48-145000-30767.05 -> 988990.43 | E4: =D4/D$3 -> 1 | F4: =IFERROR(D4/B4-1,0) -> -0.11942205 | G4: 1091503.2 | H4: =G4/G$3 -> 1 | I4: =IFERROR(G4/D4-1,0) -> 0.10365397 | J4: 943022.31 | K4: =J4/J$3 -> 1 | L4: =IFERROR(J4/G4-1,0) -> -0.13603341 | M4: =680744.49+11000 -> 691744.49 | N4: =M4/M$3 -> 1 | O4: =IFERROR(M4/J4-1,0) -> -0.2664601 | P4: 1036116.5 | Q4: =P4/P$3 -> 1 | R4: =IFERROR(P4/M4-1,0) -> 0.49783126 | S4: 883700.3 | T4: =S4/S$3 -> 1 | U4: =IFERROR(S4/P4-1,0) -> -0.14710336
A5: (-) IMPOSTOS S/ VENDAS | B5: =SUM(B6:B14) -> 15843.2 | C5: =B5/B$3 -> 0.014106479 | D5: =SUM(D6:D14) -> 35650.83 | E5: =D5/D$3 -> 0.0360477 | F5: =IFERROR(D5/B5-1,0) -> 1.2502291 | G5: =SUM(G6:G14) -> 21104.11 | H5: =G5/G$3 -> 0.019334904 | I5: =IFERROR(G5/D5-1,0) -> -0.40803314 | J5: =SUM(J6:J14) -> 19799.24 | K5: =J5/J$3 -> 0.020995516 | L5: =IFERROR(J5/G5-1,0) -> -0.061830136 | M5: =SUM(M6:M14) -> 15811.61 | N5: =M5/M$3 -> 0.022857587 | O5: =IFERROR(M5/J5-1,0) -> -0.20140319 | P5: =SUM(P6:P14) -> 29702.17 | Q5: =P5/P$3 -> 0.028666824 | R5: =IFERROR(P5/M5-1,0) -> 0.87850383 | S5: =SUM(S6:S14) -> 16859.56 | T5: =S5/S$3 -> 0.019078369 | U5: =IFERROR(S5/P5-1,0) -> -0.43237952
A6: ICMS SC | B6: =SUMIFS('C.Pagar'!G$2:G$4509,'C.Pagar'!D$2:D$4509,TRIM(A6),'C.Pagar'!K$2:K$4509,">=01/10/2025",'C.Pagar'!K$2:K$4509,"<=31/10/2025") -> 0 | C6: =B6/B$3 -> 0 | D6: =SUMIFS('C.Pagar'!G$2:G$4509,'C.Pagar'!D$2:D$4509,TRIM(A6),'C.Pagar'!K$2:K$4509,">=01/11/2025",'C.Pagar'!K$2:K$4509,"<=30/11/2025") -> 0 | E6: =D6/D$3 -> 0 | F6: =IFERROR(D6/B6-1,0) -> 0 | G6: =SUMIFS('C.Pagar'!G$2:G$4509,'C.Pagar'!D$2:D$4509,TRIM(A6),'C.Pagar'!K$2:K$4509,">=01/12/2025",'C.Pagar'!K$2:K$4509,"<=31/12/2025") -> 0 | H6: =G6/G$3 -> 0 | I6: =IFERROR(G6/D6-1,0) -> 0 | J6: =SUMIFS('C.Pagar'!G$2:G$4509,'C.Pagar'!D$2:D$4509,TRIM(A6),'C.Pagar'!K$2:K$4509,">=01/01/2026",'C.Pagar'!K$2:K$4509,"<=31/01/2026") -> 0 | K6: =J6/J$3 -> 0 | L6: =IFERROR(J6/G6-1,0) -> 0 | M6: =SUMIFS('C.Pagar'!$G$2:$G$4509,'C.Pagar'!$D$2:$D$4509,TRIM($A6),'C.Pagar'!$K$2:$K$4509,">=01/02/2026",'C.Pagar'!$K$2:$K$4509,"<=28/02/2026") -> 0 | N6: =M6/M$3 -> 0 | O6: =IFERROR(M6/J6-1,0) -> 0 | P6: =SUMIFS('C.Pagar'!$G$2:$G$4509,'C.Pagar'!$D$2:$D$4509,TRIM($A6),'C.Pagar'!$K$2:$K$4509,">=01/03/2026",'C.Pagar'!$K$2:$K$4509,"<=31/03/2026") -> 3349.76 | Q6: =P6/P$3 -> 0.0032329955 | R6: =IFERROR(P6/M6-1,0) -> 0 | S6: =SUMIFS('C.Pagar'!$G$2:$G$4509,'C.Pagar'!$D$2:$D$4509,TRIM($A6),'C.Pagar'!$K$2:$K$4509,">=01/04/2026",'C.Pagar'!$K$2:$K$4509,"<=30/04/2026") -> 5214.63 | T6: =S6/S$3 -> 0.0059009033 | U6: =IFERROR(S6/P6-1,0) -> 0.5567175
A7: ICMS SP | B7: =SUMIFS('C.Pagar'!G$2:G$4509,'C.Pagar'!D$2:D$4509,TRIM(A7),'C.Pagar'!K$2:K$4509,">=01/10/2025",'C.Pagar'!K$2:K$4509,"<=31/10/2025") -> 0 | C7: =B7/B$3 -> 0 | D7: =SUMIFS('C.Pagar'!G$2:G$4509,'C.Pagar'!D$2:D$4509,TRIM(A7),'C.Pagar'!K$2:K$4509,">=01/11/2025",'C.Pagar'!K$2:K$4509,"<=30/11/2025") -> 0 | E7: =D7/D$3 -> 0 | F7: =IFERROR(D7/B7-1,0) -> 0 | G7: =SUMIFS('C.Pagar'!G$2:G$4509,'C.Pagar'!D$2:D$4509,TRIM(A7),'C.Pagar'!K$2:K$4509,">=01/12/2025",'C.Pagar'!K$2:K$4509,"<=31/12/2025") -> 0 | H7: =G7/G$3 -> 0 | I7: =IFERROR(G7/D7-1,0) -> 0 | J7: =SUMIFS('C.Pagar'!G$2:G$4509,'C.Pagar'!D$2:D$4509,TRIM(A7),'C.Pagar'!K$2:K$4509,">=01/01/2026",'C.Pagar'!K$2:K$4509,"<=31/01/2026") -> 0 | K7: =J7/J$3 -> 0 | L7: =IFERROR(J7/G7-1,0) -> 0 | M7: =SUMIFS('C.Pagar'!$G$2:$G$4509,'C.Pagar'!$D$2:$D$4509,TRIM($A7),'C.Pagar'!$K$2:$K$4509,">=01/02/2026",'C.Pagar'!$K$2:$K$4509,"<=28/02/2026") -> 0 | N7: =M7/M$3 -> 0 | O7: =IFERROR(M7/J7-1,0) -> 0 | P7: =SUMIFS('C.Pagar'!$G$2:$G$4509,'C.Pagar'!$D$2:$D$4509,TRIM($A7),'C.Pagar'!$K$2:$K$4509,">=01/03/2026",'C.Pagar'!$K$2:$K$4509,"<=31/03/2026") -> 8749.4 | Q7: =P7/P$3 -> 0.008444417 | R7: =IFERROR(P7/M7-1,0) -> 0 | S7: =SUMIFS('C.Pagar'!$G$2:$G$4509,'C.Pagar'!$D$2:$D$4509,TRIM($A7),'C.Pagar'!$K$2:$K$4509,">=01/04/2026",'C.Pagar'!$K$2:$K$4509,"<=30/04/2026") -> 9757.13 | T7: =S7/S$3 -> 0.011041221 | U7: =IFERROR(S7/P7-1,0) -> 0.11517704
A8: PIS | B8: =SUMIFS('C.Pagar'!G$2:G$4509,'C.Pagar'!D$2:D$4509,TRIM(A8),'C.Pagar'!K$2:K$4509,">=01/10/2025",'C.Pagar'!K$2:K$4509,"<=31/10/2025") -> 0 | C8: =B8/B$3 -> 0 | D8: =SUMIFS('C.Pagar'!G$2:G$4509,'C.Pagar'!D$2:D$4509,TRIM(A8),'C.Pagar'!K$2:K$4509,">=01/11/2025",'C.Pagar'!K$2:K$4509,"<=30/11/2025") -> 0 | E8: =D8/D$3 -> 0 | F8: =IFERROR(D8/B8-1,0) -> 0 | G8: =SUMIFS('C.Pagar'!G$2:G$4509,'C.Pagar'!D$2:D$4509,TRIM(A8),'C.Pagar'!K$2:K$4509,">=01/12/2025",'C.Pagar'!K$2:K$4509,"<=31/12/2025") -> 0 | H8: =G8/G$3 -> 0 | I8: =IFERROR(G8/D8-1,0) -> 0 | J8: =SUMIFS('C.Pagar'!G$2:G$4509,'C.Pagar'!D$2:D$4509,TRIM(A8),'C.Pagar'!K$2:K$4509,">=01/01/2026",'C.Pagar'!K$2:K$4509,"<=31/01/2026") -> 0 | K8: =J8/J$3 -> 0 | L8: =IFERROR(J8/G8-1,0) -> 0 | M8: =SUMIFS('C.Pagar'!$G$2:$G$4509,'C.Pagar'!$D$2:$D$4509,TRIM($A8),'C.Pagar'!$K$2:$K$4509,">=01/02/2026",'C.Pagar'!$K$2:$K$4509,"<=28/02/2026") -> 0 | N8: =M8/M$3 -> 0 | O8: =IFERROR(M8/J8-1,0) -> 0 | P8: =SUMIFS('C.Pagar'!$G$2:$G$4509,'C.Pagar'!$D$2:$D$4509,TRIM($A8),'C.Pagar'!$K$2:$K$4509,">=01/03/2026",'C.Pagar'!$K$2:$K$4509,"<=31/03/2026") -> 1430.61 | Q8: =P8/P$3 -> 0.0013807424 | R8: =IFERROR(P8/M8-1,0) -> 0 | S8: =SUMIFS('C.Pagar'!$G$2:$G$4509,'C.Pagar'!$D$2:$D$4509,TRIM($A8),'C.Pagar'!$K$2:$K$4509,">=01/04/2026",'C.Pagar'!$K$2:$K$4509,"<=30/04/2026") -> 0 | T8: =S8/S$3 -> 0 | U8: =IFERROR(S8/P8-1,0) -> -1
A9: COFINS | B9: =SUMIFS('C.Pagar'!G$2:G$4509,'C.Pagar'!D$2:D$4509,TRIM(A9),'C.Pagar'!K$2:K$4509,">=01/10/2025",'C.Pagar'!K$2:K$4509,"<=31/10/2025") -> 0 | C9: =B9/B$3 -> 0 | D9: =SUMIFS('C.Pagar'!G$2:G$4509,'C.Pagar'!D$2:D$4509,TRIM(A9),'C.Pagar'!K$2:K$4509,">=01/11/2025",'C.Pagar'!K$2:K$4509,"<=30/11/2025") -> 0 | E9: =D9/D$3 -> 0 | F9: =IFERROR(D9/B9-1,0) -> 0 | G9: =SUMIFS('C.Pagar'!G$2:G$4509,'C.Pagar'!D$2:D$4509,TRIM(A9),'C.Pagar'!K$2:K$4509,">=01/12/2025",'C.Pagar'!K$2:K$4509,"<=31/12/2025") -> 0 | H9: =G9/G$3 -> 0 | I9: =IFERROR(G9/D9-1,0) -> 0 | J9: =SUMIFS('C.Pagar'!$G$2:$G$4509,'C.Pagar'!$D$2:$D$4509,TRIM($A9),'C.Pagar'!$K$2:$K$4509,">=01/01/2026",'C.Pagar'!$K$2:$K$4509,"<=31/01/2026") -> 0 | K9: =J9/J$3 -> 0 | L9: =IFERROR(J9/G9-1,0) -> 0 | M9: =SUMIFS('C.Pagar'!$G$2:$G$4509,'C.Pagar'!$D$2:$D$4509,TRIM($A9),'C.Pagar'!$K$2:$K$4509,">=01/02/2026",'C.Pagar'!$K$2:$K$4509,"<=28/02/2026") -> 0 | N9: =M9/M$3 -> 0 | O9: =IFERROR(M9/J9-1,0) -> 0 | P9: =SUMIFS('C.Pagar'!$G$2:$G$4509,'C.Pagar'!$D$2:$D$4509,TRIM($A9),'C.Pagar'!$K$2:$K$4509,">=01/03/2026",'C.Pagar'!$K$2:$K$4509,"<=31/03/2026") -> 6361.43 | Q9: =P9/P$3 -> 0.0061396859 | R9: =IFERROR(P9/M9-1,0) -> 0 | S9: =SUMIFS('C.Pagar'!$G$2:$G$4509,'C.Pagar'!$D$2:$D$4509,TRIM($A9),'C.Pagar'!$K$2:$K$4509,">=01/04/2026",'C.Pagar'!$K$2:$K$4509,"<=30/04/2026") -> 0 | T9: =S9/S$3 -> 0 | U9: =IFERROR(S9/P9-1,0) -> -1
A10: DIFAL | B10: =SUMIFS('C.Pagar'!G$2:G$4509,'C.Pagar'!D$2:D$4509,TRIM(A10),'C.Pagar'!K$2:K$4509,">=01/10/2025",'C.Pagar'!K$2:K$4509,"<=31/10/2025") -> 0 | C10: =B10/B$3 -> 0 | D10: =SUMIFS('C.Pagar'!G$2:G$4509,'C.Pagar'!D$2:D$4509,TRIM(A10),'C.Pagar'!K$2:K$4509,">=01/11/2025",'C.Pagar'!K$2:K$4509,"<=30/11/2025") -> 0 | E10: =D10/D$3 -> 0 | F10: =IFERROR(D10/B10-1,0) -> 0 | G10: =SUMIFS('C.Pagar'!G$2:G$4509,'C.Pagar'!D$2:D$4509,TRIM(A10),'C.Pagar'!K$2:K$4509,">=01/12/2025",'C.Pagar'!K$2:K$4509,"<=31/12/2025") -> 0 | H10: =G10/G$3 -> 0 | I10: =IFERROR(G10/D10-1,0) -> 0 | J10: =SUMIFS('C.Pagar'!$G$2:$G$4509,'C.Pagar'!$D$2:$D$4509,TRIM($A10),'C.Pagar'!$K$2:$K$4509,">=01/01/2026",'C.Pagar'!$K$2:$K$4509,"<=31/01/2026") -> 0 | K10: =J10/J$3 -> 0 | L10: =IFERROR(J10/G10-1,0) -> 0 | M10: =SUMIFS('C.Pagar'!$G$2:$G$4509,'C.Pagar'!$D$2:$D$4509,TRIM($A10),'C.Pagar'!$K$2:$K$4509,">=01/02/2026",'C.Pagar'!$K$2:$K$4509,"<=28/02/2026") -> 0 | N10: =M10/M$3 -> 0 | O10: =IFERROR(M10/J10-1,0) -> 0 | P10: =SUMIFS('C.Pagar'!$G$2:$G$4509,'C.Pagar'!$D$2:$D$4509,TRIM($A10),'C.Pagar'!$K$2:$K$4509,">=01/03/2026",'C.Pagar'!$K$2:$K$4509,"<=31/03/2026") -> 852.59 | Q10: =P10/P$3 -> 0.00082287077 | R10: =IFERROR(P10/M10-1,0) -> 0 | S10: =SUMIFS('C.Pagar'!$G$2:$G$4509,'C.Pagar'!$D$2:$D$4509,TRIM($A10),'C.Pagar'!$K$2:$K$4509,">=01/04/2026",'C.Pagar'!$K$2:$K$4509,"<=30/04/2026") -> 829.27 | T10: =S10/S$3 -> 0.00093840638 | U10: =IFERROR(S10/P10-1,0) -> -0.027351951
A11: FUNDO EDUCAÇÃO SC | B11: =SUMIFS('C.Pagar'!G$2:G$4509,'C.Pagar'!D$2:D$4509,TRIM(A11),'C.Pagar'!K$2:K$4509,">=01/10/2025",'C.Pagar'!K$2:K$4509,"<=31/10/2025") -> 0 | C11: =B11/B$3 -> 0 | D11: =SUMIFS('C.Pagar'!G$2:G$4509,'C.Pagar'!D$2:D$4509,TRIM(A11),'C.Pagar'!K$2:K$4509,">=01/11/2025",'C.Pagar'!K$2:K$4509,"<=30/11/2025") -> 0 | E11: =D11/D$3 -> 0 | F11: =IFERROR(D11/B11-1,0) -> 0 | G11: =SUMIFS('C.Pagar'!G$2:G$4509,'C.Pagar'!D$2:D$4509,TRIM(A11),'C.Pagar'!K$2:K$4509,">=01/12/2025",'C.Pagar'!K$2:K$4509,"<=31/12/2025") -> 0 | H11: =G11/G$3 -> 0 | I11: =IFERROR(G11/D11-1,0) -> 0 | J11: =SUMIFS('C.Pagar'!$G$2:$G$4509,'C.Pagar'!$D$2:$D$4509,TRIM($A11),'C.Pagar'!$K$2:$K$4509,">=01/01/2026",'C.Pagar'!$K$2:$K$4509,"<=31/01/2026") -> 0 | K11: =J11/J$3 -> 0 | L11: =IFERROR(J11/G11-1,0) -> 0 | M11: =SUMIFS('C.Pagar'!$G$2:$G$4509,'C.Pagar'!$D$2:$D$4509,TRIM($A11),'C.Pagar'!$K$2:$K$4509,">=01/02/2026",'C.Pagar'!$K$2:$K$4509,"<=28/02/2026") -> 0 | N11: =M11/M$3 -> 0 | O11: =IFERROR(M11/J11-1,0) -> 0 | P11: =SUMIFS('C.Pagar'!$G$2:$G$4509,'C.Pagar'!$D$2:$D$4509,TRIM($A11),'C.Pagar'!$K$2:$K$4509,">=01/03/2026",'C.Pagar'!$K$2:$K$4509,"<=31/03/2026") -> 153.62 | Q11: =P11/P$3 -> 0.00014826518 | R11: =IFERROR(P11/M11-1,0) -> 0 | S11: =SUMIFS('C.Pagar'!$G$2:$G$4509,'C.Pagar'!$D$2:$D$4509,TRIM($A11),'C.Pagar'!$K$2:$K$4509,">=01/04/2026",'C.Pagar'!$K$2:$K$4509,"<=30/04/2026") -> 470.46 | T11: =S11/S$3 -> 0.00053237506 | U11: =IFERROR(S11/P11-1,0) -> 2.0624919
A12: FUNDO SOCIAL SC | B12: =SUMIFS('C.Pagar'!G$2:G$4509,'C.Pagar'!D$2:D$4509,TRIM(A12),'C.Pagar'!K$2:K$4509,">=01/10/2025",'C.Pagar'!K$2:K$4509,"<=31/10/2025") -> 0 | C12: =B12/B$3 -> 0 | D12: =SUMIFS('C.Pagar'!G$2:G$4509,'C.Pagar'!D$2:D$4509,TRIM(A12),'C.Pagar'!K$2:K$4509,">=01/11/2025",'C.Pagar'!K$2:K$4509,"<=30/11/2025") -> 0 | E12: =D12/D$3 -> 0 | F12: =IFERROR(D12/B12-1,0) -> 0 | G12: =SUMIFS('C.Pagar'!G$2:G$4509,'C.Pagar'!D$2:D$4509,TRIM(A12),'C.Pagar'!K$2:K$4509,">=01/12/2025",'C.Pagar'!K$2:K$4509,"<=31/12/2025") -> 0 | H12: =G12/G$3 -> 0 | I12: =IFERROR(G12/D12-1,0) -> 0 | J12: =SUMIFS('C.Pagar'!$G$2:$G$4509,'C.Pagar'!$D$2:$D$4509,TRIM($A12),'C.Pagar'!$K$2:$K$4509,">=01/01/2026",'C.Pagar'!$K$2:$K$4509,"<=31/01/2026") -> 0 | K12: =J12/J$3 -> 0 | L12: =IFERROR(J12/G12-1,0) -> 0 | M12: =SUMIFS('C.Pagar'!$G$2:$G$4509,'C.Pagar'!$D$2:$D$4509,TRIM($A12),'C.Pagar'!$K$2:$K$4509,">=01/02/2026",'C.Pagar'!$K$2:$K$4509,"<=28/02/2026") -> 0 | N12: =M12/M$3 -> 0 | O12: =IFERROR(M12/J12-1,0) -> 0 | P12: =SUMIFS('C.Pagar'!$G$2:$G$4509,'C.Pagar'!$D$2:$D$4509,TRIM($A12),'C.Pagar'!$K$2:$K$4509,">=01/03/2026",'C.Pagar'!$K$2:$K$4509,"<=31/03/2026") -> 192.03 | Q12: =P12/P$3 -> 0.0001853363 | R12: =IFERROR(P12/M12-1,0) -> 0 | S12: =SUMIFS('C.Pagar'!$G$2:$G$4509,'C.Pagar'!$D$2:$D$4509,TRIM($A12),'C.Pagar'!$K$2:$K$4509,">=01/04/2026",'C.Pagar'!$K$2:$K$4509,"<=30/04/2026") -> 588.07 | T12: =S12/S$3 -> 0.00066546317 | U12: =IFERROR(S12/P12-1,0) -> 2.0623861
A13: SIMPLES NACIONAL | B13: =SUMIFS('C.Pagar'!G$2:G$4509,'C.Pagar'!D$2:D$4509,TRIM(A13),'C.Pagar'!K$2:K$4509,">=01/10/2025",'C.Pagar'!K$2:K$4509,"<=31/10/2025") -> 15843.2 | C13: =B13/B$3 -> 0.014106479 | D13: =SUMIFS('C.Pagar'!G$2:G$4509,'C.Pagar'!D$2:D$4509,TRIM(A13),'C.Pagar'!K$2:K$4509,">=01/11/2025",'C.Pagar'!K$2:K$4509,"<=30/11/2025") -> 35650.83 | E13: =D13/D$3 -> 0.0360477 | F13: =IFERROR(D13/B13-1,0) -> 1.2502291 | G13: =SUMIFS('C.Pagar'!G$2:G$4509,'C.Pagar'!D$2:D$4509,TRIM(A13),'C.Pagar'!K$2:K$4509,">=01/12/2025",'C.Pagar'!K$2:K$4509,"<=31/12/2025") -> 21104.11 | H13: =G13/G$3 -> 0.019334904 | I13: =IFERROR(G13/D13-1,0) -> -0.40803314 | J13: =SUMIFS('C.Pagar'!$G$2:$G$4509,'C.Pagar'!$D$2:$D$4509,TRIM($A13),'C.Pagar'!$K$2:$K$4509,">=01/01/2026",'C.Pagar'!$K$2:$K$4509,"<=31/01/2026") -> 19799.24 | K13: =J13/J$3 -> 0.020995516 | L13: =IFERROR(J13/G13-1,0) -> -0.061830136 | M13: =SUMIFS('C.Pagar'!$G$2:$G$4509,'C.Pagar'!$D$2:$D$4509,TRIM($A13),'C.Pagar'!$K$2:$K$4509,">=01/02/2026",'C.Pagar'!$K$2:$K$4509,"<=28/02/2026") -> 15811.61 | N13: =M13/M$3 -> 0.022857587 | O13: =IFERROR(M13/J13-1,0) -> -0.20140319 | P13: =SUMIFS('C.Pagar'!$G$2:$G$4509,'C.Pagar'!$D$2:$D$4509,TRIM($A13),'C.Pagar'!$K$2:$K$4509,">=01/03/2026",'C.Pagar'!$K$2:$K$4509,"<=31/03/2026") -> 0 | Q13: =P13/P$3 -> 0 | R13: =IFERROR(P13/M13-1,0) -> -1 | S13: =SUMIFS('C.Pagar'!$G$2:$G$4509,'C.Pagar'!$D$2:$D$4509,TRIM($A13),'C.Pagar'!$K$2:$K$4509,">=01/04/2026",'C.Pagar'!$K$2:$K$4509,"<=30/04/2026") -> 0 | T13: =S13/S$3 -> 0 | U13: =IFERROR(S13/P13-1,0) -> 0
A14: OUTROS IMPOSTOS | B14: =SUMIFS('C.Pagar'!G$2:G$4509,'C.Pagar'!D$2:D$4509,TRIM(A14),'C.Pagar'!K$2:K$4509,">=01/10/2025",'C.Pagar'!K$2:K$4509,"<=31/10/2025") -> 0 | C14: =B14/B$3 -> 0 | D14: =SUMIFS('C.Pagar'!G$2:G$4509,'C.Pagar'!D$2:D$4509,TRIM(A14),'C.Pagar'!K$2:K$4509,">=01/11/2025",'C.Pagar'!K$2:K$4509,"<=30/11/2025") -> 0 | E14: =D14/D$3 -> 0 | F14: =IFERROR(D14/B14-1,0) -> 0 | G14: =SUMIFS('C.Pagar'!G$2:G$4509,'C.Pagar'!D$2:D$4509,TRIM(A14),'C.Pagar'!K$2:K$4509,">=01/12/2025",'C.Pagar'!K$2:K$4509,"<=31/12/2025") -> 0 | H14: =G14/G$3 -> 0 | I14: =IFERROR(G14/D14-1,0) -> 0 | J14: =SUMIFS('C.Pagar'!$G$2:$G$4509,'C.Pagar'!$D$2:$D$4509,TRIM($A14),'C.Pagar'!$K$2:$K$4509,">=01/01/2026",'C.Pagar'!$K$2:$K$4509,"<=31/01/2026") -> 0 | K14: =J14/J$3 -> 0 | L14: =IFERROR(J14/G14-1,0) -> 0 | M14: =SUMIFS('C.Pagar'!$G$2:$G$4509,'C.Pagar'!$D$2:$D$4509,TRIM($A14),'C.Pagar'!$K$2:$K$4509,">=01/02/2026",'C.Pagar'!$K$2:$K$4509,"<=28/02/2026") -> 0 | N14: =M14/M$3 -> 0 | O14: =IFERROR(M14/J14-1,0) -> 0 | P14: =SUMIFS('C.Pagar'!$G$2:$G$4509,'C.Pagar'!$D$2:$D$4509,TRIM($A14),'C.Pagar'!$K$2:$K$4509,">=01/03/2026",'C.Pagar'!$K$2:$K$4509,"<=31/03/2026") -> 8612.73 | Q14: =P14/P$3 -> 0.008312511 | R14: =IFERROR(P14/M14-1,0) -> 0 | S14: =SUMIFS('C.Pagar'!$G$2:$G$4509,'C.Pagar'!$D$2:$D$4509,TRIM($A14),'C.Pagar'!$K$2:$K$4509,">=01/04/2026",'C.Pagar'!$K$2:$K$4509,"<=30/04/2026") -> 0 | T14: =S14/S$3 -> 0 | U14: =IFERROR(S14/P14-1,0) -> -1
A15: (-) DEVOLUÇÕES | B15: =SUM(B16:B16) -> 0 | C15: =B15/B$3 -> 0 | D15: =SUM(D16:D16) -> 0 | E15: =D15/D$3 -> 0 | F15: =IFERROR(D15/B15-1,0) -> 0 | G15: =SUM(G16:G16) -> 0 | H15: =G15/G$3 -> 0 | I15: =IFERROR(G15/D15-1,0) -> 0 | J15: =SUM(J16:J16) -> 0 | K15: =J15/J$3 -> 0 | L15: =IFERROR(J15/G15-1,0) -> 0 | M15: =SUM(M16:M16) -> 0 | N15: =M15/M$3 -> 0 | O15: =IFERROR(M15/J15-1,0) -> 0 | P15: =SUM(P16:P16) -> 0 | Q15: =P15/P$3 -> 0 | R15: =IFERROR(P15/M15-1,0) -> 0 | S15: =SUM(S16:S16) -> 0 | T15: =S15/S$3 -> 0 | U15: =IFERROR(S15/P15-1,0) -> 0
A16: (-) EM ABERTO | B16: =SUMIFS('C.Pagar'!G$2:G$4509,'C.Pagar'!D$2:D$4509,TRIM(A16),'C.Pagar'!K$2:K$4509,">=01/10/2025",'C.Pagar'!K$2:K$4509,"<=31/10/2025") -> 0 | C16: =B16/B$3 -> 0 | D16: =SUMIFS('C.Pagar'!G$2:G$4509,'C.Pagar'!D$2:D$4509,TRIM(A16),'C.Pagar'!K$2:K$4509,">=01/11/2025",'C.Pagar'!K$2:K$4509,"<=30/11/2025") -> 0 | E16: =D16/D$3 -> 0 | F16: =IFERROR(D16/B16-1,0) -> 0 | G16: =SUMIFS('C.Pagar'!G$2:G$4509,'C.Pagar'!D$2:D$4509,TRIM(A16),'C.Pagar'!K$2:K$4509,">=01/12/2025",'C.Pagar'!K$2:K$4509,"<=31/12/2025") -> 0 | H16: =G16/G$3 -> 0 | I16: =IFERROR(G16/D16-1,0) -> 0 | J16: =SUMIFS('C.Pagar'!G$2:G$4509,'C.Pagar'!D$2:D$4509,TRIM(A16),'C.Pagar'!K$2:K$4509,">=01/01/2026",'C.Pagar'!K$2:K$4509,"<=31/01/2026") -> 0 | K16: =J16/J$3 -> 0 | L16: =IFERROR(J16/G16-1,0) -> 0 | M16: =SUMIFS('C.Pagar'!$G$2:$G$4509,'C.Pagar'!$D$2:$D$4509,TRIM($A16),'C.Pagar'!$K$2:$K$4509,">=01/02/2026",'C.Pagar'!$K$2:$K$4509,"<=28/02/2026") -> 0 | N16: =M16/M$3 -> 0 | O16: =IFERROR(M16/J16-1,0) -> 0 | P16: =SUMIFS('C.Pagar'!$G$2:$G$4509,'C.Pagar'!$D$2:$D$4509,TRIM($A16),'C.Pagar'!$K$2:$K$4509,">=01/03/2026",'C.Pagar'!$K$2:$K$4509,"<=31/03/2026") -> 0 | Q16: =P16/P$3 -> 0 | R16: =IFERROR(P16/M16-1,0) -> 0 | S16: =SUMIFS('C.Pagar'!$G$2:$G$4509,'C.Pagar'!$D$2:$D$4509,TRIM($A16),'C.Pagar'!$K$2:$K$4509,">=01/04/2026",'C.Pagar'!$K$2:$K$4509,"<=30/04/2026") -> 0 | T16: =S16/S$3 -> 0 | U16: =IFERROR(S16/P16-1,0) -> 0
A17: (-) DESPESAS COM TRANSPORTE | B17: =SUM(B18:B20) -> 9199.86 | C17: =B17/B$3 -> 0.0081913774 | D17: =SUM(D18:D20) -> 1174.88 | E17: =D17/D$3 -> 0.0011879589 | F17: =IFERROR(D17/B17-1,0) -> -0.87229371 | G17: =SUM(G18:G20) -> 6687.27 | H17: =G17/G$3 -> 0.0061266609 | I17: =IFERROR(G17/D17-1,0) -> 4.6918749 | J17: =SUM(J18:J20) -> 20966.06 | K17: =J17/J$3 -> 0.022232836 | L17: =IFERROR(J17/G17-1,0) -> 2.1352196 | M17: =SUM(M18:M20) -> 31195.07 | N17: =M17/M$3 -> 0.045096232 | O17: =IFERROR(M17/J17-1,0) -> 0.48788423 | P17: =SUM(P18:P20) -> 23710.91 | Q17: =P17/P$3 -> 0.022884405 | R17: =IFERROR(P17/M17-1,0) -> -0.23991483 | S17: =SUM(S18:S20) -> 16940.68 | T17: =S17/S$3 -> 0.019170164 | U17: =IFERROR(S17/P17-1,0) -> -0.28553227
A18: TRANSPORTE - PAGAMENTO ENTREGA | B18: =SUMIFS('C.Pagar'!G$2:G$4509,'C.Pagar'!D$2:D$4509,TRIM(A18),'C.Pagar'!K$2:K$4509,">=01/10/2025",'C.Pagar'!K$2:K$4509,"<=31/10/2025") -> 6905.45 | C18: =B18/B$3 -> 0.0061484791 | D18: =SUMIFS('C.Pagar'!G$2:G$4509,'C.Pagar'!D$2:D$4509,TRIM(A18),'C.Pagar'!K$2:K$4509,">=01/11/2025",'C.Pagar'!K$2:K$4509,"<=30/11/2025") -> 0 | E18: =D18/D$3 -> 0 | F18: =IFERROR(D18/B18-1,0) -> -1 | G18: =SUMIFS('C.Pagar'!G$2:G$4509,'C.Pagar'!D$2:D$4509,TRIM(A18),'C.Pagar'!K$2:K$4509,">=01/12/2025",'C.Pagar'!K$2:K$4509,"<=31/12/2025") -> 0 | H18: =G18/G$3 -> 0 | I18: =IFERROR(G18/D18-1,0) -> 0 | J18: =SUMIFS('C.Pagar'!G$2:G$4509,'C.Pagar'!D$2:D$4509,TRIM(A18),'C.Pagar'!K$2:K$4509,">=01/01/2026",'C.Pagar'!K$2:K$4509,"<=31/01/2026") -> 0 | K18: =J18/J$3 -> 0 | L18: =IFERROR(J18/G18-1,0) -> 0 | M18: =SUMIFS('C.Pagar'!$G$2:$G$4509,'C.Pagar'!$D$2:$D$4509,TRIM($A18),'C.Pagar'!$K$2:$K$4509,">=01/02/2026",'C.Pagar'!$K$2:$K$4509,"<=28/02/2026") -> 0 | N18: =M18/M$3 -> 0 | O18: =IFERROR(M18/J18-1,0) -> 0 | P18: =SUMIFS('C.Pagar'!$G$2:$G$4509,'C.Pagar'!$D$2:$D$4509,TRIM($A18),'C.Pagar'!$K$2:$K$4509,">=01/03/2026",'C.Pagar'!$K$2:$K$4509,"<=31/03/2026") -> 0 | Q18: =P18/P$3 -> 0 | R18: =IFERROR(P18/M18-1,0) -> 0 | S18: =SUMIFS('C.Pagar'!$G$2:$G$4509,'C.Pagar'!$D$2:$D$4509,TRIM($A18),'C.Pagar'!$K$2:$K$4509,">=01/04/2026",'C.Pagar'!$K$2:$K$4509,"<=30/04/2026") -> 0 | T18: =S18/S$3 -> 0 | U18: =IFERROR(S18/P18-1,0) -> 0
A19: TRANSPORTE - PAGAMENTO FRETE | B19: =SUMIFS('C.Pagar'!G$2:G$4509,'C.Pagar'!D$2:D$4509,TRIM(A19),'C.Pagar'!K$2:K$4509,">=01/10/2025",'C.Pagar'!K$2:K$4509,"<=31/10/2025") -> 310 | C19: =B19/B$3 -> 0.000276018 | D19: =SUMIFS('C.Pagar'!G$2:G$4509,'C.Pagar'!D$2:D$4509,TRIM(A19),'C.Pagar'!K$2:K$4509,">=01/11/2025",'C.Pagar'!K$2:K$4509,"<=30/11/2025") -> 0 | E19: =D19/D$3 -> 0 | F19: =IFERROR(D19/B19-1,0) -> -1 | G19: =SUMIFS('C.Pagar'!G$2:G$4509,'C.Pagar'!D$2:D$4509,TRIM(A19),'C.Pagar'!K$2:K$4509,">=01/12/2025",'C.Pagar'!K$2:K$4509,"<=31/12/2025") -> 0 | H19: =G19/G$3 -> 0 | I19: =IFERROR(G19/D19-1,0) -> 0 | J19: =SUMIFS('C.Pagar'!G$2:G$4509,'C.Pagar'!D$2:D$4509,TRIM(A19),'C.Pagar'!K$2:K$4509,">=01/01/2026",'C.Pagar'!K$2:K$4509,"<=31/01/2026") -> 0 | K19: =J19/J$3 -> 0 | L19: =IFERROR(J19/G19-1,0) -> 0 | M19: =SUMIFS('C.Pagar'!$G$2:$G$4509,'C.Pagar'!$D$2:$D$4509,TRIM($A19),'C.Pagar'!$K$2:$K$4509,">=01/02/2026",'C.Pagar'!$K$2:$K$4509,"<=28/02/2026") -> 0 | N19: =M19/M$3 -> 0 | O19: =IFERROR(M19/J19-1,0) -> 0 | P19: =SUMIFS('C.Pagar'!$G$2:$G$4509,'C.Pagar'!$D$2:$D$4509,TRIM($A19),'C.Pagar'!$K$2:$K$4509,">=01/03/2026",'C.Pagar'!$K$2:$K$4509,"<=31/03/2026") -> 0 | Q19: =P19/P$3 -> 0 | R19: =IFERROR(P19/M19-1,0) -> 0 | S19: =SUMIFS('C.Pagar'!$G$2:$G$4509,'C.Pagar'!$D$2:$D$4509,TRIM($A19),'C.Pagar'!$K$2:$K$4509,">=01/04/2026",'C.Pagar'!$K$2:$K$4509,"<=30/04/2026") -> 0 | T19: =S19/S$3 -> 0 | U19: =IFERROR(S19/P19-1,0) -> 0
A20: FRETE DE SAÍDA | B20: =SUMIFS('C.Pagar'!G$2:G$4509,'C.Pagar'!D$2:D$4509,TRIM(A20),'C.Pagar'!K$2:K$4509,">=01/10/2025",'C.Pagar'!K$2:K$4509,"<=31/10/2025") -> 1984.41 | C20: =B20/B$3 -> 0.0017668803 | D20: =SUMIFS('C.Pagar'!G$2:G$4509,'C.Pagar'!D$2:D$4509,TRIM(A20),'C.Pagar'!K$2:K$4509,">=01/11/2025",'C.Pagar'!K$2:K$4509,"<=30/11/2025") -> 1174.88 | E20: =D20/D$3 -> 0.0011879589 | F20: =IFERROR(D20/B20-1,0) -> -0.40794493 | G20: =SUMIFS('C.Pagar'!G$2:G$4509,'C.Pagar'!D$2:D$4509,TRIM(A20),'C.Pagar'!K$2:K$4509,">=01/12/2025",'C.Pagar'!K$2:K$4509,"<=31/12/2025") -> 6687.27 | H20: =G20/G$3 -> 0.0061266609 | I20: =IFERROR(G20/D20-1,0) -> 4.6918749 | J20: =SUMIFS('C.Pagar'!G$2:G$4509,'C.Pagar'!D$2:D$4509,TRIM(A20),'C.Pagar'!K$2:K$4509,">=01/01/2026",'C.Pagar'!K$2:K$4509,"<=31/01/2026") -> 20966.06 | K20: =J20/J$3 -> 0.022232836 | L20: =IFERROR(J20/G20-1,0) -> 2.1352196 | M20: =SUMIFS('C.Pagar'!$G$2:$G$4509,'C.Pagar'!$D$2:$D$4509,TRIM($A20),'C.Pagar'!$K$2:$K$4509,">=01/02/2026",'C.Pagar'!$K$2:$K$4509,"<=28/02/2026") -> 31195.07 | N20: =M20/M$3 -> 0.045096232 | O20: =IFERROR(M20/J20-1,0) -> 0.48788423 | P20: =SUMIFS('C.Pagar'!$G$2:$G$4509,'C.Pagar'!$D$2:$D$4509,TRIM($A20),'C.Pagar'!$K$2:$K$4509,">=01/03/2026",'C.Pagar'!$K$2:$K$4509,"<=31/03/2026") -> 23710.91 | Q20: =P20/P$3 -> 0.022884405 | R20: =IFERROR(P20/M20-1,0) -> -0.23991483 | S20: =SUMIFS('C.Pagar'!$G$2:$G$4509,'C.Pagar'!$D$2:$D$4509,TRIM($A20),'C.Pagar'!$K$2:$K$4509,">=01/04/2026",'C.Pagar'!$K$2:$K$4509,"<=30/04/2026") -> 16940.68 | T20: =S20/S$3 -> 0.019170164 | U20: =IFERROR(S20/P20-1,0) -> -0.28553227
A21: (-) RECEITA OPERACIONAL LÍQUIDA | B21: =B3-B5-B15-B17 -> 1098072.1 | C21: =B21/B$3 -> 0.97770214 | D21: =D3-D5-D15-D17 -> 952164.72 | E21: =D21/D$3 -> 0.96276434 | F21: =IFERROR(D21/B21-1,0) -> -0.13287594 | G21: =G3-G5-G15-G17 -> 1063711.8 | H21: =G21/G$3 -> 0.97453843 | I21: =IFERROR(G21/D21-1,0) -> 0.11715106 | J21: =J3-J5-J15-J17 -> 902257.01 | K21: =J21/J$3 -> 0.95677165 | L21: =IFERROR(J21/G21-1,0) -> -0.15178436 | M21: =M3-M5-M15-M17 -> 644737.81 | N21: =M21/M$3 -> 0.93204618 | O21: =IFERROR(M21/J21-1,0) -> -0.28541668 | P21: =P3-P5-P15-P17 -> 982703.44 | Q21: =P21/P$3 -> 0.94844877 | R21: =IFERROR(P21/M21-1,0) -> 0.5241908 | S21: =S3-S5-S15-S17 -> 849900.06 | T21: =S21/S$3 -> 0.96175147 | U21: =IFERROR(S21/P21-1,0) -> -0.13514085
A22: (-) PAGAMENTOS DOS CUSTOS VARIÁVEIS OPERACIONAIS | B22: =B23+B28 -> 974240.78 | C22: =B22/B$3 -> 0.86744515 | D22: =D23+D28 -> 962916.64 | E22: =D22/D$3 -> 0.97363595 | F22: =IFERROR(D22/B22-1,0) -> -0.011623554 | G22: =G23+G28 -> 952048.32 | H22: =G22/G$3 -> 0.87223593 | I22: =IFERROR(G22/D22-1,0) -> -0.011286875 | J22: =J23+J28 -> 958184.09 | K22: =J22/J$3 -> 1.0160779 | L22: =IFERROR(J22/G22-1,0) -> 0.0064448094 | M22: =M23+M28 -> 726904.22 | N22: =M22/M$3 -> 1.0508276 | O22: =IFERROR(M22/J22-1,0) -> -0.24137311 | P22: =P23+P28 -> 729867.2 | Q22: =P22/P$3 -> 0.70442579 | R22: =IFERROR(P22/M22-1,0) -> 0.0040761629 | S22: =S23+S28 -> 550438.57 | T22: =S22/S$3 -> 0.62287924 | U22: =IFERROR(S22/P22-1,0) -> -0.24583737
A23: (-) PAGAMENTOS DAS MERCADORIAS VENDIDAS | B23: =SUM(B24:B27) -> 965385.46 | C23: =B23/B$3 -> 0.85956054 | D23: =SUM(D24:D27) -> 956175.13 | E23: =D23/D$3 -> 0.9668194 | F23: =IFERROR(D23/B23-1,0) -> -0.0095405725 | G23: =SUM(G24:G27) -> 923865.02 | H23: =G23/G$3 -> 0.8464153 | I23: =IFERROR(G23/D23-1,0) -> -0.033790996 | J23: =SUM(J24:J27) -> 942086.28 | K23: =J23/J$3 -> 0.99900741 | L23: =IFERROR(J23/G23-1,0) -> 0.01972286 | M23: =SUM(M24:M27) -> 706911.04 | N23: =M23/M$3 -> 1.0219251 | O23: =IFERROR(M23/J23-1,0) -> -0.24963238 | P23: =SUM(P24:P27) -> 709376.58 | Q23: =P23/P$3 -> 0.68464943 | R23: =IFERROR(P23/M23-1,0) -> 0.0034877656 | S23: =SUM(S24:S27) -> 543436.78 | T23: =S23/S$3 -> 0.61495598 | U23: =IFERROR(S23/P23-1,0) -> -0.23392343
A24: PEÇAS | B24: =SUMIFS('C.Pagar'!G$2:G$4509,'C.Pagar'!D$2:D$4509,TRIM(A24),'C.Pagar'!K$2:K$4509,">=01/10/2025",'C.Pagar'!K$2:K$4509,"<=31/10/2025") -> 927006.13 | C24: =B24/B$3 -> 0.82538833 | D24: =SUMIFS('C.Pagar'!G$2:G$4509,'C.Pagar'!D$2:D$4509,TRIM(A24),'C.Pagar'!K$2:K$4509,">=01/11/2025",'C.Pagar'!K$2:K$4509,"<=30/11/2025") -> 905795.48 | E24: =D24/D$3 -> 0.91587891 | F24: =IFERROR(D24/B24-1,0) -> -0.022880809 | G24: =SUMIFS('C.Pagar'!G$2:G$4509,'C.Pagar'!D$2:D$4509,TRIM(A24),'C.Pagar'!K$2:K$4509,">=01/12/2025",'C.Pagar'!K$2:K$4509,"<=31/12/2025") -> 871295.98 | H24: =G24/G$3 -> 0.79825325 | I24: =IFERROR(G24/D24-1,0) -> -0.038087516 | J24: =SUMIFS('C.Pagar'!G$2:G$4509,'C.Pagar'!D$2:D$4509,TRIM(A24),'C.Pagar'!K$2:K$4509,">=01/01/2026",'C.Pagar'!K$2:K$4509,"<=31/01/2026") -> 890437.48 | K24: =J24/J$3 -> 0.94423798 | L24: =IFERROR(J24/G24-1,0) -> 0.021968998 | M24: =SUMIFS('C.Pagar'!$G$2:$G$4509,'C.Pagar'!$D$2:$D$4509,TRIM($A24),'C.Pagar'!$K$2:$K$4509,">=01/02/2026",'C.Pagar'!$K$2:$K$4509,"<=28/02/2026")-9945 -> 653379.96 | N24: =M24/M$3 -> 0.94453945 | O24: =IFERROR(M24/J24-1,0) -> -0.2662259 | P24: =SUMIFS('C.Pagar'!$G$2:$G$4509,'C.Pagar'!$D$2:$D$4509,TRIM($A24),'C.Pagar'!$K$2:$K$4509,">=01/03/2026",'C.Pagar'!$K$2:$K$4509,"<=31/03/2026") -> 664545.35 | Q24: =P24/P$3 -> 0.6413809 | R24: =IFERROR(P24/M24-1,0) -> 0.017088663 | S24: =SUMIFS('C.Pagar'!$G$2:$G$4509,'C.Pagar'!$D$2:$D$4509,TRIM($A24),'C.Pagar'!$K$2:$K$4509,">=01/04/2026",'C.Pagar'!$K$2:$K$4509,"<=30/04/2026") -> 503459.83 | T24: =S24/S$3 -> 0.56971784 | U24: =IFERROR(S24/P24-1,0) -> -0.24239959
A25: EMBALAGENS | B25: =SUMIFS('C.Pagar'!G$2:G$4509,'C.Pagar'!D$2:D$4509,TRIM(A25),'C.Pagar'!K$2:K$4509,">=01/10/2025",'C.Pagar'!K$2:K$4509,"<=31/10/2025") -> 33789.33 | C25: =B25/B$3 -> 0.030085366 | D25: =SUMIFS('C.Pagar'!G$2:G$4509,'C.Pagar'!D$2:D$4509,TRIM(A25),'C.Pagar'!K$2:K$4509,">=01/11/2025",'C.Pagar'!K$2:K$4509,"<=30/11/2025") -> 34294.03 | E25: =D25/D$3 -> 0.034675796 | F25: =IFERROR(D25/B25-1,0) -> 0.014936668 | G25: =SUMIFS('C.Pagar'!G$2:G$4509,'C.Pagar'!D$2:D$4509,TRIM(A25),'C.Pagar'!K$2:K$4509,">=01/12/2025",'C.Pagar'!K$2:K$4509,"<=31/12/2025") -> 35859.96 | H25: =G25/G$3 -> 0.032853738 | I25: =IFERROR(G25/D25-1,0) -> 0.045661883 | J25: =SUMIFS('C.Pagar'!G$2:G$4509,'C.Pagar'!D$2:D$4509,TRIM(A25),'C.Pagar'!K$2:K$4509,">=01/01/2026",'C.Pagar'!K$2:K$4509,"<=31/01/2026") -> 39246.9 | K25: =J25/J$3 -> 0.041618209 | L25: =IFERROR(J25/G25-1,0) -> 0.094449074 | M25: =SUMIFS('C.Pagar'!$G$2:$G$4509,'C.Pagar'!$D$2:$D$4509,TRIM($A25),'C.Pagar'!$K$2:$K$4509,">=01/02/2026",'C.Pagar'!$K$2:$K$4509,"<=28/02/2026") -> 39493.58 | N25: =M25/M$3 -> 0.057092728 | O25: =IFERROR(M25/J25-1,0) -> 0.0062853372 | P25: =SUMIFS('C.Pagar'!$G$2:$G$4509,'C.Pagar'!$D$2:$D$4509,TRIM($A25),'C.Pagar'!$K$2:$K$4509,">=01/03/2026",'C.Pagar'!$K$2:$K$4509,"<=31/03/2026") -> 36318.73 | Q25: =P25/P$3 -> 0.035052747 | R25: =IFERROR(P25/M25-1,0) -> -0.080389015 | S25: =SUMIFS('C.Pagar'!$G$2:$G$4509,'C.Pagar'!$D$2:$D$4509,TRIM($A25),'C.Pagar'!$K$2:$K$4509,">=01/04/2026",'C.Pagar'!$K$2:$K$4509,"<=30/04/2026") -> 21564.45 | T25: =S25/S$3 -> 0.024402447 | U25: =IFERROR(S25/P25-1,0) -> -0.40624438
A26: MONTAGEM DE RODAS | B26: =SUMIFS('C.Pagar'!G$2:G$4509,'C.Pagar'!D$2:D$4509,TRIM(A26),'C.Pagar'!K$2:K$4509,">=01/10/2025",'C.Pagar'!K$2:K$4509,"<=31/10/2025") -> 4590 | C26: =B26/B$3 -> 0.0040868472 | D26: =SUMIFS('C.Pagar'!G$2:G$4509,'C.Pagar'!D$2:D$4509,TRIM(A26),'C.Pagar'!K$2:K$4509,">=01/11/2025",'C.Pagar'!K$2:K$4509,"<=30/11/2025") -> 13312.5 | E26: =D26/D$3 -> 0.013460696 | F26: =IFERROR(D26/B26-1,0) -> 1.9003268 | G26: =SUMIFS('C.Pagar'!G$2:G$4509,'C.Pagar'!D$2:D$4509,TRIM(A26),'C.Pagar'!K$2:K$4509,">=01/12/2025",'C.Pagar'!K$2:K$4509,"<=31/12/2025") -> 15240 | H26: =G26/G$3 -> 0.013962396 | I26: =IFERROR(G26/D26-1,0) -> 0.14478873 | J26: =SUMIFS('C.Pagar'!G$2:G$4509,'C.Pagar'!D$2:D$4509,TRIM(A26),'C.Pagar'!K$2:K$4509,">=01/01/2026",'C.Pagar'!K$2:K$4509,"<=31/01/2026") -> 12222.5 | K26: =J26/J$3 -> 0.012960987 | L26: =IFERROR(J26/G26-1,0) -> -0.19799869 | M26: =SUMIFS('C.Pagar'!$G$2:$G$4509,'C.Pagar'!$D$2:$D$4509,TRIM($A26),'C.Pagar'!$K$2:$K$4509,">=01/02/2026",'C.Pagar'!$K$2:$K$4509,"<=28/02/2026") -> 14037.5 | N26: =M26/M$3 -> 0.020292897 | O26: =IFERROR(M26/J26-1,0) -> 0.14849663 | P26: =SUMIFS('C.Pagar'!$G$2:$G$4509,'C.Pagar'!$D$2:$D$4509,TRIM($A26),'C.Pagar'!$K$2:$K$4509,">=01/03/2026",'C.Pagar'!$K$2:$K$4509,"<=31/03/2026") -> 8512.5 | Q26: =P26/P$3 -> 0.0082157748 | R26: =IFERROR(P26/M26-1,0) -> -0.3935886 | S26: =SUMIFS('C.Pagar'!$G$2:$G$4509,'C.Pagar'!$D$2:$D$4509,TRIM($A26),'C.Pagar'!$K$2:$K$4509,">=01/04/2026",'C.Pagar'!$K$2:$K$4509,"<=30/04/2026") -> 18412.5 | T26: =S26/S$3 -> 0.020835684 | U26: =IFERROR(S26/P26-1,0) -> 1.1629956
A27: FRETE ENTRADA | B27: =SUMIFS('C.Pagar'!G$2:G$4509,'C.Pagar'!D$2:D$4509,TRIM(A27),'C.Pagar'!K$2:K$4509,">=01/10/2025",'C.Pagar'!K$2:K$4509,"<=31/10/2025") -> 0 | C27: =B27/B$3 -> 0 | D27: =SUMIFS('C.Pagar'!G$2:G$4509,'C.Pagar'!D$2:D$4509,TRIM(A27),'C.Pagar'!K$2:K$4509,">=01/11/2025",'C.Pagar'!K$2:K$4509,"<=30/11/2025") -> 2773.12 | E27: =D27/D$3 -> 0.0028039907 | F27: =IFERROR(D27/B27-1,0) -> 0 | G27: =SUMIFS('C.Pagar'!G$2:G$4509,'C.Pagar'!D$2:D$4509,TRIM(A27),'C.Pagar'!K$2:K$4509,">=01/12/2025",'C.Pagar'!K$2:K$4509,"<=31/12/2025") -> 1469.08 | H27: =G27/G$3 -> 0.0013459237 | I27: =IFERROR(G27/D27-1,0) -> -0.4702429 | J27: =SUMIFS('C.Pagar'!G$2:G$4509,'C.Pagar'!D$2:D$4509,TRIM(A27),'C.Pagar'!K$2:K$4509,">=01/01/2026",'C.Pagar'!K$2:K$4509,"<=31/01/2026") -> 179.4 | K27: =J27/J$3 -> 0.0001902394 | L27: =IFERROR(J27/G27-1,0) -> -0.87788276 | M27: =SUMIFS('C.Pagar'!$G$2:$G$4509,'C.Pagar'!$D$2:$D$4509,TRIM($A27),'C.Pagar'!$K$2:$K$4509,">=01/02/2026",'C.Pagar'!$K$2:$K$4509,"<=28/02/2026") -> 0 | N27: =M27/M$3 -> 0 | O27: =IFERROR(M27/J27-1,0) -> -1 | P27: =SUMIFS('C.Pagar'!$G$2:$G$4509,'C.Pagar'!$D$2:$D$4509,TRIM($A27),'C.Pagar'!$K$2:$K$4509,">=01/03/2026",'C.Pagar'!$K$2:$K$4509,"<=31/03/2026") -> 0 | Q27: =P27/P$3 -> 0 | R27: =IFERROR(P27/M27-1,0) -> 0 | S27: =SUMIFS('C.Pagar'!$G$2:$G$4509,'C.Pagar'!$D$2:$D$4509,TRIM($A27),'C.Pagar'!$K$2:$K$4509,">=01/04/2026",'C.Pagar'!$K$2:$K$4509,"<=30/04/2026") -> 0 | T27: =S27/S$3 -> 0 | U27: =IFERROR(S27/P27-1,0) -> 0
A28: (-) DESPESAS DE VENDA | B28: =SUM(B29:B34) -> 8855.32 | C28: =B28/B$3 -> 0.0078846057 | D28: =SUM(D29:D34) -> 6741.51 | E28: =D28/D$3 -> 0.0068165574 | F28: =IFERROR(D28/B28-1,0) -> -0.23870509 | G28: =SUM(G29:G34) -> 28183.3 | H28: =G28/G$3 -> 0.02582063 | I28: =IFERROR(G28/D28-1,0) -> 3.1805619 | J28: =SUM(J29:J34) -> 16097.81 | K28: =J28/J$3 -> 0.017070444 | L28: =IFERROR(J28/G28-1,0) -> -0.42881742 | M28: =SUM(M29:M34) -> 19993.18 | N28: =M28/M$3 -> 0.02890255 | O28: =IFERROR(M28/J28-1,0) -> 0.24198136 | P28: =SUM(P29:P34) -> 20490.62 | Q28: =P28/P$3 -> 0.019776366 | R28: =IFERROR(P28/M28-1,0) -> 0.024880484 | S28: =SUM(S29:S34) -> 7001.79 | T28: =S28/S$3 -> 0.0079232631 | U28: =IFERROR(S28/P28-1,0) -> -0.65829292
A29: COMISSÕES E TAXAS DOS MARKETPLACES | B29: =SUMIFS('C.Pagar'!G$2:G$4509,'C.Pagar'!D$2:D$4509,TRIM(A29),'C.Pagar'!K$2:K$4509,">=01/10/2025",'C.Pagar'!K$2:K$4509,"<=31/10/2025") -> 4496.71 | C29: =B29/B$3 -> 0.0040037836 | D29: =SUMIFS('C.Pagar'!G$2:G$4509,'C.Pagar'!D$2:D$4509,TRIM(A29),'C.Pagar'!K$2:K$4509,">=01/11/2025",'C.Pagar'!K$2:K$4509,"<=30/11/2025") -> 2648.11 | E29: =D29/D$3 -> 0.0026775891 | F29: =IFERROR(D29/B29-1,0) -> -0.41110056 | G29: =SUMIFS('C.Pagar'!G$2:G$4509,'C.Pagar'!D$2:D$4509,TRIM(A29),'C.Pagar'!K$2:K$4509,">=01/12/2025",'C.Pagar'!K$2:K$4509,"<=31/12/2025") -> 35 | H29: =G29/G$3 -> 3.206587e-05 | I29: =IFERROR(G29/D29-1,0) -> -0.98678303 | J29: =SUMIFS('C.Pagar'!G$2:G$4509,'C.Pagar'!D$2:D$4509,TRIM(A29),'C.Pagar'!K$2:K$4509,">=01/01/2026",'C.Pagar'!K$2:K$4509,"<=31/01/2026") -> 7050.86 | K29: =J29/J$3 -> 0.0074768751 | L29: =IFERROR(J29/G29-1,0) -> 200.45314 | M29: =SUMIFS('C.Pagar'!$G$2:$G$4509,'C.Pagar'!$D$2:$D$4509,TRIM($A29),'C.Pagar'!$K$2:$K$4509,">=01/02/2026",'C.Pagar'!$K$2:$K$4509,"<=28/02/2026") -> 6139.24 | N29: =M29/M$3 -> 0.0088750111 | O29: =IFERROR(M29/J29-1,0) -> -0.12929203 | P29: =SUMIFS('C.Pagar'!$G$2:$G$4509,'C.Pagar'!$D$2:$D$4509,TRIM($A29),'C.Pagar'!$K$2:$K$4509,">=01/03/2026",'C.Pagar'!$K$2:$K$4509,"<=31/03/2026") -> 3535 | Q29: =P29/P$3 -> 0.0034117784 | R29: =IFERROR(P29/M29-1,0) -> -0.42419583 | S29: =SUMIFS('C.Pagar'!$G$2:$G$4509,'C.Pagar'!$D$2:$D$4509,TRIM($A29),'C.Pagar'!$K$2:$K$4509,">=01/04/2026",'C.Pagar'!$K$2:$K$4509,"<=30/04/2026") -> 2620.08 | T29: =S29/S$3 -> 0.0029648966 | U29: =IFERROR(S29/P29-1,0) -> -0.25881754
A30: ANYMARKET TAXAS | B30: =SUMIFS('C.Pagar'!G$2:G$4509,'C.Pagar'!D$2:D$4509,TRIM(A30),'C.Pagar'!K$2:K$4509,">=01/10/2025",'C.Pagar'!K$2:K$4509,"<=31/10/2025") -> 3949.61 | C30: =B30/B$3 -> 0.0035166564 | D30: =SUMIFS('C.Pagar'!G$2:G$4509,'C.Pagar'!D$2:D$4509,TRIM(A30),'C.Pagar'!K$2:K$4509,">=01/11/2025",'C.Pagar'!K$2:K$4509,"<=30/11/2025") -> 4053.4 | E30: =D30/D$3 -> 0.004098523 | F30: =IFERROR(D30/B30-1,0) -> 0.026278544 | G30: =SUMIFS('C.Pagar'!G$2:G$4509,'C.Pagar'!D$2:D$4509,TRIM(A30),'C.Pagar'!K$2:K$4509,">=01/12/2025",'C.Pagar'!K$2:K$4509,"<=31/12/2025") -> 4449.3 | H30: =G30/G$3 -> 0.004076305 | I30: =IFERROR(G30/D30-1,0) -> 0.097671091 | J30: =SUMIFS('C.Pagar'!G$2:G$4509,'C.Pagar'!D$2:D$4509,TRIM(A30),'C.Pagar'!K$2:K$4509,">=01/01/2026",'C.Pagar'!K$2:K$4509,"<=31/01/2026") -> 4422.55 | K30: =J30/J$3 -> 0.0046897618 | L30: =IFERROR(J30/G30-1,0) -> -0.0060121817 | M30: =SUMIFS('C.Pagar'!$G$2:$G$4509,'C.Pagar'!$D$2:$D$4509,TRIM($A30),'C.Pagar'!$K$2:$K$4509,">=01/02/2026",'C.Pagar'!$K$2:$K$4509,"<=28/02/2026") -> 4178.94 | N30: =M30/M$3 -> 0.0060411612 | O30: =IFERROR(M30/J30-1,0) -> -0.055083606 | P30: =SUMIFS('C.Pagar'!$G$2:$G$4509,'C.Pagar'!$D$2:$D$4509,TRIM($A30),'C.Pagar'!$K$2:$K$4509,">=01/03/2026",'C.Pagar'!$K$2:$K$4509,"<=31/03/2026") -> 3460.62 | Q30: =P30/P$3 -> 0.0033399911 | R30: =IFERROR(P30/M30-1,0) -> -0.17189048 | S30: =SUMIFS('C.Pagar'!$G$2:$G$4509,'C.Pagar'!$D$2:$D$4509,TRIM($A30),'C.Pagar'!$K$2:$K$4509,">=01/04/2026",'C.Pagar'!$K$2:$K$4509,"<=30/04/2026") -> 4088.71 | T30: =S30/S$3 -> 0.0046268062 | U30: =IFERROR(S30/P30-1,0) -> 0.18149638
A31: ADS MAGALU | B31: =SUMIFS('C.Pagar'!G$2:G$4509,'C.Pagar'!D$2:D$4509,TRIM(A31),'C.Pagar'!K$2:K$4509,">=01/10/2025",'C.Pagar'!K$2:K$4509,"<=31/10/2025") -> 0 | C31: =B31/B$3 -> 0 | D31: =SUMIFS('C.Pagar'!G$2:G$4509,'C.Pagar'!D$2:D$4509,TRIM(A31),'C.Pagar'!K$2:K$4509,">=01/11/2025",'C.Pagar'!K$2:K$4509,"<=30/11/2025") -> 0 | E31: =D31/D$3 -> 0 | F31: =IFERROR(D31/B31-1,0) -> 0 | G31: =SUMIFS('C.Pagar'!G$2:G$4509,'C.Pagar'!D$2:D$4509,TRIM(A31),'C.Pagar'!K$2:K$4509,">=01/12/2025",'C.Pagar'!K$2:K$4509,"<=31/12/2025") -> 4000 | H31: =G31/G$3 -> 0.0036646709 | I31: =IFERROR(G31/D31-1,0) -> 0 | J31: =SUMIFS('C.Pagar'!G$2:G$4509,'C.Pagar'!D$2:D$4509,TRIM(A31),'C.Pagar'!K$2:K$4509,">=01/01/2026",'C.Pagar'!K$2:K$4509,"<=31/01/2026") -> 0 | K31: =J31/J$3 -> 0 | L31: =IFERROR(J31/G31-1,0) -> -1 | M31: =SUMIFS('C.Pagar'!$G$2:$G$4509,'C.Pagar'!$D$2:$D$4509,TRIM($A31),'C.Pagar'!$K$2:$K$4509,">=01/02/2026",'C.Pagar'!$K$2:$K$4509,"<=28/02/2026") -> 0 | N31: =M31/M$3 -> 0 | O31: =IFERROR(M31/J31-1,0) -> 0 | P31: =SUMIFS('C.Pagar'!$G$2:$G$4509,'C.Pagar'!$D$2:$D$4509,TRIM($A31),'C.Pagar'!$K$2:$K$4509,">=01/03/2026",'C.Pagar'!$K$2:$K$4509,"<=31/03/2026") -> 1200 | Q31: =P31/P$3 -> 0.0011581709 | R31: =IFERROR(P31/M31-1,0) -> 0 | S31: =SUMIFS('C.Pagar'!$G$2:$G$4509,'C.Pagar'!$D$2:$D$4509,TRIM($A31),'C.Pagar'!$K$2:$K$4509,">=01/04/2026",'C.Pagar'!$K$2:$K$4509,"<=30/04/2026") -> 0 | T31: =S31/S$3 -> 0 | U31: =IFERROR(S31/P31-1,0) -> -1
A32: ADS SHOPEE | B32: =SUMIFS('C.Pagar'!G$2:G$4509,'C.Pagar'!D$2:D$4509,TRIM(A32),'C.Pagar'!K$2:K$4509,">=01/10/2025",'C.Pagar'!K$2:K$4509,"<=31/10/2025") -> 0 | C32: =B32/B$3 -> 0 | D32: =SUMIFS('C.Pagar'!G$2:G$4509,'C.Pagar'!D$2:D$4509,TRIM(A32),'C.Pagar'!K$2:K$4509,">=01/11/2025",'C.Pagar'!K$2:K$4509,"<=30/11/2025") -> 0 | E32: =D32/D$3 -> 0 | F32: =IFERROR(D32/B32-1,0) -> 0 | G32: =SUMIFS('C.Pagar'!G$2:G$4509,'C.Pagar'!D$2:D$4509,TRIM(A32),'C.Pagar'!K$2:K$4509,">=01/12/2025",'C.Pagar'!K$2:K$4509,"<=31/12/2025") -> 19000 | H32: =G32/G$3 -> 0.017407187 | I32: =IFERROR(G32/D32-1,0) -> 0 | J32: =SUMIFS('C.Pagar'!G$2:G$4509,'C.Pagar'!D$2:D$4509,TRIM(A32),'C.Pagar'!K$2:K$4509,">=01/01/2026",'C.Pagar'!K$2:K$4509,"<=31/01/2026") -> 4300 | K32: =J32/J$3 -> 0.0045598073 | L32: =IFERROR(J32/G32-1,0) -> -0.77368421 | M32: =SUMIFS('C.Pagar'!$G$2:$G$4509,'C.Pagar'!$D$2:$D$4509,TRIM($A32),'C.Pagar'!$K$2:$K$4509,">=01/02/2026",'C.Pagar'!$K$2:$K$4509,"<=28/02/2026") -> 6600 | N32: =M32/M$3 -> 0.0095410952 | O32: =IFERROR(M32/J32-1,0) -> 0.53488372 | P32: =SUMIFS('C.Pagar'!$G$2:$G$4509,'C.Pagar'!$D$2:$D$4509,TRIM($A32),'C.Pagar'!$K$2:$K$4509,">=01/03/2026",'C.Pagar'!$K$2:$K$4509,"<=31/03/2026") -> 10000 | Q32: =P32/P$3 -> 0.0096514241 | R32: =IFERROR(P32/M32-1,0) -> 0.51515152 | S32: =SUMIFS('C.Pagar'!$G$2:$G$4509,'C.Pagar'!$D$2:$D$4509,TRIM($A32),'C.Pagar'!$K$2:$K$4509,">=01/04/2026",'C.Pagar'!$K$2:$K$4509,"<=30/04/2026") -> 0 | T32: =S32/S$3 -> 0 | U32: =IFERROR(S32/P32-1,0) -> -1
A33: ADS TIKTOK | B33: =SUMIFS('C.Pagar'!G$2:G$4509,'C.Pagar'!D$2:D$4509,TRIM(A33),'C.Pagar'!K$2:K$4509,">=01/10/2025",'C.Pagar'!K$2:K$4509,"<=31/10/2025") -> 0 | C33: =B33/B$3 -> 0 | D33: =SUMIFS('C.Pagar'!G$2:G$4509,'C.Pagar'!D$2:D$4509,TRIM(A33),'C.Pagar'!K$2:K$4509,">=01/11/2025",'C.Pagar'!K$2:K$4509,"<=30/11/2025") -> 0 | E33: =D33/D$3 -> 0 | F33: =IFERROR(D33/B33-1,0) -> 0 | G33: =SUMIFS('C.Pagar'!G$2:G$4509,'C.Pagar'!D$2:D$4509,TRIM(A33),'C.Pagar'!K$2:K$4509,">=01/12/2025",'C.Pagar'!K$2:K$4509,"<=31/12/2025") -> 0 | H33: =G33/G$3 -> 0 | I33: =IFERROR(G33/D33-1,0) -> 0 | J33: =SUMIFS('C.Pagar'!G$2:G$4509,'C.Pagar'!D$2:D$4509,TRIM(A33),'C.Pagar'!K$2:K$4509,">=01/01/2026",'C.Pagar'!K$2:K$4509,"<=31/01/2026") -> 0 | K33: =J33/J$3 -> 0 | L33: =IFERROR(J33/G33-1,0) -> 0 | M33: =SUMIFS('C.Pagar'!$G$2:$G$4509,'C.Pagar'!$D$2:$D$4509,TRIM($A33),'C.Pagar'!$K$2:$K$4509,">=01/02/2026",'C.Pagar'!$K$2:$K$4509,"<=28/02/2026") -> 0 | N33: =M33/M$3 -> 0 | O33: =IFERROR(M33/J33-1,0) -> 0 | P33: =SUMIFS('C.Pagar'!$G$2:$G$4509,'C.Pagar'!$D$2:$D$4509,TRIM($A33),'C.Pagar'!$K$2:$K$4509,">=01/03/2026",'C.Pagar'!$K$2:$K$4509,"<=31/03/2026") -> 2000 | Q33: =P33/P$3 -> 0.0019302848 | R33: =IFERROR(P33/M33-1,0) -> 0 | S33: =SUMIFS('C.Pagar'!$G$2:$G$4509,'C.Pagar'!$D$2:$D$4509,TRIM($A33),'C.Pagar'!$K$2:$K$4509,">=01/04/2026",'C.Pagar'!$K$2:$K$4509,"<=30/04/2026") -> 0 | T33: =S33/S$3 -> 0 | U33: =IFERROR(S33/P33-1,0) -> -1
A34: REEMBOLSO SAC | B34: =SUMIFS('C.Pagar'!G$2:G$4509,'C.Pagar'!D$2:D$4509,TRIM(A34),'C.Pagar'!K$2:K$4509,">=01/10/2025",'C.Pagar'!K$2:K$4509,"<=31/10/2025") -> 409 | C34: =B34/B$3 -> 0.00036416569 | D34: =SUMIFS('C.Pagar'!G$2:G$4509,'C.Pagar'!D$2:D$4509,TRIM(A34),'C.Pagar'!K$2:K$4509,">=01/11/2025",'C.Pagar'!K$2:K$4509,"<=30/11/2025") -> 40 | E34: =D34/D$3 -> 4.0445285e-05 | F34: =IFERROR(D34/B34-1,0) -> -0.90220049 | G34: =SUMIFS('C.Pagar'!G$2:G$4509,'C.Pagar'!D$2:D$4509,TRIM(A34),'C.Pagar'!K$2:K$4509,">=01/12/2025",'C.Pagar'!K$2:K$4509,"<=31/12/2025") -> 699 | H34: =G34/G$3 -> 0.00064040123 | I34: =IFERROR(G34/D34-1,0) -> 16.475 | J34: =SUMIFS('C.Pagar'!G$2:G$4509,'C.Pagar'!D$2:D$4509,TRIM(A34),'C.Pagar'!K$2:K$4509,">=01/01/2026",'C.Pagar'!K$2:K$4509,"<=31/01/2026") -> 324.4 | K34: =J34/J$3 -> 0.00034400035 | L34: =IFERROR(J34/G34-1,0) -> -0.53590844 | M34: =SUMIFS('C.Pagar'!$G$2:$G$4509,'C.Pagar'!$D$2:$D$4509,TRIM($A34),'C.Pagar'!$K$2:$K$4509,">=01/02/2026",'C.Pagar'!$K$2:$K$4509,"<=28/02/2026") -> 3075 | N34: =M34/M$3 -> 0.004445283 | O34: =IFERROR(M34/J34-1,0) -> 8.4790382 | P34: =SUMIFS('C.Pagar'!$G$2:$G$4509,'C.Pagar'!$D$2:$D$4509,TRIM($A34),'C.Pagar'!$K$2:$K$4509,">=01/03/2026",'C.Pagar'!$K$2:$K$4509,"<=31/03/2026") -> 295 | Q34: =P34/P$3 -> 0.00028471701 | R34: =IFERROR(P34/M34-1,0) -> -0.90406504 | S34: =SUMIFS('C.Pagar'!$G$2:$G$4509,'C.Pagar'!$D$2:$D$4509,TRIM($A34),'C.Pagar'!$K$2:$K$4509,">=01/04/2026",'C.Pagar'!$K$2:$K$4509,"<=30/04/2026") -> 293 | T34: =S34/S$3 -> 0.00033156037 | U34: =IFERROR(S34/P34-1,0) -> -0.006779661
A35: (=) MARGEM DE CONTRIBUIÇÃO | B35: =B21-B22 -> 123831.3 | C35: =B35/B$3 -> 0.11025699 | D35: =D21-D22 -> -10751.92 | E35: =D35/D$3 -> -0.010871612 | F35: =IFERROR(D35/B35-1,0) -> -1.0868272 | G35: =G21-G22 -> 111663.51 | H35: =G35/G$3 -> 0.1023025 | I35: =IFERROR(G35/D35-1,0) -> -11.385448 | J35: =J21-J22 -> -55927.08 | K35: =J35/J$3 -> -0.059306211 | L35: =IFERROR(J35/G35-1,0) -> -1.5008537 | M35: =M21-M22 -> -82166.41 | N35: =M35/M$3 -> -0.11878144 | O35: =IFERROR(M35/J35-1,0) -> 0.46917039 | P35: =P21-P22 -> 252836.24 | Q35: =P35/P$3 -> 0.24402298 | R35: =IFERROR(P35/M35-1,0) -> -4.0771241 | S35: =S21-S22 -> 299461.49 | T35: =S35/S$3 -> 0.33887223 | U35: =IFERROR(S35/P35-1,0) -> 0.18440889
A36: (-) CUSTOS FIXOS OPERACIONAIS | B36: =B37+B42+B45+B69+B108+B113+B121+B123+B127-B129 -> 94036.07 | C36: =B36/B$3 -> 0.083727898 | D36: =D37+D42+D45+D69+D108+D113+D121+D123+D127-D129 -> 105279.79 | E36: =D36/D$3 -> 0.10645178 | F36: =IFERROR(D36/B36-1,0) -> 0.11956816 | G36: =G37+G42+G45+G69+G108+G113+G121+G123+G127-G129 -> 108655.94 | H36: =G36/G$3 -> 0.099547064 | I36: =IFERROR(G36/D36-1,0) -> 0.032068358 | J36: =J37+J42+J45+J69+J108+J113+J121+J123+J127-J129 -> 120407.84 | K36: =J36/J$3 -> 0.12768292 | L36: =IFERROR(J36/G36-1,0) -> 0.108157 | M36: =M37+M42+M45+M69+M108+M113+M121+M123+M127-M129 -> 104587.45 | N36: =M36/M$3 -> 0.15119376 | O36: =IFERROR(M36/J36-1,0) -> -0.13139003 | P36: =P37+P42+P45+P69+P108+P113+P121+P123+P127-P129 -> 152982.51 | Q36: =P36/P$3 -> 0.14764991 | R36: =IFERROR(P36/M36-1,0) -> 0.4627234 | S36: =S37+S42+S45+S69+S108+S113+S121+S123+S127-S129 -> 177611.11 | T36: =S36/S$3 -> 0.20098568 | U36: =IFERROR(S36/P36-1,0) -> 0.16098965
